Workbook

Sheet README
A1: India data centres: data register
A2: Everything gathered across the 12-report research series and the atlas, with verification status, intended use and what to derive. Built 8 Oct 2026.
A4: What is in this file
A5: Register | B5: One row per dataset (128 datasets): contents and key values, source, verification status, how to use it, what to derive from it, where it is used in the atlas, and the next step to verify or improve it.
A6: Summary | B6: Counts of datasets by report and verification status (live formulas).
A7: Verified figures | B7: Every individual figure confirmed against its source document during the research, with the link. Where it confirms or corrects a figure from an earlier report, that is noted.
A8: Conflicts | B8: Places where two of our sources disagree, which value to use now, and how to resolve it.
A9: Data gaps | B9: What is still missing, why it matters, and who to ask.
A10: Sources | B10: Source documents, with links where the research captured them.
A12: Verification status
A13: Verified | B13: Confirmed against the primary or authoritative document during the research run (Report 12 recorded this figure by figure). Every value in the row is confirmed unless the note says otherwise.
A14: Verified (secondary source) | B14: Confirmed through a secondary summary of the primary document (for example a news report of a tariff order). Good enough for analysis; check the primary before investment decisions.
A15: Partly verified | B15: Some values in the row are verified (named in the note), the rest are reported, estimated or modelled.
A16: Reported, not verified | B16: Taken from a named published source as cited in Reports 1–11, but not checked against the original document. Most of Reports 1–11 is in this category because those reports recorded sources without a verification step.
A17: Estimate / proxy | B17: Analyst estimate, engineering range, proxy or series judgement (for example rubric scores, design temperatures, substation distances).
A18: Model output | B18: Calculated by our own formulas from the inputs above (for example worked examples, forecasts, rankings). Only as good as its inputs.
A19: Unpublished / gap | B19: No public data exists; the value has to be requested from the owner.
A21: Important
A22: What "Verified" means here | B22: Verification was done during the research runs (mainly Report 12, which checked figures against source documents and labelled each one). Nothing was re-checked when this register was compiled. Where Report 12 later verified a figure first used in an earlier report, the earlier row says so and is marked Partly verified.
A23: Reports 1–9 | B23: The original nine reports are not stored as files in this workspace; their data is catalogued from the atlas, which carries each figure with its source and an evidence tag (reported / estimate / model).
A24: Columns to filter | B24: Use the filter on the Register header. "Verified?" is a formula (Yes / Partly / No) driven by the status column; change a status and it updates.
A26: Counts (live)
A27: Verified | B27: =COUNTIF(Register!$K$5:$K$132,A27) -> 4
A28: Verified (secondary source) | B28: =COUNTIF(Register!$K$5:$K$132,A28) -> 0
A29: Partly verified | B29: =COUNTIF(Register!$K$5:$K$132,A29) -> 31
A30: Reported, not verified | B30: =COUNTIF(Register!$K$5:$K$132,A30) -> 44
A31: Estimate / proxy | B31: =COUNTIF(Register!$K$5:$K$132,A31) -> 18
A32: Model output | B32: =COUNTIF(Register!$K$5:$K$132,A32) -> 30
A33: Unpublished / gap | B33: =COUNTIF(Register!$K$5:$K$132,A33) -> 1
A34: Total datasets | B34: =COUNTA(Register!$A$5:$A$132) -> 128
A35: Individually verified figures | B35: =COUNTA('Verified figures'!$B$5:$B$62) -> 58

Sheet Summary
A1: Summary by report and status
A2: Live counts from the Register.
A4: Report | B4: Verified | C4: Verified (secondary source) | D4: Partly verified | E4: Reported, not verified | F4: Estimate / proxy | G4: Model output | H4: Unpublished / gap | I4: Total | J4: Verified or partly
A5: R1 Types | B5: =COUNTIFS(Register!$B$5:$B$132,$A5,Register!$K$5:$K$132,B$4) -> 0 | C5: =COUNTIFS(Register!$B$5:$B$132,$A5,Register!$K$5:$K$132,C$4) -> 0 | D5: =COUNTIFS(Register!$B$5:$B$132,$A5,Register!$K$5:$K$132,D$4) -> 1 | E5: =COUNTIFS(Register!$B$5:$B$132,$A5,Register!$K$5:$K$132,E$4) -> 6 | F5: =COUNTIFS(Register!$B$5:$B$132,$A5,Register!$K$5:$K$132,F$4) -> 0 | G5: =COUNTIFS(Register!$B$5:$B$132,$A5,Register!$K$5:$K$132,G$4) -> 0 | H5: =COUNTIFS(Register!$B$5:$B$132,$A5,Register!$K$5:$K$132,H$4) -> 0 | I5: =SUM(B5:H5) -> 7 | J5: =SUM(B5:D5) -> 1
A6: R2 AI vs conventional | B6: =COUNTIFS(Register!$B$5:$B$132,$A6,Register!$K$5:$K$132,B$4) -> 0 | C6: =COUNTIFS(Register!$B$5:$B$132,$A6,Register!$K$5:$K$132,C$4) -> 0 | D6: =COUNTIFS(Register!$B$5:$B$132,$A6,Register!$K$5:$K$132,D$4) -> 4 | E6: =COUNTIFS(Register!$B$5:$B$132,$A6,Register!$K$5:$K$132,E$4) -> 4 | F6: =COUNTIFS(Register!$B$5:$B$132,$A6,Register!$K$5:$K$132,F$4) -> 1 | G6: =COUNTIFS(Register!$B$5:$B$132,$A6,Register!$K$5:$K$132,G$4) -> 0 | H6: =COUNTIFS(Register!$B$5:$B$132,$A6,Register!$K$5:$K$132,H$4) -> 0 | I6: =SUM(B6:H6) -> 9 | J6: =SUM(B6:D6) -> 4
A7: R3 Cooling | B7: =COUNTIFS(Register!$B$5:$B$132,$A7,Register!$K$5:$K$132,B$4) -> 0 | C7: =COUNTIFS(Register!$B$5:$B$132,$A7,Register!$K$5:$K$132,C$4) -> 0 | D7: =COUNTIFS(Register!$B$5:$B$132,$A7,Register!$K$5:$K$132,D$4) -> 1 | E7: =COUNTIFS(Register!$B$5:$B$132,$A7,Register!$K$5:$K$132,E$4) -> 5 | F7: =COUNTIFS(Register!$B$5:$B$132,$A7,Register!$K$5:$K$132,F$4) -> 3 | G7: =COUNTIFS(Register!$B$5:$B$132,$A7,Register!$K$5:$K$132,G$4) -> 0 | H7: =COUNTIFS(Register!$B$5:$B$132,$A7,Register!$K$5:$K$132,H$4) -> 0 | I7: =SUM(B7:H7) -> 9 | J7: =SUM(B7:D7) -> 1
A8: R4 Bengaluru | B8: =COUNTIFS(Register!$B$5:$B$132,$A8,Register!$K$5:$K$132,B$4) -> 0 | C8: =COUNTIFS(Register!$B$5:$B$132,$A8,Register!$K$5:$K$132,C$4) -> 0 | D8: =COUNTIFS(Register!$B$5:$B$132,$A8,Register!$K$5:$K$132,D$4) -> 0 | E8: =COUNTIFS(Register!$B$5:$B$132,$A8,Register!$K$5:$K$132,E$4) -> 7 | F8: =COUNTIFS(Register!$B$5:$B$132,$A8,Register!$K$5:$K$132,F$4) -> 0 | G8: =COUNTIFS(Register!$B$5:$B$132,$A8,Register!$K$5:$K$132,G$4) -> 1 | H8: =COUNTIFS(Register!$B$5:$B$132,$A8,Register!$K$5:$K$132,H$4) -> 0 | I8: =SUM(B8:H8) -> 8 | J8: =SUM(B8:D8) -> 0
A9: R5 Carbon | B9: =COUNTIFS(Register!$B$5:$B$132,$A9,Register!$K$5:$K$132,B$4) -> 0 | C9: =COUNTIFS(Register!$B$5:$B$132,$A9,Register!$K$5:$K$132,C$4) -> 0 | D9: =COUNTIFS(Register!$B$5:$B$132,$A9,Register!$K$5:$K$132,D$4) -> 3 | E9: =COUNTIFS(Register!$B$5:$B$132,$A9,Register!$K$5:$K$132,E$4) -> 4 | F9: =COUNTIFS(Register!$B$5:$B$132,$A9,Register!$K$5:$K$132,F$4) -> 1 | G9: =COUNTIFS(Register!$B$5:$B$132,$A9,Register!$K$5:$K$132,G$4) -> 3 | H9: =COUNTIFS(Register!$B$5:$B$132,$A9,Register!$K$5:$K$132,H$4) -> 0 | I9: =SUM(B9:H9) -> 11 | J9: =SUM(B9:D9) -> 3
A10: R6 Water impact | B10: =COUNTIFS(Register!$B$5:$B$132,$A10,Register!$K$5:$K$132,B$4) -> 0 | C10: =COUNTIFS(Register!$B$5:$B$132,$A10,Register!$K$5:$K$132,C$4) -> 0 | D10: =COUNTIFS(Register!$B$5:$B$132,$A10,Register!$K$5:$K$132,D$4) -> 2 | E10: =COUNTIFS(Register!$B$5:$B$132,$A10,Register!$K$5:$K$132,E$4) -> 1 | F10: =COUNTIFS(Register!$B$5:$B$132,$A10,Register!$K$5:$K$132,F$4) -> 0 | G10: =COUNTIFS(Register!$B$5:$B$132,$A10,Register!$K$5:$K$132,G$4) -> 5 | H10: =COUNTIFS(Register!$B$5:$B$132,$A10,Register!$K$5:$K$132,H$4) -> 0 | I10: =SUM(B10:H10) -> 8 | J10: =SUM(B10:D10) -> 2
A11: R7 Unit economics | B11: =COUNTIFS(Register!$B$5:$B$132,$A11,Register!$K$5:$K$132,B$4) -> 0 | C11: =COUNTIFS(Register!$B$5:$B$132,$A11,Register!$K$5:$K$132,C$4) -> 0 | D11: =COUNTIFS(Register!$B$5:$B$132,$A11,Register!$K$5:$K$132,D$4) -> 2 | E11: =COUNTIFS(Register!$B$5:$B$132,$A11,Register!$K$5:$K$132,E$4) -> 4 | F11: =COUNTIFS(Register!$B$5:$B$132,$A11,Register!$K$5:$K$132,F$4) -> 0 | G11: =COUNTIFS(Register!$B$5:$B$132,$A11,Register!$K$5:$K$132,G$4) -> 5 | H11: =COUNTIFS(Register!$B$5:$B$132,$A11,Register!$K$5:$K$132,H$4) -> 0 | I11: =SUM(B11:H11) -> 11 | J11: =SUM(B11:D11) -> 2
A12: R8 Green | B12: =COUNTIFS(Register!$B$5:$B$132,$A12,Register!$K$5:$K$132,B$4) -> 0 | C12: =COUNTIFS(Register!$B$5:$B$132,$A12,Register!$K$5:$K$132,C$4) -> 0 | D12: =COUNTIFS(Register!$B$5:$B$132,$A12,Register!$K$5:$K$132,D$4) -> 2 | E12: =COUNTIFS(Register!$B$5:$B$132,$A12,Register!$K$5:$K$132,E$4) -> 1 | F12: =COUNTIFS(Register!$B$5:$B$132,$A12,Register!$K$5:$K$132,F$4) -> 1 | G12: =COUNTIFS(Register!$B$5:$B$132,$A12,Register!$K$5:$K$132,G$4) -> 3 | H12: =COUNTIFS(Register!$B$5:$B$132,$A12,Register!$K$5:$K$132,H$4) -> 0 | I12: =SUM(B12:H12) -> 7 | J12: =SUM(B12:D12) -> 2
A13: R9 State policies | B13: =COUNTIFS(Register!$B$5:$B$132,$A13,Register!$K$5:$K$132,B$4) -> 0 | C13: =COUNTIFS(Register!$B$5:$B$132,$A13,Register!$K$5:$K$132,C$4) -> 0 | D13: =COUNTIFS(Register!$B$5:$B$132,$A13,Register!$K$5:$K$132,D$4) -> 1 | E13: =COUNTIFS(Register!$B$5:$B$132,$A13,Register!$K$5:$K$132,E$4) -> 4 | F13: =COUNTIFS(Register!$B$5:$B$132,$A13,Register!$K$5:$K$132,F$4) -> 1 | G13: =COUNTIFS(Register!$B$5:$B$132,$A13,Register!$K$5:$K$132,G$4) -> 0 | H13: =COUNTIFS(Register!$B$5:$B$132,$A13,Register!$K$5:$K$132,H$4) -> 0 | I13: =SUM(B13:H13) -> 6 | J13: =SUM(B13:D13) -> 1
A14: Simulator (R1–R9 synthesis) | B14: =COUNTIFS(Register!$B$5:$B$132,$A14,Register!$K$5:$K$132,B$4) -> 0 | C14: =COUNTIFS(Register!$B$5:$B$132,$A14,Register!$K$5:$K$132,C$4) -> 0 | D14: =COUNTIFS(Register!$B$5:$B$132,$A14,Register!$K$5:$K$132,D$4) -> 1 | E14: =COUNTIFS(Register!$B$5:$B$132,$A14,Register!$K$5:$K$132,E$4) -> 0 | F14: =COUNTIFS(Register!$B$5:$B$132,$A14,Register!$K$5:$K$132,F$4) -> 0 | G14: =COUNTIFS(Register!$B$5:$B$132,$A14,Register!$K$5:$K$132,G$4) -> 1 | H14: =COUNTIFS(Register!$B$5:$B$132,$A14,Register!$K$5:$K$132,H$4) -> 0 | I14: =SUM(B14:H14) -> 2 | J14: =SUM(B14:D14) -> 1
A15: R10 Where to build | B15: =COUNTIFS(Register!$B$5:$B$132,$A15,Register!$K$5:$K$132,B$4) -> 0 | C15: =COUNTIFS(Register!$B$5:$B$132,$A15,Register!$K$5:$K$132,C$4) -> 0 | D15: =COUNTIFS(Register!$B$5:$B$132,$A15,Register!$K$5:$K$132,D$4) -> 4 | E15: =COUNTIFS(Register!$B$5:$B$132,$A15,Register!$K$5:$K$132,E$4) -> 4 | F15: =COUNTIFS(Register!$B$5:$B$132,$A15,Register!$K$5:$K$132,F$4) -> 1 | G15: =COUNTIFS(Register!$B$5:$B$132,$A15,Register!$K$5:$K$132,G$4) -> 2 | H15: =COUNTIFS(Register!$B$5:$B$132,$A15,Register!$K$5:$K$132,H$4) -> 1 | I15: =SUM(B15:H15) -> 12 | J15: =SUM(B15:D15) -> 4
A16: R11 Forecast | B16: =COUNTIFS(Register!$B$5:$B$132,$A16,Register!$K$5:$K$132,B$4) -> 0 | C16: =COUNTIFS(Register!$B$5:$B$132,$A16,Register!$K$5:$K$132,C$4) -> 0 | D16: =COUNTIFS(Register!$B$5:$B$132,$A16,Register!$K$5:$K$132,D$4) -> 4 | E16: =COUNTIFS(Register!$B$5:$B$132,$A16,Register!$K$5:$K$132,E$4) -> 4 | F16: =COUNTIFS(Register!$B$5:$B$132,$A16,Register!$K$5:$K$132,F$4) -> 5 | G16: =COUNTIFS(Register!$B$5:$B$132,$A16,Register!$K$5:$K$132,G$4) -> 5 | H16: =COUNTIFS(Register!$B$5:$B$132,$A16,Register!$K$5:$K$132,H$4) -> 0 | I16: =SUM(B16:H16) -> 18 | J16: =SUM(B16:D16) -> 4
A17: R12 Water & energy | B17: =COUNTIFS(Register!$B$5:$B$132,$A17,Register!$K$5:$K$132,B$4) -> 4 | C17: =COUNTIFS(Register!$B$5:$B$132,$A17,Register!$K$5:$K$132,C$4) -> 0 | D17: =COUNTIFS(Register!$B$5:$B$132,$A17,Register!$K$5:$K$132,D$4) -> 6 | E17: =COUNTIFS(Register!$B$5:$B$132,$A17,Register!$K$5:$K$132,E$4) -> 0 | F17: =COUNTIFS(Register!$B$5:$B$132,$A17,Register!$K$5:$K$132,F$4) -> 5 | G17: =COUNTIFS(Register!$B$5:$B$132,$A17,Register!$K$5:$K$132,G$4) -> 5 | H17: =COUNTIFS(Register!$B$5:$B$132,$A17,Register!$K$5:$K$132,H$4) -> 0 | I17: =SUM(B17:H17) -> 20 | J17: =SUM(B17:D17) -> 10
A18: Total | B18: =SUM(B5:B17) -> 4 | C18: =SUM(C5:C17) -> 0 | D18: =SUM(D5:D17) -> 31 | E18: =SUM(E5:E17) -> 44 | F18: =SUM(F5:F17) -> 18 | G18: =SUM(G5:G17) -> 30 | H18: =SUM(H5:H17) -> 1 | I18: =SUM(I5:I17) -> 128 | J18: =SUM(J5:J17) -> 35
A20: Reading it
A21: Report 12 is the only report that verified figures one by one. Earlier reports cited named sources without a verification step, so their rows are "Reported" unless Report 12 later confirmed the same figure. Model outputs and estimates are expected: they are our calculations and judgements, labelled as such.

Sheet Register
A1: Dataset register
A2: One row per dataset. Status colours follow the README legend. Filter on any column.
A4: ID | B4: Report | C4: Theme | D4: Dataset | E4: What it contains (key values) | F4: Unit | G4: Geography | H4: As of | I4: Source(s) | J4: Link | K4: Verification status | L4: Verified? | M4: Verification note | N4: How to use it | O4: What to derive from it | P4: Used in (atlas) | Q4: Next step to verify or improve
A5: R1-01 | B5: R1 Types | C5: Market size | D5: Global data-centre capacity | E5: ~103 GW (2025) → ~200 GW (2030), ~14% CAGR | F5: GW (IT) | G5: Global | H5: Jan 2026 | I5: JLL global outlook, Jan 2026 | K5: Reported, not verified | L5: =IF(K5="Partly verified","Partly",IF(LEFT(K5,8)="Verified","Yes","No")) -> No | M5: Cited by name in Report 1; not checked against the JLL document. | N5: Global benchmark for India's scale and growth rate. | O5: India's share of global capacity (1.79 GW ÷ ~103 GW ≈ 1.7%); compare India's ~25% growth with the global 14%. | P5: Ch 1 headline; Key numbers | Q5: Check against JLL report text.
A6: R1-02 | B6: R1 Types | C6: Market structure | D6: Ownership mix of global capacity | E6: Hyperscale 41% (2024), 44% (2025), 48% (2026), ~67% (2031 proj.); colocation 22/22/20/14%; enterprise on-prem 37/34/32/19%; enterprise 56% in 2018. 20 metros hold 60% of hyperscale; N. Virginia 11%. | F6: % of capacity | G6: Global | H6: Apr 2026 | I6: Synergy Research Group | K6: Reported, not verified | L6: =IF(K6="Partly verified","Partly",IF(LEFT(K6,8)="Verified","Yes","No")) -> No | M6: 2031 is a Synergy projection. | N6: Shows where demand is moving (hyperscale and wholesale colo, away from enterprise rooms). | O6: Expected Indian demand mix by business model; justify wholesale/hyperscale campuses as the build priority. | P6: Ch 1 "Who owns the world's capacity" chart | Q6: Confirm against Synergy release.
A7: R1-03 | B7: R1 Types | C7: Business models | D7: Six data-centre business models | E7: Enterprise <1–20 MW; retail colo 1 rack–1 MW; wholesale/BTS 10–100+ MW; hyperscale 30 MW–1 GW+; AI factory 50 MW–5 GW; edge 50 kW–5 MW. Self-build ~13–27% cheaper than leasing in India; >20 MW sites PUE ~1.44. | F7: MW bands | G7: Global / India | H7: 2026 | I7: Report 1 synthesis (industry sources); PUE 1.44 for >20 MW from Uptime 2025 | K7: Partly verified | L7: =IF(K7="Partly verified","Partly",IF(LEFT(K7,8)="Verified","Yes","No")) -> Partly | M7: PUE 1.44 for >20 MW sites verified in Report 12 (Uptime 2025); size bands and self-build saving are series estimates. | N7: Classify any project; feeds the Type finder. | O7: Which model fits a given size/workload; expected PUE and cost band per type. | P7: Ch 1 Type explorer and Type finder | Q7: Source the 13–27% self-build saving.
A8: R1-04 | B8: R1 Types | C8: Reliability | D8: Uptime Tier availability targets | E8: Tier I 99.671%, Tier II 99.741%, Tier III 99.982% (1.6 h/yr), Tier IV 99.995%; ANSI/TIA-942 Rated 1–4. | F8: % availability | G8: Global standard | H8: Current | I8: Uptime Institute Tier Standard | K8: Reported, not verified | L8: =IF(K8="Partly verified","Partly",IF(LEFT(K8,8)="Verified","Yes","No")) -> No | M8: Standard design targets; not re-checked. | N8: Set reliability level per workload. | O8: Allowed downtime = (1 − availability) × 8,760 h; Tier III is the Indian commercial norm. | P8: Ch 1 Tier clock | Q8: —
A9: R1-05 | B9: R1 Types | C9: India market | D9: India operational and pipeline capacity by city | E9: Operational / upcoming MW: Mumbai 890/1,726; Chennai 214/368; Delhi NCR 183/387; Bengaluru 162/100; Hyderabad 151/710; Pune 133/258; Kolkata 22/84. Total 1,789 MW operational; pipeline 3,860 MW (509 under construction, 3,351 planned); 147 facilities, 33 providers; vacancy 14.9%. | F9: MW (IT) | G9: India, 7 markets | H9: H1 2026 (press release 16 Sep 2026) | I9: Cushman & Wakefield India Data Centre H1 2026 Update | K9: Reported, not verified | L9: =IF(K9="Partly verified","Partly",IF(LEFT(K9,8)="Verified","Yes","No")) -> No | M9: Press release figures cited in Reports 1, 10 and 11; city sum (3,633 MW) is 227 MW short of the 3,860 MW total, unexplained. | N9: Anchor for every capacity number in the atlas: market share, pipeline and the forecast starting point. | O9: City shares (Mumbai 49.7%); pipeline-to-stock ratios (Hyderabad 4.7×); forecast base C₀ = 1,789 − 178 = 1,611 MW for end-2025. | P9: Ch 1 city chart; Ch 9 map; Ch 10 demand scores; Ch 11 forecast | Q9: Obtain the full C&W report; reconcile the 227 MW gap.
A10: R1-06 | B10: R1 Types | C10: Connectivity | D10: Subsea cable landings and bandwidth concentration | E10: 17–18 international cables at 14–15 landing stations in 5 cities (Mumbai, Chennai, Kochi, Thoothukudi, Thiruvananthapuram); 15 of 17 land within ~6 km of Versova; ~95% of international bandwidth via Mumbai; Chennai 8 cables (JLL); new: SEA-ME-WE 6 Chennai, Google Vizag gateway (3 paths), Meta Waterworth, Jio Digha (unconfirmed). | F10: Count / % | G10: India | H10: 2026 | I10: Report 1 and Report 10 (TeleGeography-style sources, JLL, Google, Meta announcements) | K10: Reported, not verified | L10: =IF(K10="Partly verified","Partly",IF(LEFT(K10,8)="Verified","Yes","No")) -> No | M10: The 95% bandwidth share is a series figure without a primary citation. | N10: Connectivity factor in site ranking; concentration-risk argument. | O10: Connectivity scores per city; case for east-coast landings; latency to cable heads. | P10: Ch 1; Ch 10 connectivity scores | Q10: Confirm counts on TeleGeography Submarine Cable Map.
A11: R1-07 | B11: R1 Types | C11: Investment | D11: Announced hyperscale and AI investments in India | E11: Google ≈US$15 bn (1 GW AI hub, Vizag); Microsoft US$17.5 bn; Amazon US$35 bn+ by 2030; Reliance up to 3 GW Jamnagar; Adani ≈US$100 bn by 2035; TCS HyperVault 1 GW+. | F11: US$ bn / GW | G11: India | H11: 2025–26 | I11: Company announcements (Report 1) | K11: Reported, not verified | L11: =IF(K11="Partly verified","Partly",IF(LEFT(K11,8)="Verified","Yes","No")) -> No | M11: Announcements, not built capacity. | N11: Upside scenarios and pipeline outside C&W's 7 markets. | O11: Apply 0.2–0.5 conversion to announced capacity (Report 11) to get expected MW. | P11: Ch 1 callout; Ch 11 extra-campus slider | Q11: Track commissioning, not announcements.
A12: R2-01 | B12: R2 AI vs conventional | C12: Energy | D12: Global data-centre electricity | E12: 415 TWh (2024) → 945 TWh (2030) base; >1,260 TWh high case; ~1,200 TWh (2035). IEA 2026 update: 485 → 950 TWh. US and China ~80% of growth. | F12: TWh/yr | G12: Global | H12: Apr 2025 / 2026 update | I12: IEA, Energy and AI (Apr 2025) and 2026 update | K12: Reported, not verified | L12: =IF(K12="Partly verified","Partly",IF(LEFT(K12,8)="Verified","Yes","No")) -> No | M12: Two IEA vintages differ for 2024 (415 vs 485 TWh). | N12: Global context for India's electricity path. | O12: India's share of global DC electricity (base 2030: 35 TWh ÷ 945 ≈ 3.7%). | P12: Ch 2 chart; Ch 11 context; Key numbers | Q12: Use the 2026 update consistently.
A13: R2-02 | B13: R2 AI vs conventional | C13: Energy | D13: AI share of server electricity | E13: AI servers 24% of server electricity (2024); AI growing ~30%/yr vs ~9% for conventional servers. | F13: % / %/yr | G13: Global | H13: 2025 | I13: IEA, Energy and AI | K13: Reported, not verified | L13: =IF(K13="Partly verified","Partly",IF(LEFT(K13,8)="Verified","Yes","No")) -> No | N13: Explains why AI dominates new demand. | O13: AI share of new Indian capacity assumptions (40% → 70% of new builds in Report 11). | P13: Ch 2 headline | Q13: —
A14: R2-03 | B14: R2 AI vs conventional | C14: Energy per workload | D14: Energy per query and per training run | E14: Gemini median text prompt 0.24 Wh and 0.26 mL water (May 2025); ChatGPT avg ~0.34 Wh (Jun 2025); Google search ~0.3 Wh (2009); GPT-4o 500 tokens ~0.3 Wh; 10k/100k-token inputs 2.5/40 Wh; Llama 3.1 405B ≤21.6 GWh (30.84 M H100-hours); GPT-4 training ~50–62 GWh (unofficial). | F14: Wh / GWh | G14: Global | H14: 2009–2025 | I14: Google (arXiv 2508.15734), OpenAI (Altman), Epoch AI, Meta | J14: Open source | K14: Partly verified | L14: =IF(K14="Partly verified","Partly",IF(LEFT(K14,8)="Verified","Yes","No")) -> Partly | M14: Gemini figures verified (Report 12, GOOG25); ChatGPT 0.34 Wh verified via secondary source; others reported or unofficial estimates. | N14: Per-query footprint comparisons and explainer. | O14: Water per prompt in India = Wh × (site WUE + grid water); daily load of a service (1 bn messages ≈ 12.5 MW). | P14: Ch 2 table; Ch 6 and Ch 12 prompt charts | Q14: —
A15: R2-04 | B15: R2 AI vs conventional | C15: Hardware | D15: Rack density and GPU system power | E15: Enterprise modal ~7–9 kW; air practical ~20 kW; active RDHx ~60 kW; GB200/GB300 NVL72 120–142 kW (HPE 132 kW nominal); Vera Rubin ~190–230 kW (industry estimate); Kyber ~600 kW (2027). DGX H100 10.2 kW; DGX B200 14.3 kW max. | F15: kW per rack / system | G15: Global | H15: 2025–27 | I15: Nvidia specifications and GTC roadmap; LBNL 2024; NVIDIA DGX B200 guide | J15: Open source | K15: Partly verified | L15: =IF(K15="Partly verified","Partly",IF(LEFT(K15,8)="Verified","Yes","No")) -> Partly | M15: DGX B200 14.3 kW and DGX H100 10.2 kW verified (Report 12); NVL72 ~120 kW verified via secondary source; Rubin figures are estimates. | N15: Design density for cooling and power chain. | O15: Racks per MW (1,000 ÷ kW); GPUs per MW; per-GPU energy (NVL72: 18.2 MWh/yr at PUE 1.25). | P15: Ch 2 rack inspector; Ch 12 energy | Q15: Confirm Rubin specs when published.
A16: R2-05 | B16: R2 AI vs conventional | C16: Energy split | D16: Facility electricity split by class | E16: IT / cooling / power losses / other (%): legacy PUE~1.9 52/35/10/3; enterprise-colo ~1.55 64/27/7/2; hyperscale ~1.15 88/7.5/3.5/1; AI liquid ~1.2 84/11/4.5/0.5. | F16: % of facility energy | G16: Generic | H16: 2025 | I16: Series synthesis from PUE ranges and IEA component shares | K16: Estimate / proxy | L16: =IF(K16="Partly verified","Partly",IF(LEFT(K16,8)="Verified","Yes","No")) -> No | M16: Indicative. | N16: Explain where non-IT energy goes. | O16: Cooling energy per MW; savings from cooling upgrades. | P16: Ch 2 chart; simulator overhead split | Q16: —
A17: R2-06 | B17: R2 AI vs conventional | C17: Power chain | D17: Power-chain conversion losses | E17: Transformer 1–2%; UPS 2–8%; PDU/busway 1–3%; server PSU 4–10%. UPS efficiency: edge 77–85%, colo 80–94%, hyperscale/AI 90–99%. 800 VDC (Kyber, 2027) removes stages. | F17: % loss | G17: Generic | H17: 2024–26 | I17: Industry ranges; LBNL 2024 for UPS efficiency | J17: Open source | K17: Partly verified | L17: =IF(K17="Partly verified","Partly",IF(LEFT(K17,8)="Verified","Yes","No")) -> Partly | M17: UPS efficiency ranges verified (Report 12, LBNL); stage losses are typical ranges. | N17: PUE build-up and electrical design. | O17: Loss share of PUE; benefit of high-efficiency UPS / DC distribution. | P17: Ch 2 power chain; simulator losses | Q17: —
A18: R2-07 | B18: R2 AI vs conventional | C18: Grid reliability | D18: AI load swings and grid events | E18: NERC: 10 Jul 2024, ~1,500 MW of DC load disconnected (60 load points, 25 substations); ~1,800 MW load loss Feb 2025; ~1,260 MW did not return for hours; one site 450 → 40 MW in 36 s; NERC Level 3 alert 4 May 2026. | F18: MW | G18: USA (Virginia) | H18: 2024–26 | I18: NERC/FERC large-loads presentation; POWER; Keentel; NERC alert | J18: Open source | K18: Partly verified | L18: =IF(K18="Partly verified","Partly",IF(LEFT(K18,8)="Verified","Yes","No")) -> Partly | M18: 1,500 MW and 1,800 MW events verified (Report 12); 1,260 MW and 450→40 MW via secondary sources; Level 3 alert reported. | N18: Argue for ride-through and ramp-rate clauses in Indian connection agreements. | O18: Required BESS/UPS ride-through for >100 MW AI loads. | P18: Ch 2 load profiles; Ch 12 Example C | Q18: —
A19: R2-08 | B19: R2 AI vs conventional | C19: India AI compute | D19: IndiaAI Mission and Indian AI build-out | E19: IndiaAI Mission ₹10,372 cr; 38,231 GPUs onboarded across 14 providers (Mar 2026), avg ≈₹65/GPU-hr subsidised; ~20,000 more announced. Yotta NM1 52 MW, 8,192 H100; Reliance Jamnagar up to 3 GW, 120 MW+ H2 2026, Meta lease ~168 MW; Sify DGX-Ready 130 kW/rack, then 200 kW/rack. | F19: ₹ cr / GPUs / MW | G19: India | H19: Mar 2026 | I19: PIB (Mar 2026); company announcements | K19: Reported, not verified | L19: =IF(K19="Partly verified","Partly",IF(LEFT(K19,8)="Verified","Yes","No")) -> No | N19: Size of public AI compute; anchor-tenant evidence. | O19: IndiaAI GPUs ≈ 40–55 MW of IT (≈3% of national capacity) at 1.0–1.4 kW/GPU. | P19: Ch 2 India build-out; Ch 7 GPU prices; Ch 11 | Q19: Track PIB updates.
A20: R2-09 | B20: R2 AI vs conventional | C20: Design comparison | D20: Conventional vs AI data-centre attributes | E20: Density 5–15 vs 120–142 → 600 kW; capex JLL shell ≈US$11.3 m/MW + up to US$25 m/MW AI fit-out; India ₹50–55 vs up to ₹75 cr/MW; training sites 300 MW–5 GW, inference 10–200 MW; GPU economic life 3–6 years (contested). | F20: mixed | G20: Global / India | H20: 2025–26 | I20: JLL, SBI (Apr 2026), Report 2 synthesis | K20: Reported, not verified | L20: =IF(K20="Partly verified","Partly",IF(LEFT(K20,8)="Verified","Yes","No")) -> No | M20: GPU life and some ranges contested. | N20: Planning differences between AI and cloud campuses. | O20: Siting rule: train near power, serve inference near users. | P20: Ch 2 tables | Q20: —
A21: R3-01 | B21: R3 Cooling | C21: Physics | D21: Heat-carrying capacity of coolants | E21: kJ/m³·K: air 1.2; dielectric oil 1,750; two-phase (sensible) 1,850; PG25 4,000; water 4,180. 100 kW at 10 K rise needs ~8 m³/s air vs 2.4 L/s water. | F21: kJ/m³·K | G21: Physics | H21: — | I21: Standard physical properties | K21: Reported, not verified | L21: =IF(K21="Partly verified","Partly",IF(LEFT(K21,8)="Verified","Yes","No")) -> No | M21: Textbook values. | N21: Explain why liquid cooling wins at high density. | O21: Flow rates for a given heat load (Q = ρ·cp·V·ΔT). | P21: Ch 3 chart | Q21: —
A22: R3-02 | B22: R3 Cooling | C22: Design limits | D22: Practical rack-density limits by cooling method | E22: Perimeter air 15 kW; air + containment 30; active RDHx 70; direct-to-chip and immersion ~250 kW per rack; air stops being practical at 20–40 kW. | F22: kW per rack | G22: Generic | H22: 2026 | I22: Report 3 synthesis (vendor and ASHRAE guidance) | K22: Estimate / proxy | L22: =IF(K22="Partly verified","Partly",IF(LEFT(K22,8)="Verified","Yes","No")) -> No | N22: Choose in-room cooling for a target density. | O22: Which halls are stranded by a density jump; retrofit needs. | P22: Ch 3 cooling selector | Q22: —
A23: R3-03 | B23: R3 Cooling | C23: Heat rejection | D23: Heat-rejection options: water and energy | E23: WUE L/kWh: open tower + water-cooled chiller 1.4–2.5; adiabatic 0.1–0.5; hybrid/thermosyphon 0.5–0.7; dry + air-cooled chiller ~0 (+5–15% energy); DLC at W40–W45 + dry 0–0.1; seawater ~0 freshwater. | F23: L/kWh IT | G23: Generic, India fit | H23: 2026 | I23: Report 3 synthesis; consistent with Report 12 table and LBNL ranking | K23: Estimate / proxy | L23: =IF(K23="Partly verified","Partly",IF(LEFT(K23,8)="Verified","Yes","No")) -> No | M23: Ranges consistent with Report 12 (proxy) and NTT evaporative 1.42–2.93 (verified). | N23: Pick heat rejection by water stress and climate. | O23: Site WUE for calculators; water cut from switching designs. | P23: Ch 3 table; simulator WUE functions | Q23: Replace with metered operator data when disclosed.
A24: R3-04 | B24: R3 Cooling | C24: Liquid cooling | D24: Liquid-cooling technologies compared | E24: 1-phase DLC 50–250 kW+, 70–98% heat to liquid, PUE 1.05–1.20; 2-phase DLC 100–300 kW, PUE 1.04–1.15; 1-phase immersion 100–250 kW/tank, PUE 1.03–1.08; 2-phase immersion 200 kW+, PUE 1.01–1.05 (PFAS risk; 3M exited end-2025). | F24: kW / PUE | G24: Global | H24: 2026 | I24: Vendor and industry reports (Report 3) | K24: Reported, not verified | L24: =IF(K24="Partly verified","Partly",IF(LEFT(K24,8)="Verified","Yes","No")) -> No | M24: Reported PUEs are vendor claims. | N24: Technology choice for AI halls. | O24: PUE and WUE inputs for liquid-cooled cases. | P24: Ch 3 table | Q24: —
A25: R3-05 | B25: R3 Cooling | C25: Market | D25: Liquid-cooling market size | E25: Manufacturer revenue US$1.5 bn (2024) → ~3 bn (2025) → ~7 bn (2029); DLC US$1.1 bn (2024) → 5.8 bn (2029), +156% YoY Q2 2025; India US$113 m (2026) → 790 m (2031). 26–50% of projects use liquid for AI (Turner & Townsend). | F25: US$ | G25: Global / India | H25: Jan 2026 | I25: Dell'Oro Group; MarketsandMarkets; Turner & Townsend | K25: Reported, not verified | L25: =IF(K25="Partly verified","Partly",IF(LEFT(K25,8)="Verified","Yes","No")) -> No | N25: Evidence for fast adoption of liquid cooling. | O25: Bass diffusion parameters (q ≫ p) for the liquid/dry share in Report 11. | P25: Ch 3 chart; Ch 11 water model | Q25: —
A26: R3-06 | B26: R3 Cooling | C26: Market | D26: Cooling-sector M&A 2024–26 | E26: Eaton–Boyd Thermal US$9.5 bn; Ecolab–CoolIT US$4.75 bn; Vertiv–PurgeRite ~US$1 bn; Schneider–Motivair US$0.85 bn; Trane–LiquidStack (undisclosed). ~US$16 bn total. | F26: US$ bn | G26: Global | H26: 2024–26 | I26: Company announcements | K26: Reported, not verified | L26: =IF(K26="Partly verified","Partly",IF(LEFT(K26,8)="Verified","Yes","No")) -> No | N26: Supply-chain and lock-in risk argument. | O26: Procurement advice: insist on open interfaces (OCP UQD, CDU controls). | P26: Ch 3 | Q26: —
A27: R3-07 | B27: R3 Cooling | C27: Regulation | D27: India HFC phase-down under Kigali Amendment | E27: Baseline 2024–26; freeze 1 Jan 2028; −10% 2032; −20% 2037; −30% 2042; −85% 2047. | F27: Dates / % cut | G27: India | H27: 2016 amendment | I27: Kigali Amendment to the Montreal Protocol (India: Group 2) | K27: Reported, not verified | L27: =IF(K27="Partly verified","Partly",IF(LEFT(K27,8)="Verified","Yes","No")) -> No | N27: Refrigerant choice for chillers bought now. | O27: Specify low-GWP refrigerants (R-1234ze, R-513A, R-32) or chiller-free designs. | P27: Ch 3; Key numbers | Q27: —
A28: R3-08 | B28: R3 Cooling | C28: Climate | D28: City design temperatures (cooling chapter and simulator) | E28: Design dry-bulb / wet-bulb °C: Bengaluru 35/23; Hyderabad 41/26; Pune 39/25; Mumbai 35/28; Chennai 38/29; Visakhapatnam 36/28; Delhi NCR 45/29. | F28: °C | G28: 7 Indian cities | H28: 2026 | I28: Indicative 0.4% summer conditions (series estimate) | K28: Estimate / proxy | L28: =IF(K28="Partly verified","Partly",IF(LEFT(K28,8)="Verified","Yes","No")) -> No | M28: Not station data. Report 10 has a separate DB/WB list for 50 cities (also estimates). | N28: Decide which heat-rejection option can meet a facility water temperature. | O28: Free-cooling hours, chiller need at peak, PUE by city. | P28: Ch 3 warm-water explorer; simulator; Ch 4 day model | Q28: Replace with ISHRAE/ASHRAE station design data.
A29: R3-09 | B29: R3 Cooling | C29: Operator practice | D29: Hyperscaler and Indian cooling deployments | E29: Microsoft: zero-water-evaporation designs since Aug 2024, avoiding >125 million L/yr per site; Google Vizag hub air-cooled heat rejection; Meta air-assisted liquid; AWS in-row HX (Jul 2025). India: NTT NAV1 4.8 MW immersion; Sify 130–200 kW/rack; Yotta RDHx 50–60 kW, DLC 80 kW; leading operators PUE 1.4–1.5; MeitY tenders PUE <1.35; Schneider/Motivair factory Bengaluru, Vertiv Pune. | F29: mixed | G29: Global / India | H29: 2024–26 | I29: Company statements; Microsoft blog (Dec 2024) | J29: Open source | K29: Partly verified | L29: =IF(K29="Partly verified","Partly",IF(LEFT(K29,8)="Verified","Yes","No")) -> Partly | M29: Microsoft 125 million L/yr verified (Report 12); others reported. | N29: Benchmarks for what is achievable now. | O29: Target PUE/WUE for new Indian builds. | P29: Ch 3 | Q29: —
A30: R4-01 | B30: R4 Bengaluru | C30: City water | D30: Bengaluru water supply (BWSSB) | E30: ~1,935 MLD delivered of 2,225 MLD capacity; Cauvery Stage V ~485 of 775 MLD; industrial tariff ₹99/kL; STP capacity ~1,348.5 MLD, only ~30 MLD reused commercially at ₹10–20/kL. | F30: MLD, ₹/kL | G30: Bengaluru | H30: Aug 2026 | I30: Karnataka Legislative Council reply (Aug 2026); BWSSB tariff | K30: Reported, not verified | L30: =IF(K30="Partly verified","Partly",IF(LEFT(K30,8)="Verified","Yes","No")) -> No | N30: Denominator for data-centre water shares; water price in calculators. | O30: DC share of city supply (50 MW evaporative ≈ 0.09%); treated-water opportunity. | P30: Ch 4, Ch 6, simulator, Ch 11 city water | Q30: —
A31: R4-02 | B31: R4 Bengaluru | C31: Groundwater | D31: Bengaluru groundwater extraction | E31: Bengaluru Urban extraction 1,457 MLD (2024) from ~600 MLD (2020); every taluk over-exploited; Bangalore East ~305% (2024 assessment), Devanahalli 169%; Bangalore East sustainable groundwater ~45 MLD (series estimate). | F31: % stage of extraction; MLD | G31: Bengaluru taluks | H31: 2024 | I31: Karnataka dynamic groundwater assessment 2024 | K31: Reported, not verified | L31: =IF(K31="Partly verified","Partly",IF(LEFT(K31,8)="Verified","Yes","No")) -> No | M31: Conflicts with Report 10 (Bangalore East 395% in IN-GRES 2025-26, secondary compilation). See Conflicts tab. | N31: Water hard filter and scarcity weighting. | O31: Share of local sustainable groundwater a site would take (50 MW evaporative ≈ 4%). | P31: Ch 4, Ch 6, Ch 10 filter | Q31: Verify on IN-GRES portal.
A32: R4-03 | B32: R4 Bengaluru | C32: DC water use | D32: Bengaluru data-centre water use today | E32: Estimates (MLD): DTE permitted volumes ~2.2; Karnataka IT dept (32 DCs) ~4; series model mixed cooling 4–5; all-evaporative ~8.8; WELL Labs heuristic ~20. BWSSB billing 129,000 L/month for five centres on shared meters; KSPCB cannot quantify. | F32: MLD | G32: Bengaluru | H32: 2025–26 | I32: Down To Earth; Karnataka IT department; WELL Labs; series model | K32: Reported, not verified | L32: =IF(K32="Partly verified","Partly",IF(LEFT(K32,8)="Verified","Yes","No")) -> No | M32: Fivefold spread; nobody meters it. | N32: Shows the disclosure gap. | O32: Range for sector water; case for mandatory metering. | P32: Ch 4 chart | Q32: Request metered data from BWSSB/KSPCB.
A33: R4-04 | B33: R4 Bengaluru | C33: Water stress event | D33: March 2024 borewell failure | E33: 6,997 of 14,781 public borewells failed (47%) after a weak 2023 monsoon; BWSSB banned non-essential potable use; tanker prices capped. | F33: count / % | G33: Bengaluru | H33: Mar 2024 | I33: BWSSB / press reports | K33: Reported, not verified | L33: =IF(K33="Partly verified","Partly",IF(LEFT(K33,8)="Verified","Yes","No")) -> No | N33: Summer stress test for water supply. | O33: Tanker trips and storage days needed in a 2024-style summer. | P33: Ch 6 "Water you can picture" stress test | Q33: —
A34: R4-05 | B34: R4 Bengaluru | C34: Power | D34: Karnataka electricity denominators | E34: Karnataka demand ~93,000 MU/yr; household use ~16,089 MU/yr; a Bengaluru home ~1,800 kWh/yr. | F34: MU | G34: Karnataka | H34: FY25 | I34: Report 4 (state energy statistics) | K34: Reported, not verified | L34: =IF(K34="Partly verified","Partly",IF(LEFT(K34,8)="Verified","Yes","No")) -> No | N34: Express campus energy as share of state demand and homes. | O34: 100 MW AI campus ≈ 841 MU ≈ 5% of household use. | P34: Ch 4 calculator; simulator | Q34: Confirm with KERC/CEA state data.
A35: R4-06 | B35: R4 Bengaluru | C35: Grid connection | D35: KERC supply voltage by contract demand | E35: ≤20 MVA 66 kV; ≤35 MVA (55 MVA since June 2025 if feasible) 110 kV; >20 MVA 220 kV dual circuit; 300 MW+ campuses 400 kV. | F35: MVA / kV | G35: Karnataka | H35: 2025 | I35: KERC conditions of supply (as reported) | K35: Reported, not verified | L35: =IF(K35="Partly verified","Partly",IF(LEFT(K35,8)="Verified","Yes","No")) -> No | N35: Size the grid connection. | O35: Contract MVA = MW × (PUE + 0.12) ÷ 0.95; voltage class. | P35: Ch 4; simulator grid connection | Q35: Check KERC supply code text.
A36: R4-07 | B36: R4 Bengaluru | C36: Comparators | D36: Other water users in Karnataka | E36: MLD: JSW Vijayanagar 330 (allocation); Raichur TPS ~130; 10 m sq ft IT campus ~6; Toyota Bidadi 4.7; brewery 1.7; 1,000-flat apartments 0.61; 500-bed hospital 0.23. | F36: MLD | G36: Karnataka | H36: 2025–26 | I36: Report 4 (company and allocation data; some estimates) | K36: Reported, not verified | L36: =IF(K36="Partly verified","Partly",IF(LEFT(K36,8)="Verified","Yes","No")) -> No | M36: Mix of allocations and estimates. | N36: Put data-centre water in context. | O36: Rank DC water among industrial users. | P36: Ch 4 comparison chart | Q36: —
A37: R4-08 | B37: R4 Bengaluru | C37: Model | D37: Bengaluru campus central cases | E37: 20 MW colo ~178 MU/yr, ~33 MVA, 0.60 MLD on site; 50 MW hyperscale evaporative ~1.47 MLD; 100 MW AI ~841 MU/yr, ~140 MVA, 0.13 MLD; 1 GW target all-evaporative ~32 MLD (~1% of supply). | F37: MU, MVA, MLD | G37: Bengaluru | H37: 2026 | I37: Report 4 calculations | K37: Model output | L37: =IF(K37="Partly verified","Partly",IF(LEFT(K37,8)="Verified","Yes","No")) -> No | N37: Default cases in calculators. | O37: Energy, connection and water per campus size. | P37: Ch 4 calculator; Key numbers | Q37: —
A38: R5-01 | B38: R5 Carbon | C38: Grid carbon | D38: India grid emission factor (CEA) | E38: Weighted average incl. RE, tCO₂/MWh: FY14 0.774; FY21 0.703; FY23 0.716; FY24 0.727; FY25 0.710 (1,234.19 Mt ÷ 1,739.06 BU). | F38: tCO₂/MWh | G38: India | H38: Nov 2025 (v21) | I38: CEA CO₂ Baseline Database User Guide v21 | K38: Partly verified | L38: =IF(K38="Partly verified","Partly",IF(LEFT(K38,8)="Verified","Yes","No")) -> Partly | M38: FY14 and FY25 verified in Report 12; intermediate years reported in Report 11. | N38: Carbon for every calculator. | O38: CO₂ = facility MWh × EF × (1 − clean share); CUE = PUE × EF; ~0.77 at the meter with ~8% losses. | P38: All calculators; Ch 5; Ch 11 carbon | Q38: —
A39: R5-02 | B39: R5 Carbon | C39: Grid carbon | D39: Carbon of 1 TWh by supply type | E39: Mt CO₂ per TWh: India grid avg incl. losses 0.77; Karnataka mix 0.54; marginal coal evening 1.09; 24/7 RE + battery (90% CFE) 0.11; gas CCGT 0.49; France 0.045; Norway 0.025; nuclear 0.009. | F39: Mt/TWh | G39: Various | H39: 2026 | I39: Report 5 comparison across CEA, Ember, IPCC | K39: Model output | L39: =IF(K39="Partly verified","Partly",IF(LEFT(K39,8)="Verified","Yes","No")) -> No | N39: Show that where/when/what you buy matters more than efficiency. | O39: Carbon range for procurement choices. | P39: Ch 5 chart | Q39: —
A40: R5-03 | B40: R5 Carbon | C40: Grid profile | D40: Indian grid hourly fossil profile | E40: Fossil generation ~174 GW at 7 pm vs ~125 GW at 1 pm (H1 2026); Ember India average 670 g/kWh (2025). | F40: GW; g/kWh | G40: India | H40: H1 2026 | I40: Ember (Global Electricity Review 2026, India data) | K40: Reported, not verified | L40: =IF(K40="Partly verified","Partly",IF(LEFT(K40,8)="Verified","Yes","No")) -> No | N40: Case for shifting load to solar hours. | O40: Evening vs solar-hour intensity gap. | P40: Ch 5 headline | Q40: —
A41: R5-04 | B41: R5 Carbon | C41: Grid profile | D41: Karnataka hourly carbon curve (illustrative) | E41: Average intensity by hour 215–610 gCO₂/kWh (low at 13:00, high at 20:00); marginal unit coal 980 (1,080 at 18–22 h). Third-party dashboard 90-day range ~210–603 g. | F41: gCO₂/kWh | G41: Karnataka | H41: 2026 | I41: Modelled third-party dashboard (Report 5) | K41: Model output | L41: =IF(K41="Partly verified","Partly",IF(LEFT(K41,8)="Verified","Yes","No")) -> No | M41: No official hourly or marginal factor exists for India. | N41: Hourly carbon in the 24-hour Bengaluru day and load-shift calculator. | O41: CO₂ saved per MWh shifted (~0.30 t/MWh evening → solar). | P41: Ch 4 day model; Ch 5 load shift | Q41: Ask CEA to publish hourly/marginal factors.
A42: R5-05 | B42: R5 Carbon | C42: Lifecycle | D42: Lifecycle carbon by generation source | E42: gCO₂e/kWh (IPCC AR5 medians): coal 820, gas CCGT 490, solar PV 48, hydro 24, nuclear 12, wind 11. Indian coal units actual 900–1,100. | F42: gCO₂e/kWh | G42: Global | H42: 2014 | I42: IPCC AR5 Annex III; UNECE LCA | K42: Reported, not verified | L42: =IF(K42="Partly verified","Partly",IF(LEFT(K42,8)="Verified","Yes","No")) -> No | N42: Compare power sources beyond operational emissions. | O42: Lifecycle CUE for procurement options. | P42: Ch 5 chart | Q42: —
A43: R5-06 | B43: R5 Carbon | C43: Grid carbon | D43: Karnataka consumption-mix intensity | E43: ~0.50 tCO₂/MWh (consumption basis). | F43: tCO₂/MWh | G43: Karnataka | H43: 2025 | I43: Series estimate | K43: Estimate / proxy | L43: =IF(K43="Partly verified","Partly",IF(LEFT(K43,8)="Verified","Yes","No")) -> No | M43: Contested; no official state factor. | N43: State-specific carbon in Bengaluru cases. | O43: Karnataka CUE (PUE 1.5 → 0.75 kg/IT-kWh). | P43: Ch 5; Key numbers | Q43: —
A44: R5-07 | B44: R5 Carbon | C44: Projection | D44: NEP emission-factor path | E44: 0.548 (2026-27) → 0.430 (2031-32) kg/kWh net; draft 0.524 / 0.441. Already ~0.15 off track given FY25 = 0.710. | F44: tCO₂/MWh | G44: India | H44: NEP 2022-32 | I44: National Electricity Plan 2022-32 (CEA) | K44: Reported, not verified | L44: =IF(K44="Partly verified","Partly",IF(LEFT(K44,8)="Verified","Yes","No")) -> No | N44: Upper bound for grid decarbonisation. | O44: Fast EF scenario in the forecast (NEP delayed ~4 years). | P44: Ch 11 carbon | Q44: —
A45: R5-08 | B45: R5 Carbon | C45: Corporate reporting | D45: Location vs market-based emissions | E45: Microsoft Scope 2 location-based 4.33 → 9.96 Mt (FY20 → FY24, +130%); market-based 0.456 → 0.259 Mt (−43%). Google 66% hourly CFE globally (2024), 12% in Asia-Pacific. Google +18%, Microsoft +25% emissions growth despite 100% annual RE matching. | F45: Mt CO₂e; % | G45: Global | H45: 2024 | I45: Microsoft and Google sustainability reports | K45: Reported, not verified | L45: =IF(K45="Partly verified","Partly",IF(LEFT(K45,8)="Verified","Yes","No")) -> No | N45: Show why annual RE matching is not enough. | O45: Case for hourly CFE targets and dual Scope 2 reporting. | P45: Ch 5 chart; Ch 8 | Q45: —
A46: R5-09 | B46: R5 Carbon | C46: Water by source | D46: Water consumed per MWh by generation source | E46: L/MWh: coal tower (India actual) ~3,400; CSP wet tower ~3,250; nuclear tower ~2,600; gas CCGT ~850; solar PV 20–100; wind ~0. CSE: ~half of non-seawater coal capacity broke 3.5 m³/MWh; Raichur 87% over. | F46: L/MWh | G46: India / global | H46: 2024–26 | I46: CSE; NREL; CEA research | K46: Partly verified | L46: =IF(K46="Partly verified","Partly",IF(LEFT(K46,8)="Verified","Yes","No")) -> Partly | M46: Coal 2.8–3.4 m³/MWh, nuclear 2.54 L/kWh and the 3.5 m³/MWh norm verified in Report 12; CSP and Raichur reported. | N46: Power-station (indirect) water in calculators. | O46: Indirect water = facility kWh × source intensity. | P46: Ch 5; Ch 6; Ch 12 | Q46: —
A47: R5-10 | B47: R5 Carbon | C47: Framework | D47: Five-factor scorecard | E47: Weights: carbon 30%, water 25%, source 20%, timing 15%, location 10%; each scored 1–5; ≥4 leading, ≥3 improving. | F47: weights | G47: Framework | H47: 2026 | I47: Report 5 framework | K47: Model output | L47: =IF(K47="Partly verified","Partly",IF(LEFT(K47,8)="Verified","Yes","No")) -> No | M47: Our framework, not an external standard. | N47: Score a site or power contract. | O47: Weighted 1–5 score per option. | P47: Ch 5 scorecard | Q47: —
A48: R5-11 | B48: R5 Carbon | C48: Tariff timing | D48: Time-of-day tariff rules | E48: India ToD rules: ≥20% off in solar hours, ≥20% extra at peak. Telangana FY26 HT: +₹1.00 at 06–10 and 18–22 h, −₹1.50 at 22–06 h. Maharashtra HT ToD 25%, solar-hour rebate from −15%. | F48: % / ₹ per unit | G48: India; TG; MH | H48: 2023–FY26 | I48: Electricity (Rights of Consumers) ToD rules; TGERC; MERC | J48: Open source | K48: Partly verified | L48: =IF(K48="Partly verified","Partly",IF(LEFT(K48,8)="Verified","Yes","No")) -> Partly | M48: Telangana and Maharashtra ToD verified (Report 12); national rule reported. | N48: Price signal for load shifting. | O48: Saving from shifting MWh into solar hours. | P48: Ch 5 load shift; Ch 12 hourly | Q48: —
A49: R6-01 | B49: R6 Water impact | C49: Model | D49: 50 MW evaporative water balance | E49: At 80% load (350.4 GWh IT): evaporation 504.6 ML/yr; at CoC 5 withdrawal 646.6 ML (1.77 MLD, peak ~2.4), consumption 508.7 ML (1.39 MLD); WUE 1.85 withdrawal / 1.45 consumption; drift 1.2 ML; non-cooling 14.6 ML; RO recovery 75%. | F49: ML/yr; L/kWh | G49: Bengaluru 50 MW case | H49: 2026 | I49: Report 6 model | K49: Model output | L49: =IF(K49="Partly verified","Partly",IF(LEFT(K49,8)="Verified","Yes","No")) -> No | N49: Separate withdrawal, consumption and discharge. | O49: Effect of CoC, RO and ZLD on what is drawn vs evaporated. | P49: Ch 6 water balance | Q49: —
A50: R6-02 | B50: R6 Water impact | C50: Model | D50: Monthly withdrawal profile (50 MW evaporative) | E50: MLD by month: Jan 1.5, Feb 1.68, Mar 2.04, Apr 2.3, May 2.3, Jun 1.77, Jul 1.59, Aug 1.59, Sep 1.68, Oct 1.68, Nov 1.5, Dec 1.5. | F50: MLD | G50: Bengaluru | H50: 2026 | I50: Report 6 model | K50: Model output | L50: =IF(K50="Partly verified","Partly",IF(LEFT(K50,8)="Verified","Yes","No")) -> No | N50: Seasonal peaks coincide with tanker scarcity. | O50: Peak ÷ average; storage sizing. | P50: Ch 6 season chart | Q50: Calibrate with metered data.
A51: R6-03 | B51: R6 Water impact | C51: Model | D51: Scarcity-weighted water footprint scenarios | E51: Mm³-eq/yr, on site + off site: A evaporative on Bangalore East groundwater 50.9 + 34.2; B potable 30.5 + 34.2; C treated + RO 15.3 + 34.2; D dry + grid 1.1 + 38.1; E dry + RE PPA 1.1 + 2.5. Impact scores 4.6 (refuse) … 1.9 (preferred). | F51: Mm³-eq | G51: Bengaluru 50 MW | H51: 2026 | I51: Report 6 model with AWARE-style factors | K51: Model output | L51: =IF(K51="Partly verified","Partly",IF(LEFT(K51,8)="Verified","Yes","No")) -> No | M51: Weights illustrative; rankings hold, absolute values do not. | N51: Compare water impact, not just litres. | O51: Dry cooling cuts footprint ~54%; adding RE ~96%. | P51: Ch 6 charts and scorecard | Q51: Use AWARE / Aqueduct factors per catchment.
A52: R6-04 | B52: R6 Water impact | C52: Model | D52: Bengaluru scenario WUEs | E52: Site / source WUE: S1 20 MW colo evaporative 1.80 / 3.90; S2 50 MW evaporative CoC 5 1.85 / 3.80; S3 50 MW dry 0.05 / 2.23; S4 100 MW AI DLC + adiabatic 0.13 / 1.86. Also L per H100-hour and mL per prompt. | F52: L/kWh | G52: Bengaluru | H52: 2026 | I52: Report 6 model | K52: Model output | L52: =IF(K52="Partly verified","Partly",IF(LEFT(K52,8)="Verified","Yes","No")) -> No | N52: Show indirect water dominates for dry sites. | O52: Water per GPU-hour and per prompt. | P52: Ch 6 table | Q52: —
A53: R6-05 | B53: R6 Water impact | C53: Water per prompt | D53: Water per AI prompt, by boundary | E53: mL: Bengaluru DLC site only 0.03; Gemini on-site 0.26; DLC site + grid 0.5–0.9; same site on coal ~2; GPT-3 India case 19.7 (Li et al.); Mistral Large 2 full LCA 45. | F53: mL | G53: Various | H53: 2023–25 | I53: Google; Li et al. (UCR, ACM); Mistral LCA; Report 6 model | J53: Open source | K53: Partly verified | L53: =IF(K53="Partly verified","Partly",IF(LEFT(K53,8)="Verified","Yes","No")) -> Partly | M53: Gemini 0.26 mL and Li et al. 19.7 mL verified (Report 12); Mistral reported; Bengaluru values model. | N53: Explain boundary choices. | O53: Per-prompt water for Indian sites. | P53: Ch 6 and Ch 12 charts | Q53: —
A54: R6-06 | B54: R6 Water impact | C54: Framework | D54: Water thresholds and disclosure metrics | E54: Green/amber/red: site consumption WUE ≤0.2 / 0.2–1.0 / >1.0; groundwater for cooling in over-exploited taluk 0% / — / >0%; withdrawal ÷ taluk recharge <0.5% / 0.5–1% / >1%; peak ÷ average <1.5 / 1.5–3 / >3; source WUE <1.0 / 1.0–2.5 / >2.5. Seven monthly metrics to publish. | F54: thresholds | G54: Proposed | H54: 2026 | I54: Report 6 proposal | K54: Model output | L54: =IF(K54="Partly verified","Partly",IF(LEFT(K54,8)="Verified","Yes","No")) -> No | M54: Our proposed thresholds, not regulation. | N54: Screen sites and set permit conditions. | O54: Traffic-light rating for any site. | P54: Ch 6 | Q54: —
A55: R6-07 | B55: R6 Water impact | C55: Disclosure | D55: Operator water disclosure status | E55: Nxtra and CtrlS publish no WUE; CtrlS total water 409,037 kL (2023-24) vs 468,330 kL (2022-23); Yotta claims "extremely low WUE" with no number; Sify's reported withdrawal fell 20× in a year unexplained; NTT omitted water in 2025; AdaniConneX has no standalone report. | F55: kL | G55: India operators | H55: 2025 | I55: Down To Earth; company reports | J55: Open source | K55: Partly verified | L55: =IF(K55="Partly verified","Partly",IF(LEFT(K55,8)="Verified","Yes","No")) -> Partly | M55: DTE findings and CtrlS volumes verified (Report 12); Sify/NTT/AdaniConneX points reported. | N55: Evidence of the disclosure gap. | O55: Case for Karnataka-style mandatory PUE/WUE reporting. | P55: Ch 6; Ch 12 | Q55: Collect BRSR filings.
A56: R6-08 | B56: R6 Water impact | C56: Everyday units | D56: Water conversion norms | E56: 135 L per person per day (CPHEEO); 12,000 L tanker; Olympic pool 2.5 ML. | F56: L | G56: India | H56: — | I56: CPHEEO manual; common norms | K56: Reported, not verified | L56: =IF(K56="Partly verified","Partly",IF(LEFT(K56,8)="Verified","Yes","No")) -> No | N56: Turn ML into people, tankers, pools. | O56: People-equivalent of a site's water. | P56: Ch 6 water you can picture; Ch 12 calculator | Q56: —
A57: R7-01 | B57: R7 Unit economics | C57: Build cost | D57: Global construction cost index | E57: US$/W (air-cooled): Tokyo 15.2, Singapore 14.5, Zurich 14.2, Silicon Valley 13.3, New Jersey 12.9, Oslo 12.4, London 12.0, Frankfurt 11.6, Atlanta 9.9, Phoenix 9.8, Charlotte 9.5, Mumbai 6.64 (51st of 52; ₹589/W). Inflation +5.5% (2025), +9.0% (2024). | F57: US$/W | G57: Global | H57: 2025 | I57: Turner & Townsend Data Centre Cost Index 2025 | K57: Reported, not verified | L57: =IF(K57="Partly verified","Partly",IF(LEFT(K57,8)="Verified","Yes","No")) -> No | N57: Benchmark Indian capex. | O57: Mumbai ≈ ₹58.4 cr/MW base for the forecast cost path. | P57: Ch 7 chart; Ch 11 costs | Q57: —
A58: R7-02 | B58: R7 Unit economics | C58: Build cost | D58: Capex stacks for three cases | E58: ₹ cr/MW: A 20 MW Tier III colo — land 5, shell 8.5, electrical 22, cooling 10, backup 4.2, fire/BMS/network 3, soft/contingency/IDC 8.4 → 56.1 excl. land (61.1 incl.). B 50 MW hyperscale BTS 39.2 excl. land (~42 incl.). C 100 MW AI facility 72.5 + GPUs ~266 → ~340 incl. GPUs. | F58: ₹ cr/MW | G58: India | H58: 2026 | I58: Report 7 bottom-up model | K58: Model output | L58: =IF(K58="Partly verified","Partly",IF(LEFT(K58,8)="Verified","Yes","No")) -> No | M58: Consistent with T&T Mumbai US$6.64/W and SBI ₹50–55 cr/MW. | N58: Default capex in simulator and LCOD. | O58: Capex per case, per rack, per GPU. | P58: Ch 7; simulator | Q58: Benchmark against actual project disclosures.
A59: R7-03 | B59: R7 Unit economics | C59: Build cost | D59: Indian build-cost data points | E59: SBI: Tier III air ₹50–55 cr/MW, AI/Tier IV up to ₹75; ICRA ~₹47 cr/MW (₹50–55k cr for ~1,100 MW) and ₹62–70 (₹2.0–2.3 lakh cr for 3.0–3.5 GW); C&W ~₹69 (US$29.9 bn for 3,860 MW); Jefferies US$4–5 m/MW; C&W APAC guide US$5.9–9.0 m/MW (secondary); CareEdge ~₹54, costs up 50–70%; US AI premium ×1.7–2.0. | F59: ₹ cr/MW | G59: India | H59: 2024–26 | I59: SBI (Apr 2026); ICRA; C&W; Jefferies; CareEdge; Quartz | K59: Reported, not verified | L59: =IF(K59="Partly verified","Partly",IF(LEFT(K59,8)="Verified","Yes","No")) -> No | M59: C&W APAC guide seen via a secondary source. | N59: Cross-check capex model; Wright's-law test. | O59: Implied learning exponent b ≈ −0.66 (costs rising with volume). | P59: Ch 7; Ch 11 cost path | Q59: —
A60: R7-04 | B60: R7 Unit economics | C60: Opex | D60: Colo opex breakdown (Case A) | E60: ₹ cr/yr: electricity 129; maintenance 15.3; SG&A 15; personnel 7.5; insurance 2.2; DG fuel & testing 1.5; property tax 1.5; network 1; water & chemicals 1 → ~174. | F60: ₹ cr/yr | G60: 20 MW colo | H60: 2026 | I60: Report 7 model | K60: Model output | L60: =IF(K60="Partly verified","Partly",IF(LEFT(K60,8)="Verified","Yes","No")) -> No | N60: Show power dominates colo opex. | O60: Opex per MW; power share of cost (39%). | P60: Ch 7 chart | Q60: —
A61: R7-05 | B61: R7 Unit economics | C61: Levelised cost | D61: LCOD and break-even rent | E61: Case A LCOD ₹29.7 per IT-kWh (electricity ₹11.7, 39%); break-even ₹13,647/kW-month incl. power; sensitivities: utilisation 22–35, capex ±10% 28.3–31.1, PUE 1.35/1.65 28.5–30.9, tariff ±₹1 28.2–31.2, WACC 10/12% 28.8–30.6. | F61: ₹/IT-kWh | G61: 20 MW colo | H61: 2026 | I61: Report 7 model | K61: Model output | L61: =IF(K61="Partly verified","Partly",IF(LEFT(K61,8)="Verified","Yes","No")) -> No | N61: Price a colo deal. | O61: CRF = r(1+r)ⁿ/((1+r)ⁿ−1); break-even rent; which lever matters most (utilisation). | P61: Ch 7 calculator and tornado; simulator | Q61: —
A62: R7-06 | B62: R7 Unit economics | C62: Returns | D62: Returns by business model | E62: Colo: capex ₹61 cr/MW, EBITDA 42%, payback 9.6 yrs, IRR ~9.5%, power 39% of cost. Hyperscale BTS: ₹42 cr, 84% of rent, 7.1 yrs, ~14.7%, 48%. AI neocloud: ₹340 cr, 90%, 3.2 yrs, 21.5% → negative, ~6%. | F62: % / years | G62: India | H62: 2026 | I62: Report 7 model | K62: Model output | L62: =IF(K62="Partly verified","Partly",IF(LEFT(K62,8)="Verified","Yes","No")) -> No | N62: Compare investment cases. | O62: Which model earns its cost of capital. | P62: Ch 7 table | Q62: —
A63: R7-07 | B63: R7 Unit economics | C63: Rents and markets | D63: Rents, cap rates and power cost: India vs US vs Singapore | E63: Build US$/W 6.64 / 9.5–13.3 / 14.5; rent US$/kW/month 80–100 / 160–225 / 300–475; electricity US$ m/MW/yr 0.7–0.9 / ~1.22 / ~1.7; cap rate 7.5–8.5% / 4.5–6.5% / 5.0–6.5%. Mumbai 1–5 MW colo rent ₹6,500–8,000/kW/month. Nxtra raise (Mar 2026) ≈US$7 m per operating MW. | F63: US$; ₹/kW-month | G63: India, US, Singapore | H63: 2025–26 | I63: Cushman & Wakefield; CBRE; JLL; press | K63: Reported, not verified | L63: =IF(K63="Partly verified","Partly",IF(LEFT(K63,8)="Verified","Yes","No")) -> No | N63: Market pricing check for LCOD. | O63: Spread between break-even and market rent. | P63: Ch 7 table; simulator | Q63: —
A64: R7-08 | B64: R7 Unit economics | C64: GPU economics | D64: GPU-hour market prices | E64: ₹/GPU-hr (H100-class, Oct 2026): IndiaAI L1 150 (users ~92 after subsidy; L1 standard ₹115.85); JarvisLabs 218; OCPI-H100 US$2.79 ≈251; E2E 255.55; Yotta ~269 dedicated / 356 on-demand; Neysa 395 on-demand, ~219 on 36-month; Cyfuture 219; hyperscalers 540–1,080. Global H100 peak ~US$8 (early 2024); SemiAnalysis US$1.70 (Oct 2025) → 2.35 (early 2026); contract prices +~40% Oct 2025–Mar 2026. | F64: ₹ or US$ per GPU-hour | G64: India / global | H64: Oct 2026 | I64: IndiaAI tenders; provider price lists; SemiAnalysis; Neysa; OCPI index | K64: Reported, not verified | L64: =IF(K64="Partly verified","Partly",IF(LEFT(K64,8)="Verified","Yes","No")) -> No | M64: Trade press and price pages; prices move monthly. | N64: Benchmark the GPU-hour cost model. | O64: Break-even utilisation; GPU price decline path (base −20%/yr). | P64: Ch 7 GPU chart; Ch 11 GPU path | Q64: Re-scrape prices quarterly.
A65: R7-09 | B65: R7 Unit economics | C65: GPU economics | D65: GPU cost model inputs and result | E65: HGX capex: H100 ~US$275k per 8, H200 ~315k, B200 ~450k; kW per GPU incl. server 1.4 (H100/H200), 2.0 (B200); PUE 1.35; colo ₹7,000/kW-month; ₹70k/yr ops; life 5 yrs; WACC 11%. Result: H100 ≈ ₹178/GPU-hr at 80% use; break-even 96% vs IndiaAI ₹150, 55% vs E2E ₹255.55. GB300 rack price contested US$3.7–6.5 m. | F65: ₹/GPU-hr | G65: India | H65: 2026 | I65: Report 7 model; market prices for hardware | K65: Model output | L65: =IF(K65="Partly verified","Partly",IF(LEFT(K65,8)="Verified","Yes","No")) -> No | M65: Hardware prices are estimates. | N65: Rent vs own decision. | O65: Cost per GPU-hour at any utilisation; renting beats owning below ~55%. | P65: Ch 7 GPU calculator | Q65: —
A66: R7-10 | B66: R7 Unit economics | C66: Land | D66: Land prices by hub | E66: ₹ cr/acre: Navi Mumbai 15–40 (in-fill ~80); MIDC TTC base ₹31,390/m² (≈₹12.7 cr/acre), market ₹45,000–60,000/m², STT paid ₹282 cr for 14,093 m² incl. building (May 2026); Taloja ₹12,100/m²; Chennai Ambattur 8–15, Oragadam 3–8; Hyderabad 2–6; Bengaluru Devanahalli/Hoskote 4–10 (estimate); YEIDA residential ₹36,260/m² (2026). Land is 4–8% of capex. | F66: ₹ cr/acre | G66: India hubs | H66: 2026 | I66: MIDC rates; transactions; Report 7 and Report 10 | K66: Partly verified | L66: =IF(K66="Partly verified","Partly",IF(LEFT(K66,8)="Verified","Yes","No")) -> Partly | M66: MIDC and YEIDA rates reported with named sources; Bengaluru figure is an estimate. | N66: Land line in capex. | O66: Land share of capex by city. | P66: Ch 7; simulator land | Q66: Get industrial DC rates for YEIDA.
A67: R7-11 | B67: R7 Unit economics | C67: Power price | D67: Grid HT tariffs used in Reports 7 and simulator | E67: Energy + demand: Karnataka ₹6.70 + ₹365/kVA; Maharashtra ₹7.27 + ₹560; Tamil Nadu ₹7.50 + ₹608; Telangana ₹6.65 + ₹500 (FY2025–26 orders). UP ₹7.4, AP ₹7.2 (not verified). RTC renewable SECI tranche V ₹5.25–5.26 at bus. | F67: ₹/kWh; ₹/kVA-month | G67: 6 states | H67: FY2025–26 | I67: State commission tariff orders | K67: Partly verified | L67: =IF(K67="Partly verified","Partly",IF(LEFT(K67,8)="Verified","Yes","No")) -> Partly | M67: Telangana verified and TN verified-secondary in Report 12. Karnataka (Report 12 verified 660 paise + ₹345) and Maharashtra (₹7.48 + ₹555 FY26) differ — see Conflicts. | N67: Power cost in simulator and LCOD. | O67: Annual power bill; RE saving vs grid (₹0.8–1.5/kWh in MH/TN). | P67: Simulator; Ch 7 | Q67: Update simulator to Report 12 verified rates.
A68: R8-01 | B68: R8 Green | C68: Framework | D68: Twelve dimensions of a green data centre | E68: Targets: PUE ≤1.30 air / ≤1.20 liquid AI; hourly CFE ≥70–80%, CUE ≤0.3; freshwater WUE ≤0.2; embodied carbon −30–40%; ≥90% assets reused; low-GWP refrigerants; diesel run-hours tracked; flexible MW; public disclosure. | F68: targets | G68: India-calibrated | H68: 2026 | I68: Report 8 framework | K68: Model output | L68: =IF(K68="Partly verified","Partly",IF(LEFT(K68,8)="Verified","Yes","No")) -> No | M68: Our framework. | N68: Define "green" for Indian sites. | O68: Checklist for design and procurement. | P68: Ch 8 grid | Q68: —
A69: R8-02 | B69: R8 Green | C69: Model | D69: Green upgrade, 20 MW Bengaluru colo | E69: Capex premium ₹60 cr; savings ₹35.5 cr/yr (efficiency 24.5, RE 9.2); payback 2.3 yrs; CO₂ avoided ~108,843 t/yr (83%); freshwater saved ~196 ML/yr; abatement −₹2,536/t. Inputs: PUE 1.50 → 1.25, 80% hourly RE, grid ₹8.00 vs RE ₹7.25, water ₹90/kL. | F69: ₹ cr; t; ML | G69: Bengaluru 20 MW | H69: 2026 | I69: Report 8 model | K69: Model output | L69: =IF(K69="Partly verified","Partly",IF(LEFT(K69,8)="Verified","Yes","No")) -> No | N69: Business case for green design. | O69: Payback and marginal abatement cost. | P69: Ch 8 calculator; Key numbers | Q69: —
A70: R8-03 | B70: R8 Green | C70: Model | D70: Abatement cost by measure | E70: ₹/tCO₂: efficiency + water −8,450; RE at ₹0.75 discount −1,060; full package −2,540; RE at ₹0.50 premium +700. India carbon credit price ~₹955/t (expected initial); EU ETS ~€84/t. | F70: ₹/tCO₂ | G70: Bengaluru 20 MW | H70: 2026 | I70: Report 8 model; carbon prices reported | K70: Model output | L70: =IF(K70="Partly verified","Partly",IF(LEFT(K70,8)="Verified","Yes","No")) -> No | M70: Carbon prices are reported context. | N70: Rank green measures. | O70: Which measures pay for themselves. | P70: Ch 8 MAC chart | Q70: —
A71: R8-04 | B71: R8 Green | C71: Regulation | D71: PUE and green thresholds worldwide | E71: EU A–G grades from Aug 2027 (A: PUE ≤1.15, WUE ≤0.10), EED reporting ≥500 kW; Germany EnEfG new sites PUE ≤1.2 from Jul 2026, 100% RE from 2027; Singapore 2026: PUE 1.25, ≥50% green; China new large DCs ≤1.25 (hubs ≤1.2, ≥80% RE); MeitY tenders <1.35; Karnataka ₹20 cr for ≤1.20; global average 1.54. | F71: PUE | G71: Global | H71: 2024–27 | I71: EU Delegated Reg. 2024/1364; EnEfG; IMDA; China MIIT; MeitY; Uptime | J71: Open source | K71: Partly verified | L71: =IF(K71="Partly verified","Partly",IF(LEFT(K71,8)="Verified","Yes","No")) -> Partly | M71: EU reporting rule verified; EU rating scheme verified via secondary source; Uptime 1.54 verified (Report 12); others reported. | N71: Benchmark Indian targets. | O71: Gap between Indian practice (1.4–1.5) and leading rules. | P71: Ch 8 chart | Q71: —
A72: R8-05 | B72: R8 Green | C72: Clean power | D72: Clean-power routes and landed cost | E72: ₹/kWh landed: rooftop 3–4 (<2–5% of load); group captive 5.5–7; third-party OA 6.5–8; ISTS hybrid 5–6.5 + charges; SECI RTC/FDRE ~5.25 + delivery; unbundled RECs +0.1–0.3. KERC 2025 banking: monthly, 8% charge in kind. | F72: ₹/kWh | G72: India | H72: 2026 | I72: Report 8 synthesis; SECI; KERC | K72: Partly verified | L72: =IF(K72="Partly verified","Partly",IF(LEFT(K72,8)="Verified","Yes","No")) -> Partly | M72: SECI ₹5.25 verified (Report 12). Report 12 refines landed costs: group captive ₹6.5–7.5, third-party ISTS ₹8.5–10 with surcharges — see Conflicts. | N72: Choose a procurement route. | O72: Blended power price; carbon and water by route. | P72: Ch 8 table; simulator RE price | Q72: Use Report 12 landed-cost build-ups.
A73: R8-06 | B73: R8 Green | C73: Operators | D73: Indian operators' green disclosures | E73: Nxtra: 49% RE in core DCs (FY25), RE100, 70% target by 2027, net zero 2031, wheeling 140,208 MWh/yr cutting 99,547 tCO₂e; AdaniConneX US$875 m sustainability-linked loan (Report 8) / US$1.44 bn (Report 11); Sify >231 MW RE contracted; CtrlS captive solar, NTPC Green up to 2 GW, 100% RE by 2030; Yotta green tariff via TUCO; Meta ~1 GW RE in India; DCs 13.6% of open-access demand (CB Insights). | F73: % / MW / US$ | G73: India | H73: 2025–26 | I73: Company reports and announcements | K73: Reported, not verified | L73: =IF(K73="Partly verified","Partly",IF(LEFT(K73,8)="Verified","Yes","No")) -> No | M73: AdaniConneX financing figures differ between reports (likely different instruments). | N73: Benchmark clean-power share. | O73: Fleet clean share for carbon forecast (30% in 2026). | P73: Ch 8 table; Ch 11 carbon | Q73: Reconcile AdaniConneX figures.
A74: R8-07 | B74: R8 Green | C74: Framework | D74: Green maturity ladder L1–L5 | E74: Eight dimensions (energy, carbon, water, materials, circularity, heat, backup, transparency); Indian leaders mostly L2–L3; heat reuse weakest (L1). | F74: levels | G74: India | H74: 2026 | I74: Report 8 India-calibrated ladder (series judgement) | K74: Estimate / proxy | L74: =IF(K74="Partly verified","Partly",IF(LEFT(K74,8)="Verified","Yes","No")) -> No | N74: Self-assessment. | O74: Average level and weakest dimension. | P74: Ch 8 radar | Q74: —
A75: R9-01 | B75: R9 State policies | C75: Policy register | D75: State data-centre policy register | E75: 15–16 states: instrument, status (active/expiring/lapsed/legacy), power incentives, green conditions, targets, land and approvals, projects. E.g. Maharashtra IT/ITeS 2023 + Green DC Park GRs (ED waiver 20 yrs, ₹1/unit, RE floor 100% → 51% in Jun 2026); Tamil Nadu 2021 lapsed 31 Mar 2026; West Bengal lapses ~Sep 2026; UP 2026; Gujarat 2026–29 (7.5 GW, ₹6 lakh cr); Karnataka 2026–31 (1 GW, ₹1,300.45 cr); AP Policy 4.0. | F75: text | G75: India states | H75: Oct 2026 | I75: State policy documents and GRs; cabinet notes and press | K75: Reported, not verified | L75: =IF(K75="Partly verified","Partly",IF(LEFT(K75,8)="Verified","Yes","No")) -> No | M75: Gazette numbers not located for Karnataka, UP and Gujarat 2026; some items from press. | N75: Compare state regimes; incentives in simulator. | O75: Incentive value per site; renewal risk. | P75: Ch 9 table and map; simulator incentives | Q75: Obtain gazette copies.
A76: R9-02 | B76: R9 State policies | C76: Scoring | D76: State attractiveness factor scores | E76: Seven factors scored 0–10 per state (power, renewables, connectivity, incentives, land, water, regulatory); report weights 25/15/15/15/10/10/10. Index e.g. Maharashtra 7.6, AP 7.3, Telangana 7.2, Gujarat 7.0, UP 6.7, TN 6.5, Odisha 6.3, Rajasthan 6.1, Karnataka 6.0. Sustainability ranks 1–8. | F76: 0–10 | G76: 12 states | H76: 2026 | I76: Report 9 judgement | K76: Estimate / proxy | L76: =IF(K76="Partly verified","Partly",IF(LEFT(K76,8)="Verified","Yes","No")) -> No | M76: Not published data. | N76: Rank states for a use case. | O76: Weighted policy index; policy score input for Ch 10. | P76: Ch 9 index; map colouring | Q76: —
A77: R9-03 | B77: R9 State policies | C77: Incentives | D77: Electricity-duty holidays and tariff subsidies | E77: Duty holiday years: TN 5, WB 5, Rajasthan 7, UP 10, Odisha 10, Haryana 20, Maharashtra 20, Gujarat 20. ₹1/unit subsidies went from 5 yrs (Gujarat 2022) to 20 yrs (Gujarat 2026; Maharashtra ≥₹60,000 cr). No state publishes disbursements. | F77: years | G77: 8 states | H77: 2026 | I77: State policies | K77: Reported, not verified | L77: =IF(K77="Partly verified","Partly",IF(LEFT(K77,8)="Verified","Yes","No")) -> No | N77: Incentive race chart; incentive value. | O77: Present value of duty waivers (modelled at 7.5% of energy charge). | P77: Ch 9 chart; simulator | Q77: —
A78: R9-04 | B78: R9 State policies | C78: Validity | D78: Policy validity periods | E78: Start and end dates of each state's main data-centre instrument (e.g. Telangana 2016–2027, TN 2021–Mar 2026, WB 2021–Sep 2026, UP 2021–2026 replaced, Haryana 2022–2029, Odisha 2022–2027, Maharashtra IT 2023–2028). | F78: dates | G78: States | H78: Oct 2026 | I78: State policies | K78: Reported, not verified | L78: =IF(K78="Partly verified","Partly",IF(LEFT(K78,8)="Verified","Yes","No")) -> No | N78: Show renewal risk. | O78: States in renewal limbo. | P78: Ch 9 validity chart | Q78: —
A79: R9-05 | B79: R9 State policies | C79: Central framework | D79: Central data-centre framework | E79: Draft National DC Policy (2020) never notified; infrastructure status (Oct 2022) for DCs ≥5 MW; Budget 2026–27 tax holiday to 31 Mar 2047 for foreign cloud firms using Indian DCs; DPDP Rules (Nov 2025); Green Energy Open Access Rules 2022 (100 kW threshold); IndiaAI Mission. | F79: text | G79: India | H79: 2020–26 | I79: Gazette notifications; Finance Act 2026; MeitY | J79: Open source | K79: Partly verified | L79: =IF(K79="Partly verified","Partly",IF(LEFT(K79,8)="Verified","Yes","No")) -> Partly | M79: GEOA Rules 2022 verified (Report 12 gazette); others reported. | N79: National context for state competition. | O79: Which levers are national vs state. | P79: Ch 9 table | Q79: —
A80: R9-06 | B80: R9 State policies | C80: Controversy | D80: Siting controversies and policy critiques | E80: Vizag Google–Adani campus: Jal Biradari PIL on water near Kambalakonda sanctuary, PIL on 160 acres of temple land, protests at Tarluvada; Karnataka minister called AP's ~₹22,000 cr package "an economic disaster" (unpublished); CEEW (Feb 2026): 5 of 15 policies had sustainability provisions (~8 of 16 now). | F80: text | G80: India | H80: 2026 | I80: Press reports; CEEW & Systemiq (Feb 2026) | K80: Reported, not verified | L80: =IF(K80="Partly verified","Partly",IF(LEFT(K80,8)="Verified","Yes","No")) -> No | M80: AP package value is a claim; terms unpublished. | N80: Social-licence risk. | O80: Risk flags for siting. | P80: Ch 9 | Q80: —
A81: SIM-01 | B81: Simulator (R1–R9 synthesis) | C81: Model inputs | D81: Simulator city parameters | E81: Per city (Bengaluru, Mumbai, Chennai, Hyderabad, Noida, Vizag): design DB/WB, land ₹3–20 cr/acre, tariff and demand charge, RE price ₹5.5–6.2, power-station water (KA 1.5, others 2.2 L/kWh), water stress weight, water price (BWSSB ₹99/kL; ₹80 elsewhere; groundwater ₹20; treated + RO ₹40). | F81: mixed | G81: 6 cities | H81: 2026 | I81: Reports 3–7 (see Assumptions table in the simulator) | K81: Partly verified | L81: =IF(K81="Partly verified","Partly",IF(LEFT(K81,8)="Verified","Yes","No")) -> Partly | M81: Tariffs partly verified; grid carbon 0.710 verified; power-station water now superseded by Report 12 proxies (KA 1.5–2.2; others 2.8–3.4). | N81: Drive the "Build a data centre" simulator. | O81: Capex, LCOD, energy, water, CO₂, MVA, incentives for any design. | P81: Simulator | Q81: Update grid water and MH/KA tariffs to Report 12 values.
A82: SIM-02 | B82: Simulator (R1–R9 synthesis) | C82: Model functions | D82: Simulator PUE and WUE functions | E82: PUE = 1 + losses + other + cooling overhead(DB, WB); towers 0.30 + 0.012(WB−23); adiabatic 0.27 + 0.01(DB−35); air chillers 0.42 + 0.015(DB−35); liquid 0.12 (AI variants lower). WUE: towers 1.8 × (1 + 0.03(WB−23)); adiabatic 0.4 × (1 + 0.05(DB−35)); air 0.02; liquid 0.03. Finance WACC 11%, 20/5 yrs; duty 7.5% of energy charge. | F82: functions | G82: Generic | H82: 2026 | I82: Reports 3, 4, 6, 7 (series model) | K82: Model output | L82: =IF(K82="Partly verified","Partly",IF(LEFT(K82,8)="Verified","Yes","No")) -> No | N82: Climate-sensitive energy and water. | O82: PUE and WUE by city and design. | P82: Simulator; Ch 4 day model | Q82: Calibrate against metered Indian sites.
A83: R10-01 | B83: R10 Where to build | C83: India market | D83: India capacity estimates by source (H1 2026) | E83: C&W 1,789 MW operational, 3,860 MW pipeline, vacancy 14.9%; JLL 1,637 MW (Jun 2026), 6 GW by 2029, US$110 bn, H1 absorption 101 MW (82% pre-committed hyperscale), vacancy 2.8%; CBRE ~130 MW added H1 2026 (94% Mumbai, 48% domestic developers), ~2 GW by end-2026; PIB 1.57 GW (Aug 2026). | F83: MW | G83: India | H83: Jun–Oct 2026 | I83: C&W H1 2026 Update; JLL 2026 Mid-Year Report (2 Sep 2026); CBRE "Beyond Growth" (Oct 2026); PIB factsheet (14 Sep 2026) | K83: Reported, not verified | L83: =IF(K83="Partly verified","Partly",IF(LEFT(K83,8)="Verified","Yes","No")) -> No | M83: Sources differ by ~±7% and on vacancy (14.9% vs 2.8%) because definitions differ. | N83: Range for "how much India has today" (treat as 1.6–1.8 GW). | O83: Forecast anchor; definitional reconciliation. | P83: Ch 10 context; Ch 11 history | Q83: Rebase every six months.
A84: R10-02 | B84: R10 Where to build | C84: Site data | D84: 50 candidate cities: site attributes | E84: For each of 50 cities in 23 states/UTs: lat/long, district, nearest 220 kV+ / 400 kV node and distance, water status, seismic zone, flood/cyclone exposure, design DB/WB, free-cooling hours, demand context, strength, weakness. | F84: mixed | G84: 50 cities | H84: Oct 2026 | I84: Report 10 (public grid knowledge, CGWB/IN-GRES, IS 1893, ASHRAE approximations) | K84: Partly verified | L84: =IF(K84="Partly verified","Partly",IF(LEFT(K84,8)="Verified","Yes","No")) -> Partly | M84: Coordinates and seismic zones reliable; EHV nodes/distances, most water categories, design temperatures and free-cooling hours are estimates. | N84: Inputs to Step A (hard filters) and factor scores. | O84: Pass/fail per filter; latency; climate score. | P84: Ch 10 map, table, detail panel; worked example | Q84: Verify EHV nodes on STU single-line diagrams; water on IN-GRES.
A85: R10-03 | B85: R10 Where to build | C85: Scores | D85: Nine factor scores per city | E85: Power (50% tariff score + 50% grid/RE judgement), connectivity, water, climate, hazards, land, policy, demand/talent (0–10 rubric) plus computed latency. Policy scores: AP, UP 9; KA, MH, GJ 8; RJ 7; TG, OD, MP 6; HR 5; TN, WB, KL 3–4; Delhi 3. Report totals 4.0–7.2. | F85: 0–10 | G85: 50 cities | H85: Oct 2026 | I85: Report 10 rubric | K85: Estimate / proxy | L85: =IF(K85="Partly verified","Partly",IF(LEFT(K85,8)="Verified","Yes","No")) -> No | M85: Rubric judgements; illustrative. | N85: Steps B–C of the ranking. | O85: Weighted and geometric scores; tiers; use-case rankings. | P85: Ch 10 ranking engine; worked example workbook | Q85: Replace judgement scores with measured inputs where possible.
A86: R10-04 | B86: R10 Where to build | C86: Power price | D86: Effective tariff by state at 80% load factor | E86: ₹/kWh (energy + demand ÷ 584 h): Odisha ≈5.96; Kerala ≈6.23; Haryana ≈7.1; Andhra Pradesh ≈7.3 (est.); Uttar Pradesh ≈7.41; Telangana ≈7.51; Karnataka ≈7.61; Gujarat ≈8.0 (est.); West Bengal ≈7.5 (est.); Rajasthan ≈7.7 (est.); Madhya Pradesh ≈8.2; Delhi ≈8.5 (est.); Tamil Nadu ≈8.54; Maharashtra ≈8.7. | F86: ₹/kWh | G86: 14 states | H86: FY2026-27 | I86: State commission tariff orders (OERC, KSERC, HERC, UPERC, TGERC, KERC, TNERC, MERC, MPERC; others estimated) | K86: Partly verified | L86: =IF(K86="Partly verified","Partly",IF(LEFT(K86,8)="Verified","Yes","No")) -> Partly | M86: Telangana inputs verified (Report 12) and TN verified-secondary; Delhi, WB, AP, Rajasthan, Gujarat estimated; Karnataka and Maharashtra inputs conflict with Report 12. | N86: Tariff half of the power score. | O86: Tariff score = 10 × (8.70 − x) ÷ (8.70 − 5.96); 20-year cost gap between states. | P86: Ch 10 power score; worked example | Q86: Re-derive with Report 12 verified KA/MH rates.
A87: R10-05 | B87: R10 Where to build | C87: Power price | D87: State tariff details (FY2026-27) | E87: MSEDCL HT-I(A) ₹7.11–7.27/kVAh + ~₹0.60 wheeling, ₹560–565/kVA; TNERC T.O. 6/2025 HT-I ₹7.50/kWh + ₹608/kVA; KERC HT-2(a) ~700 paise + ~₹355/kVA (unconfirmed); TGERC HT-I(A) ₹6.65/7.15/7.65 per kVAh (132/33/11 kV) + ₹500/kVA, grid support ₹19.77/kW/month, green +₹0.66; APERC HT-I ~₹475/kVA; UPERC NIDP HV-2 ₹270/kVA + ₹6.95/kVAh, green +₹0.34; HERC ₹290/kVA + ₹6.95/6.85/~6.6; GERC HTP-I ₹4.30 + FPPPA, OA surcharge ₹0.99; WBERC ₹320/kVA; KSERC ₹6.75/6.15/5.55 to Mar 2027; OERC ₹250/kVA, 580/470 paise; Rajasthan ~₹380 + ₹6.50 (aggregator); MPERC ₹729 + 734/635 paise; PSERC ₹5.82–7.04. | F87: ₹/kWh; ₹/kVA | G87: 14 states | H87: FY2026-27 | I87: State commission orders (Report 10) | K87: Partly verified | L87: =IF(K87="Partly verified","Partly",IF(LEFT(K87,8)="Verified","Yes","No")) -> Partly | M87: TGERC rates verified in Report 12; several others flagged unconfirmed in Report 10 (KERC row, Gujarat slabs, WB energy, AP energy, Rajasthan, MP column mapping, Kerala demand, Delhi). | N87: Build effective tariffs. | O87: Effective ₹/kWh per state and voltage. | P87: Ch 10; simulator | Q87: Pull final orders for flagged states.
A88: R10-06 | B88: R10 Where to build | C88: Water | D88: Groundwater stage of extraction | E88: National (DGWRA 2025): 60.63% stage; 6,762 units — 730 over-exploited (10.8%), 201 critical, 758 semi-critical, 4,946 safe (73.14%). Bengaluru Urban units (IN-GRES 2025-26, secondary compilation): East 395%, North 257.9%, Yelahanka 251.5%, City 223.4%, South 121.9%, Anekal 106.4%. Chennai district 127.47%, 13 of 16 taluks over-exploited (CGWB 2023). Haryana 136.75%, 91 of 143 units over-exploited, 5 blocks in Gurugram (2025). | F88: % / count | G88: India; selected districts | H88: 2023–2026 | I88: Ministry of Jal Shakti / CGWB DGWRA 2025; IN-GRES; CGWB 2023 | K88: Reported, not verified | L88: =IF(K88="Partly verified","Partly",IF(LEFT(K88,8)="Verified","Yes","No")) -> No | M88: Bengaluru unit values come from a secondary compilation; conflict with Report 4 (East ~305%). | N88: Water hard filter (conditional on treated water). | O88: Which sites pass the water filter; water factor score. | P88: Ch 10 filter and water score | Q88: Pull block-level 2025 categories from IN-GRES.
A89: R10-07 | B89: R10 Where to build | C89: Hazards | D89: Seismic zoning standard | E89: IS 1893:2016 zones used; IS 1893:2025 (with Zone VI on the Himalayan arc) withdrawn by gazette 3 Mar 2026. | F89: zone | G89: India | H89: Mar 2026 | I89: BIS gazette notification | K89: Reported, not verified | L89: =IF(K89="Partly verified","Partly",IF(LEFT(K89,8)="Verified","Yes","No")) -> No | N89: Seismic hard filter (zone V excluded). | O89: Excluded sites (Guwahati); design-risk flag for Himalayan sites. | P89: Ch 10 Step A | Q89: —
A90: R10-08 | B90: R10 Where to build | C90: Connectivity | D90: Internet exchanges | E90: NIXI 77 nodes; core nodes Delhi (Noida), Mumbai (Vashi), Chennai, Kolkata, Bengaluru, Hyderabad, Ahmedabad, Guwahati; 27 named regional nodes. Private IX (DE-CIX, Extreme IX) in six metros (estimate). | F90: count | G90: India | H90: 2026 | I90: NIXI; PeeringDB (to confirm) | K90: Partly verified | L90: =IF(K90="Partly verified","Partly",IF(LEFT(K90,8)="Verified","Yes","No")) -> Partly | M90: NIXI reported; private IX locations estimated. | N90: Connectivity score; edge siting. | O90: Edge DC locations near peering. | P90: Ch 10 connectivity scores | Q90: Confirm on PeeringDB.
A91: R10-09 | B91: R10 Where to build | C91: Anchor projects | D91: Visakhapatnam anchor project | E91: Google broke ground 28 Apr 2026 on a 1 GW AI hub (US$15 bn, with AdaniConneX and Airtel Nxtra), 601 acres at Tarluvada, Adavivaram, Rambilli; AP promised ~5 GW in Vizag (The Ken); Raiden applied for ~2.1 GW power allowance (DCD); America-India Connect adds three subsea paths. | F91: MW / acres / US$ | G91: Visakhapatnam | H91: 2026 | I91: Google; The Ken; DatacenterDynamics | K91: Reported, not verified | L91: =IF(K91="Partly verified","Partly",IF(LEFT(K91,8)="Verified","Yes","No")) -> No | M91: Announcements, not commissioned assets. | N91: Upside for Vizag and AP. | O91: Vizag city allocation in forecast (~250 MW by 2030). | P91: Ch 10; Ch 11 city split | Q91: Track commissioning.
A92: R10-10 | B92: R10 Where to build | C92: Latency | D92: Great-circle distances and latency | E92: Distances from each city to Mumbai, Delhi, Chennai, Bengaluru; RTT = 2 × d × 1.4 ÷ 200 = 0.014 × km. Inter-hub: Mumbai–Delhi 1,150 km 16.1 ms; Mumbai–Chennai 1,030 km 14.4 ms; Mumbai–Bengaluru 845 km 11.8 ms; Delhi–Chennai 1,760 km 24.6 ms; Chennai–Bengaluru 290 km 4.1 ms. | F92: km; ms | G92: 50 cities | H92: 2026 | I92: Computed (haversine on coordinates) | K92: Model output | L92: =IF(K92="Partly verified","Partly",IF(LEFT(K92,8)="Verified","Yes","No")) -> No | M92: Straight-line proxy; ignores real fibre routes and peering. | N92: Latency factor (computed, not judged). | O92: Mean RTT per city; min–max latency score. | P92: Ch 10; worked example | Q92: Replace with measured RTTs (RIPE Atlas, operators).
A93: R10-11 | B93: R10 Where to build | C93: Model output | D93: City ranking and Monte Carlo stability | E93: Default weights 25/15/10/15/5/10/5/10/5; presets for AI campus, interconnection, sustainability; tiers A (top 30%), B (next 40%), C; 1,000-run Monte Carlo (±20% weights and scores). Report 10 top: Hyderabad periphery 7.2, Visakhapatnam 6.8, Hyderabad core 6.7, Navi Mumbai 6.6, Mysuru 6.5. Atlas engine (min–max): Mysuru 6.35, #5 of 48, Tier A, 76% India top-10. | F93: score 0–10 | G93: 50 cities | H93: Oct 2026 | I93: Report 10 model; atlas Chapter 10 engine | K93: Model output | L93: =IF(K93="Partly verified","Partly",IF(LEFT(K93,8)="Verified","Yes","No")) -> No | N93: Shortlist sites by use case. | O93: Robust vs fragile picks; use-case top-3. | P93: Ch 10; worked-example workbook | Q93: —
A94: R10-12 | B94: R10 Where to build | C94: Grid | D94: Substation spare capacity (MVA headroom) | E94: Not published by any of 15 state transmission utilities. | F94: MVA | G94: India | H94: — | I94: None (unpublished) | K94: Unpublished / gap | L94: =IF(K94="Partly verified","Partly",IF(LEFT(K94,8)="Verified","Yes","No")) -> No | M94: The binding unknown for every site. | N94: Would replace the grid half of the power score. | O94: Real grid-feasibility filter. | P94: Ch 10 (flagged) | Q94: Request load-flow studies from STUs and CTUIL GNA margins.
A95: R11-01 | B95: R11 Forecast | C95: History | D95: Harmonised capacity history | E95: MW IT (year-end): 2019 375; 2020 450; 2021 560; 2022 720; 2023 977; 2024 1,200; 2025 1,611; H1 2026 1,789. Reported points from JLL, C&W, MeitY, ICRA, CBRE, Colliers, Rubix shown alongside. | F95: MW | G95: India | H95: 2019–2026 | I95: Harmonised from C&W, JLL, MeitY, ICRA, CBRE, Colliers | K95: Estimate / proxy | L95: =IF(K95="Partly verified","Partly",IF(LEFT(K95,8)="Verified","Yes","No")) -> No | M95: Estimate built from reported points with differing definitions. | N95: Fit growth models. | O95: CAGR 27.9% (log-linear fit, R² ≈ 0.99); logistic rate r. | P95: Ch 11 chart | Q95: —
A96: R11-02 | B96: R11 Forecast | C96: Forecasts | D96: Published forecasts for 2030 | E96: GW: CareEdge ~4 (FY30); Colliers >4.5; Arizton 4.8; C&W 5.6 if all built; JLL 6 (2029); Rubix 6.5; Macquarie ~6.5–7.5 implied; Jefferies 8; PIB "nearly 8"; Wood Mackenzie 12. Median ~6.5 GW. ICRA 2.0–2.1 GW by Mar 2027; CBRE ~2 GW end-2026. | F96: GW | G96: India | H96: 2024–26 | I96: Named forecasters (Report 11) | K96: Reported, not verified | L96: =IF(K96="Partly verified","Partly",IF(LEFT(K96,8)="Verified","Yes","No")) -> No | M96: No public India MW forecasts found from Morgan Stanley, Bernstein, Nomura, Goldman, CRISIL, NASSCOM, IEA. | N96: Compare our base case. | O96: Haircut test: base 4.7 GW = 0.72× median. | P96: Ch 11 forecaster chart | Q96: —
A97: R11-03 | B97: R11 Forecast | C97: Backtest | D97: Forecast track record | E97: Delivered ÷ forecast additions 0.58–0.74; actual ÷ forecast level 0.78–0.87; under-construction projects ~100% within 4–5 years; Arizton raised its 2030 forecast 37% in five months. | F97: ratio | G97: India | H97: 2021–26 | I97: Report 11 backtest of JLL, C&W, ICRA forecasts | K97: Model output | L97: =IF(K97="Partly verified","Partly",IF(LEFT(K97,8)="Verified","Yes","No")) -> No | M97: Built from reported forecasts and outcomes. | N97: Calibrate pipeline conversion. | O97: 25–35% haircut on headline additions; conversion c_UC 0.95, c_P 0.60. | P97: Ch 11 pipeline model | Q97: —
A98: R11-04 | B98: R11 Forecast | C98: Power demand | D98: Government data-centre power-demand estimates | E98: CEA: up to 17 GW by 2031-32 (PIB factsheet 14 Sep 2026); Ministry of Power 13.56 GW (Mar 2026); MoS Power: additional 26.3 GW AI DC load by 2031-32 (written reply, 29 Jul 2026); CEA committee set up with CTU and Nasscom. | F98: GW | G98: India | H98: 2026 | I98: PIB; Ministry of Power; Business Standard | K98: Reported, not verified | L98: =IF(K98="Partly verified","Partly",IF(LEFT(K98,8)="Verified","Yes","No")) -> No | N98: High-case check for connected load. | O98: Plan grids for the high case (~14 GW in 2032). | P98: Ch 11 | Q98: —
A99: R11-05 | B99: R11 Forecast | C99: Electricity | D99: National electricity requirement | E99: 1,694 BU (FY2024-25, CEA LT-NRAP); 20th EPS mid-term review: 3,365 BU and 459 GW peak in 2035-36 (6.41% CAGR); NEP 2,473.8 BU (2031-32); FY26 peak ~245 GW vs 270 projected. FY25 generation 1,824 BU (thermal 74.7%). | F99: BU | G99: India | H99: FY25–FY36 | I99: CEA LT-NRAP; 20th EPS MTR; NEP 2022-32; CREA (generation) | K99: Partly verified | L99: =IF(K99="Partly verified","Partly",IF(LEFT(K99,8)="Verified","Yes","No")) -> Partly | M99: FY25 generation 1,824 BU and thermal 74.7% verified (Report 12); requirement figures reported. Requirement and generation are different bases. | N99: Denominator for data-centre share of electricity. | O99: DC share: 1% (2028), 2% (2033), ~2.5% (2035) base. | P99: Ch 11 share | Q99: —
A100: R11-06 | B100: R11 Forecast | C100: Efficiency | D100: Indian PUE evidence | E100: tele.net: Indian DCs typically 1.45–1.55; CtrlS design 1.35; Takshashila 1.6 (2024 assumption); SBI: leaders below 1.5; Karnataka incentive band 1.00–1.20; Uptime Asia-Pacific (excl. China) 1.52 (n=79). | F100: PUE | G100: India | H100: 2024–26 | I100: tele.net; CtrlS; Takshashila; SBI; Uptime Field Report 183 | K100: Partly verified | L100: =IF(K100="Partly verified","Partly",IF(LEFT(K100,8)="Verified","Yes","No")) -> Partly | M100: Uptime APAC 1.52 verified (Report 12); Indian figures reported. | N100: PUE path in forecast and calculators. | O100: PUE 1.50 (2026) → 1.42 (2030) → 1.35 (2035). | P100: Ch 11; Ch 12 calculator | Q100: Collect operator-metered PUE.
A101: R11-07 | B101: R11 Forecast | C101: Calibration | D101: Current Indian DC electricity use | E101: Nomura: ~8.4 TWh (cited by IEA); CEEW: ~0.5% of national electricity (2025); model gives ~8.8 TWh (2024) and ~10 TWh (2025, 0.57%). | F101: TWh / % | G101: India | H101: 2024–25 | I101: IEA critical review citing Nomura; CEEW (Feb 2026) | J101: Open source | K101: Partly verified | L101: =IF(K101="Partly verified","Partly",IF(LEFT(K101,8)="Verified","Yes","No")) -> Partly | M101: CEEW 0.5% verified (Report 12); Nomura reported. | N101: Calibrate the energy model. | O101: Utilisation assumption u ≈ 0.55. | P101: Ch 11 | Q101: —
...

Sheet Verified figures
A1: Individually verified figures
A2: Confirmed against the source document during the research (Report 12). Secondary = confirmed via a summary of the primary.
A4: # | B4: Figure | C4: Value | D4: As of | E4: Source | F4: Link | G4: Status | H4: Register ID | I4: Confirms or corrects
A5: 1 | B5: Microsoft fleet WUE / PUE | C5: 0.30 L/kWh / 1.16 (FY24); 0.27 / 1.17 (FY25) | D5: FY24–25 | E5: Microsoft datacenter efficiency page | F5: Open source | G5: Verified | H5: R12-03 | I5: Confirms Report 3 "fleet WUE 0.30"
A6: 2 | B6: Microsoft Asia-Pacific WUE / PUE | C6: 0.03 / 1.25 (FY24); 0.25 / 1.28 (FY25) | D6: FY24–25 | E6: Microsoft datacenter efficiency page | F6: Open source | G6: Verified | H6: R12-03
A7: 3 | B7: Microsoft zero-water cooling design | C7: Avoids >125 million L/yr per datacenter; all new designs from Aug 2024 | D7: Dec 2024 | E7: Microsoft Cloud blog | F7: Open source | G7: Verified | H7: R3-09 | I7: Confirms Report 3
A8: 4 | B8: Google fleet PUE | C8: 1.09 | D8: 2025 | E8: Google data centre efficiency | F8: Open source | G8: Verified | H8: R12-03 | I8: Confirms Key numbers
A9: 5 | B9: Gemini median text prompt | C9: 0.24 Wh; 0.26 mL water (0.15 mL narrow); 0.03 gCO₂e | D9: May 2025 | E9: Elsworth et al. (Google), arXiv 2508.15734 | F9: Open source | G9: Verified | H9: R2-03 | I9: Confirms Reports 2 and 6
A10: 6 | B10: US data-centre average site WUE | C10: ~0.36 L/kWh through 2023; 0.45–0.48 after | D10: 2024 | E10: LBNL US Data Center Energy Usage Report | F10: Open source | G10: Verified | H10: R12-03
A11: 7 | B11: US data-centre water | C11: 66 bn L direct (2023); ~800 bn L at power plants (4.52 L/kWh) on ~176 TWh | D11: 2024 | E11: LBNL 2024 | F11: Open source | G11: Verified | H11: R12-08
A12: 8 | B12: US hyperscale median WUE | C12: 0.32 L/kWh (0.40 if adiabatic at 0.2); adiabatic self-reported 0.1–0.3 | D12: 2024 | E12: LBNL 2024 | F12: Open source | G12: Verified | H12: R12-03
A13: 9 | B13: US average PUE (LBNL) | C13: 1.6 (2014), 1.4 (2023), 1.15–1.35 (2028) | D13: 2024 | E13: LBNL 2024 | F13: Open source | G13: Verified | H13: R12-03
A14: 10 | B14: UPS efficiency by class | C14: Edge 77–85%; colo 80–94%; hyperscale/AI 90–99% | D14: 2024 | E14: LBNL 2024 | F14: Open source | G14: Verified | H14: R2-06
A15: 11 | B15: Server utilisation and AI load factors | C15: Colo 21% (2014) → 35% (2027); hyperscale 45% → 50%; AI training 80% of time at ~70% rated; inference 40% | D15: 2024 | E15: LBNL 2024 | F15: Open source | G15: Verified | H15: R12-13
A16: 12 | B16: DGX H100 rated power | C16: 10.2 kW (8 GPU); saturated node 7.9 kW | D16: 2024 | E16: LBNL 2024 | F16: Open source | G16: Verified | H16: R2-04 | I16: Confirms Report 2
A17: 13 | B17: DGX B200 maximum power | C17: 14.3 kW | D17: 2025 | E17: NVIDIA DGX B200 user guide | F17: Open source | G17: Verified | H17: R2-04
A18: 14 | B18: NTT DATA WUE and PUE | C18: Portfolio WUE 1.01 / 0.65 / 0.72; evaporative sites 2.93 / 2.77 / 1.42; PUE 1.40 / 1.38 / 1.38 | D18: FY22–24 | E18: NTT DATA ESG environment data | F18: Open source | G18: Verified | H18: R12-03
A19: 15 | B19: Global average PUE (Uptime) | C19: 1.54 (2025); 1.56 (2024); 1.58 (2023); facilities since ~2020 1.48; >20 MW 1.44 | D19: 2025 | E19: Uptime Institute Global Data Center Survey 2025 | F19: Open source | G19: Verified | H19: R12-03 | I19: Confirms Key numbers and Report 1 (1.44 for >20 MW)
A20: 16 | B20: Asia-Pacific average PUE (excl. China) | C20: 1.52 (n = 79) vs global 1.54 | D20: 2025 | E20: Uptime Field Report 183 | F20: Open source | G20: Verified | H20: R11-06
A21: 17 | B21: GPT-3 request served from India (Li et al.) | C21: 19.7 mL (0 on-site + 19.7 off-site); PUE 1.430; EWIF 3.445 L/kWh; Microsoft India on-site WUE 0.000 | D21: 2023/2025 | E21: Li, Yang, Islam & Ren, ACM | F21: Open source | G21: Verified | H21: R6-05 | I21: Confirms Report 6
A22: 18 | B22: CEEW India sector data | C22: DCs ≈ 0.5% of national electricity (2025); ~271 DCs (Jan 2026); 100 MW hyperscale ~2 million L/day | D22: Feb 2026 | E22: CEEW & Systemiq, Scaling India's Data Centre Ecosystem | F22: Open source | G22: Verified | H22: R12-04 | I22: Confirms Report 11 calibration
A23: 19 | B23: Indian operator water disclosure | C23: Nxtra and CtrlS publish no WUE; CtrlS 409,037 kL (2023-24) vs 468,330 kL (2022-23); Yotta gives no number | D23: 2025 | E23: Down To Earth | F23: Open source | G23: Verified | H23: R6-07 | I23: Confirms Report 6 disclosure gap
A24: 20 | B24: Karnataka Sustainable DC Policy 2026–31 | C24: Plant-wise PUE and WUE reporting required; water-charge reimbursement for WUE 0.7–1.3 L/kWh | D24: 2026 | E24: The News Minute (policy summary) | F24: Open source | G24: Verified | H24: R9-01 | I24: Confirms Report 4 critique of the WUE band
A25: 21 | B25: Thermal plant water norms | C25: ≤3.5 m³/MWh for existing cooling-tower plants (by 7 Dec 2017); 2.5 m³/MWh for post-2017 plants, relaxed to 3.0 (Jun 2018) | D25: 2015/2018 | E25: MoEFCC S.O. 3305(E) (CPCB); PowerLine | F25: Open source | G25: Verified | H25: R12-05 | I25: Confirms Report 5 "3.5/3.0 norms"
A26: 22 | B26: Indian coal plant water consumption | C26: 2.8–3.4 m³/MWh (≈2× world 1.2–1.5); air-cooled condenser 0.45–0.65 | D26: 2023 | E26: Energy journal (SD23) vulnerability assessment | F26: Open source | G26: Verified | H26: R12-05 | I26: Confirms Report 5 (~3,400 L/MWh)
A27: 23 | B27: Coal plant withdrawal and FGD | C27: Once-through 70–200 m³/MWh; average withdrawal ~4 m³/MWh; FGD adds ~0.3 m³/MWh | D27: Sep 2026 | E27: CSE via PowerLine | F27: Open source | G27: Verified | H27: R12-05
A28: 24 | B28: Nuclear and thermal water factors (NREL) | C28: Nuclear tower 672 gal/MWh = 2.54 L/kWh; tower thermal upper ~1,000 gal/MWh ≈ 3.8 L/kWh; wind ~0 | D28: 2011 | E28: Macknick et al., NREL | F28: Open source | G28: Verified | H28: R12-05 | I28: Confirms Report 5 nuclear ~2,600 L/MWh
A29: 25 | B29: Thermal plants in water-stressed areas | C29: 40% now; 70% by 2030; 14 of 20 utilities had shutdowns 2013–16 costing US$1.4 bn | D29: Jan 2018 | E29: WRI | F29: Open source | G29: Verified | H29: R12-06
A30: 26 | B30: India FY25 generation | C30: 1,824 BU total; thermal 1,363 BU (74.7%) | D30: FY2024-25 | E30: CREA via Deccan Herald | F30: Open source | G30: Verified | H30: R12-07
A31: 27 | B31: India and Karnataka renewable share | C31: RE 403.64 BU (22.13% of generation); Karnataka RE 48.10% of state generation | D31: FY2024-25 | E31: MNRE Renewable Energy Statistics 2024-25 | F31: Open source | G31: Verified | H31: R12-07
A32: 28 | B32: India grid emission factor | C32: 0.710 tCO₂/MWh FY25 (1,234.19 Mt ÷ 1,739.06 BU); 0.774 FY2013-14 | D32: Nov 2025 | E32: CEA CO₂ Baseline Database User Guide v21 | F32: (not captured) | G32: Verified | H32: R5-01 | I32: Confirms Reports 5, 7, 8, 11 and simulator
A33: 29 | B33: EU water reporting | C33: Sites ≥500 kW IT report total and potable water input (m³); first returns 15 Sep 2024, then 15 May yearly | D33: 2024 | E33: Delegated Regulation (EU) 2024/1364 | F33: Open source | G33: Verified | H33: R12-01 | I33: Confirms Report 8
A34: 30 | B34: NERC large-load events | C34: ~1,500 MW DC load disconnected 10 Jul 2024 (60 load points, 25 substations); 1,800 MW loss Feb 2025 | D34: 2025 | E34: NERC / FERC presentation | F34: Open source | G34: Verified | H34: R2-07 | I34: Confirms Report 2
A35: 31 | B35: IEX prices | C35: DAM Jan 2026 ₹3.86, Feb ₹3.58; G-DAM FY25 ₹4.01, Jan 2026 ₹4.06, Feb ₹3.43 | D35: 2026 | E35: IEX via SaurEnergy and Business Standard | F35: Open source | G35: Verified | H35: R12-16
A36: 32 | B36: SECI firm renewable tenders | C36: FDRE-RTC ₹5.25/kWh; 4-hour assured peak ₹5.99/kWh; RTC-IV ₹5.06–5.07; SJVN FDRE-3 ₹4.82–4.91 | D36: Aug 2026 | E36: pv-magazine; SaurEnergy | F36: Open source | G36: Verified | H36: R12-16 | I36: Confirms Reports 7 and 8 (₹5.25)
A37: 33 | B37: ISTS charge waiver phase-out | C37: ISTS charges at 25% for COD Jul 2025–Jun 2026, then 50%, 75%, 100% after 1 Jul 2028 | D37: 2025 | E37: Ministry of Power via T&D India | F37: Open source | G37: Verified | H37: R12-16
A38: 34 | B38: Green Energy Open Access Rules 2022 | C38: CSS may not rise >50% over 12 years; additional surcharge not applicable if fixed charges paid; banking ≥30% monthly | D38: Jun 2022 | E38: GEOA Rules gazette | F38: Open source | G38: Verified | H38: R12-16 | I38: Confirms Report 9
A39: 35 | B39: FOR model GEOA regulations | C39: Cross-subsidy surcharge not to exceed 20% of tariff or ABR | D39: — | E39: Forum of Regulators | F39: Open source | G39: Verified | H39: R12-16
A40: 36 | B40: MSEDCL HT tariffs (MERC MYT) | C40: HT-I(A) ₹7.48/kVAh FY26 → 7.27 → 7.11; ₹555/560/565 per kVA-month; HT-II commercial ₹9.26 + ₹0.62; 10% wheeling discount for DCs on OA/green tariff | D40: Mar 2025 | E40: MERC press note, MSEDCL MYT order | F40: Open source | G40: Verified | H40: R12-15 | I40: Differs from Reports 7/10 (₹7.27 / ₹7.11–7.27) — see Conflicts
A41: 37 | B41: Tata Power-D HT tariffs | C41: HT-II / EHV commercial ₹5.89 + ₹0.69 wheeling / ₹5.89; ₹300/kVA-month; green tariff ₹0.25/kWh | D41: Mar 2025 | E41: MERC press note, TPC-D MYT order | F41: Open source | G41: Verified | H41: R12-15
A42: 38 | B42: TGSPDCL HT tariffs | C42: HT-I(A) ₹7.65 / 7.15 / 6.65 per kVAh (11 / 33 / ≥132 kV); ₹500/kVA-month; green +₹0.66; HT-II(A) ₹8.80 / 8.00 / 7.80 | D42: FY2025-26 | E42: TGERC tariff schedule | F42: Open source | G42: Verified | H42: R12-15 | I42: Confirms Reports 7 and 10 Telangana tariffs
A43: 39 | B43: Telangana cross-subsidy surcharge | C43: HT-I ₹1.82 / 1.56 / 1.46; HT-II(A) ₹2.15 / 1.86 / 1.79 per kWh | D43: FY2025-26 | E43: TGERC tariff schedule | F43: Open source | G43: Verified | H43: R12-16
A44: 40 | B44: Telangana ToD | C44: +₹1.00/unit 06–10 and 18–22 h; −₹1.50/unit 22–06 h | D44: FY2025-26 | E44: TGERC tariff schedule | F44: Open source | G44: Verified | H44: R5-11
A45: 41 | B45: Maharashtra ToD | C45: HT ToD charge 25%; solar-hour rebate from −15% (FY26) | D45: FY26–30 | E45: MERC press note | F45: Open source | G45: Verified | H45: R5-11
A46: 42 | B46: KERC HT-2(a) tariff | C46: 660 paise/kWh (FY26, FY27), 650 (FY28); ₹345 / 350 / 355 per kVA-month; P&G surcharge 36 paise (FY26), 35 (FY27) | D46: 2025 | E46: KERC tariff schedule | F46: Open source | G46: Verified | H46: R12-15 | I46: Differs from Report 10 (~700 paise) and simulator (₹6.70) — see Conflicts
A47: 43 | B47: ChatGPT average query | C47: 0.34 Wh; ~0.32 mL water (Altman, Jun 2025) | D47: Jun 2025 | E47: Towards Data Science | F47: Open source | G47: Verified (secondary source) | H47: R2-03 | I47: Confirms Report 2
A48: 44 | B48: Google fleet WUE | C48: 1.15 L/kWh | D48: 2024 | E48: MDPI reconstruction of Google data | F48: Open source | G48: Verified (secondary source) | H48: R12-03
A49: 45 | B49: Equinix WUE | C49: 0.91 global; 1.41 evaporative sites | D49: 2025 | E49: Equinix 2025 report via Wikipedia | F49: Open source | G49: Verified (secondary source) | H49: R12-03
A50: 46 | B50: EU data-centre rating scheme | C50: A–G energy and water labels auto-generated from 15 Aug 2027; A: PUE ≤1.15, WUE ≤0.10 | D50: 2026 (draft) | E50: Philip Lee | F50: Open source | G50: Verified (secondary source) | H50: R8-04 | I50: Confirms Report 8
A51: 47 | B51: DC share of India water demand | C51: ~0.02–0.03% of national water demand | D51: 2025 | E51: CEEW author in Scroll | F51: Open source | G51: Verified (secondary source) | H51: R12-04 | I51: Confirms Report 11 (Mongabay)
A52: 48 | B52: India DC siting and water | C52: ~75% of DCs in water-stressed regions; ~25 million L per MW per year | D52: Apr 2026 | E52: DTE via Substack | F52: Open source | G52: Verified (secondary source) | H52: R12-04
A53: 49 | B53: Global DC water split (IEA) | C53: 560 bn L (2023) = 373 indirect + 140 direct + 47 hardware manufacturing | D53: 2023 | E53: IEA via gpusmith | F53: Open source | G53: Verified (secondary source) | H53: R12-09
A54: 50 | B54: Solar PV water use | C54: <0.19 L/kWh (cleaning) | D54: — | E54: NREL-derived secondary sources | F54: (not captured) | G54: Verified (secondary source) | H54: R12-05
A55: 51 | B55: IEX hourly price shape | C55: June 2026 averages: trough ₹1.17 at 11:00; peak ₹9.90 at 22:30; 08–16 h ₹1.63; 18–23 h ₹8.10 | D55: Jun 2026 | E55: earthsync | F55: Open source | G55: Verified (secondary source) | H55: R12-14
A56: 52 | B56: NERC follow-on details | C56: ~1,260 MW did not return for hours (POWER); one site 450 → 40 MW in 36 s (NERC Jul 2025 white paper, via Keentel) | D56: 2025 | E56: POWER; Keentel Engineering | F56: Open source | G56: Verified (secondary source) | H56: R2-07 | I56: Confirms Report 2
A57: 53 | B57: GB200 / GB300 NVL72 rack power | C57: ~120 kW (NVIDIA); 132 kW HPE nominal; GB300 135–142 kW | D57: 2025 | E57: Pantheon summary of NVIDIA specs | F57: Open source | G57: Verified (secondary source) | H57: R2-04 | I57: Confirms Report 2 range
A58: 54 | B58: Tamil Nadu HT tariffs | C58: HT-I ₹7.50 / HT-III ₹9.40 per kWh; ₹608/kVA-month; HT wheeling ₹1.04; CSS industrial ₹1.99, commercial ₹2.57 | D58: 2025 | E58: eClouds Energy summary of TNERC T.O. 6/2025 | F58: Open source | G58: Verified (secondary source) | H58: R12-15 | I58: Confirms Reports 7 and 10 Tamil Nadu tariffs
A59: 55 | B59: BESCOM true-up and proposed surcharge | C59: True-up +56 paise (May 2026–Apr 2027); additional surcharge ₹1.65/kWh proposed, not approved | D59: 2025–26 | E59: MENAFN; SolarQuarter | F59: Open source | G59: Verified (secondary source) | H59: R12-15 | I59: Confirms Report 8 mention of ₹1.65
A60: 56 | B60: Tamil Nadu GEOA banking | C60: 8% of banked energy, in kind (TN GEOA Regulations 2025) | D60: Sep 2025 | E60: SolarQuarter | F60: Open source | G60: Verified (secondary source) | H60: R12-16
A61: 57 | B61: 2025 coal PPAs | C61: ₹5.38–6.30/kWh starting tariffs | D61: 2025 | E61: IECC via SaurEnergy | F61: Open source | G61: Verified (secondary source) | H61: R12-16
A62: 58 | B62: Maharashtra grid support charge | C62: ₹1.40/unit for HT rooftop solar | D62: 2025 | E62: Secondary summary of MERC order | F62: Open source | G62: Verified (secondary source) | H62: R12-16

Sheet Conflicts
A1: Where our sources disagree
A2: Use the "Use now" column until the conflict is resolved.
A4: # | B4: Topic | C4: Value A (source) | D4: Value B (source) | E4: Likely reason | F4: Use now | G4: How to resolve
A5: 1 | B5: MSEDCL HT-I(A) energy charge | C5: ₹7.48/kVAh FY26 → 7.27 → 7.11 (MERC press note; verified in Report 12) | D5: ₹7.11–7.27 (Report 10, MERC documents); ₹7.27 (Report 7 and simulator); ₹8.68 after a Mar 2026 review (blog, unverified) | E5: Different tariff years and documents; blog figure unconfirmed | F5: Use ₹7.48 for FY26 and ₹7.27 for FY27 per MERC; ignore ₹8.68 until an order is found | G5: Pull MERC Case 217/2024 schedule and any 2026 review order
A6: 2 | B6: Karnataka HT-2(a) energy charge | C6: 660 paise/kWh FY26–27, ₹345/kVA (KERC schedule; verified in Report 12) | D6: ~700 paise + ~₹355/kVA (Report 10, unconfirmed row); ₹6.70 + ₹365 (Report 7 and simulator) | E6: Report 10 subagent could not confirm the row; Report 7 used an older figure | F6: Use 660 paise + ₹345 (+36 paise P&G, +56 paise BESCOM true-up where applicable) | G6: Update Report 10 effective tariff (≈₹7.61) and simulator
A7: 3 | B7: Bangalore East groundwater stage | C7: ~305% (2024 assessment; Report 4) | D7: 395% (IN-GRES 2025-26, secondary compilation; Report 10) | E7: Different assessment years and sources | F7: Both say severely over-exploited; cite as "305–395%" until verified | G7: Check IN-GRES 2025-26 directly
A8: 4 | B8: India operational capacity | C8: 1,789 MW (C&W, H1 2026) | D8: 1,637 MW (JLL, Jun 2026); 1.57 GW (PIB, Aug 2026); ~1.7 GW end-2025 (CBRE) | E8: Coverage (7 markets vs national), IT vs gross MW, timing | F8: Use C&W for city splits; quote 1.6–1.8 GW range | G8: Rebase every six months
A9: 5 | B9: Colocation vacancy | C9: 14.9% (C&W) | D9: 2.8% (JLL) | E9: Different definitions of vacancy | F9: Avoid using vacancy as a model input without stating the source | G9: —
A10: 6 | B10: Global DC electricity 2024 | C10: 415 TWh (IEA Apr 2025) | D10: 485 TWh (IEA 2026 update) | E10: Revised baseline | F10: Use the 2026 update for new work; atlas still shows 415 | G10: Update atlas Ch 2 chart
A11: 7 | B11: Power-station water, non-Karnataka states | C11: 2.2 L/kWh (simulator, Reports 4–6) | D11: 2.8–3.4 L/kWh (Report 12 proxies for MH, TG, UP); 3.0 national default | E11: Report 12 recomputed from the FY25 generation mix | F11: Use Report 12 values | G11: Update simulator input
A12: 8 | B12: Karnataka power-station water | C12: ~1.5 L/kWh (Reports 4–6) | D12: 1.5–2.2 L/kWh (Report 12 proxy); 1.8 used in Example C | E12: Report 12 range based on 48% RE share | F12: Use 1.8 as central value | G12: —
A13: 9 | B13: Group-captive renewable landed cost | C13: ₹5.5–7/kWh (Report 8) | D13: ₹6.5–7.5/kWh landed incl. wheeling, losses, banking and demand (Report 12) | E13: Report 12 adds delivery charges and demand charge | F13: Use Report 12 build-up | G13: —
A14: 10 | B14: Third-party open access landed cost | C14: ₹6.5–8/kWh (Report 8) | D14: ₹8.5–10/kWh once CSS, AS and residual demand are added (Report 12) | E14: Report 12 includes state surcharges | F14: Use Report 12 build-up | G14: —
A15: 11 | B15: Hyderabad adiabatic annual WUE | C15: 0.45 L/kWh (Report 12 planning value) | D15: 0.31 L/kWh (atlas Ch 12 hourly model on average temperatures) | E15: Average temperatures miss heatwaves; report adds margin | F15: Plan with 0.45 | G15: Calibrate with ISHRAE TMY
A16: 12 | B16: Peak-hour reduction from "dry at noon" | C16: Halves peak hour with an 11:00–16:00 window (Report 12 text) | D16: Only 67 → 63 kL/h with 11:00–16:00 on Report 12's own profile; 67 → 47 kL/h with 10:00–18:00 | E16: 16:00–17:00 hours stay hot | F16: Use a window to ~18:00 | G16: —
... A21: 17 | B21: Tamil Nadu policy status | C21: Lapsed 31 Mar 2026 (Report 9) | D21: — | E21: — | F21: Treat incentives as unavailable until a successor is notified | G21: Track TN notifications

Sheet Data gaps
A1: Data gaps and how to close them
A2: Sorted by priority.
A4: # | B4: Gap | C4: Why it matters | D4: Who to ask / where | E4: Instrument | F4: Affects (Register IDs, chapters) | G4: Priority
A5: 1 | B5: Substation spare capacity (MVA headroom) | C5: Binding constraint for every site; power scores rest on tariff and judgement | D5: MSETCL, TANTRANSCO, KPTCL, TGTRANSCO, APTRANSCO, UPPTCL, HVPNL, DTL, GETCO, WBSETCL, KSEB-T, OPTCL, RVPN, MPPTCL, CSPTCL; CTUIL (ISTS GNA margins); Grid-India ATC/TTC | E5: Load-flow / connectivity study request | F5: R10-02, R10-12; Ch 10 | G5: High
A6: 2 | B6: EHV node names and distances | C6: All 50 site distances are estimates | D6: STU single-line diagrams; CEA/CTUIL transmission maps | E6: Map check | F6: R10-02; Ch 10 filter | G6: High
A7: 3 | B7: Block-level groundwater categories | C7: Only Bengaluru, Chennai, Haryana and national figures are reported | D7: IN-GRES (ingres.iith.ac.in), CGWB 2025 assessment | E7: Portal download | F7: R4-02, R10-06; Ch 10 water filter | G7: High
A8: 4 | B8: Operator WUE / PUE (metered) | C8: No national dataset; most Indian operators publish neither | D8: Nxtra, CtrlS, Yotta, Sify, STT GDC, AdaniConneX, NTT India; Karnataka plant-wise filings | E8: ESG/BRSR requests; Karnataka disclosures | F8: R6-07, R12-03, R11-06 | G8: High
A9: 5 | B9: Hourly climate (typical-year files) | C9: Wet-mode hours, free-cooling hours, design temperatures are approximations | D9: ISHRAE / ASHRAE TMY for 8+ cities | E9: Licence | F9: R3-08, R10-02, R12-11, R12-14 | G9: High
A10: 6 | B10: Tariff conflicts and missing orders | C10: MSEDCL, KERC differ across reports; DERC, APERC energy, Gujarat demand slabs, WB energy, Rajasthan, MP mapping, Kerala demand unverified | D10: MERC Case 217/2024 and 2026 orders; KERC; DERC; APERC; GERC; WBERC; RERC; MPERC; KSERC | E10: Regulator PDFs | F10: R7-11, R10-04, R10-05, R12-15 | G10: High
A11: 7 | B11: CSS, additional surcharge and wheeling for MH and KA | C11: Needed for open-access landed cost | D11: MERC tables 446–447; KERC OA orders | E11: Regulator PDFs | F11: R12-16 | G11: Medium
A12: 8 | B12: Water permits and allocations for named DC projects | C12: No verified Indian figures found (Navi Mumbai, Chennai, Hyderabad, Vizag, Greater Noida, Hoskote) | D12: State PCBs (CTE/CTO), MIDC, CMWSSB, HMWSSB, BWSSB, GVMC; MoEFCC PARIVESH | E12: RTI; portal downloads | F12: R12-12; Ch 12 | G12: Medium
A13: 9 | B13: Hourly and marginal grid emission factors | C13: No official hourly or marginal factor for India | D13: CEA; Grid-India; SLDCs | E13: Policy request | F13: R5-04 | G13: Medium
A14: 10 | B14: Hourly DC load data | C14: All hourly profiles are modelled | D14: Grid-India / SLDCs; DISCOM AMR data | E14: Data-sharing MoU | F14: R12-14, R4 day model | G14: Medium
A15: 11 | B15: Plant-level power-station water | C15: Grid water intensity is modelled from norms and studies | D15: CEA; plant CTO returns; WRI India | E15: RTI; WRI satellite method | F15: R12-08 | G15: Medium
A16: 12 | B16: State electricity requirement tables | C16: State DC shares use extrapolated denominators | D16: 20th EPS mid-term review state tables (CEA) | E16: Publication | F16: R11-16 | G16: Medium
... A25: 21 | B25: Measured network latency | C25: Latency uses straight-line distance × 1.4 | D25: RIPE Atlas; operators | E25: Measurement | F25: R10-10 | G25: Low

Sheet Sources
A1: Sources
A2: Links captured by the research runs. Reports 1–11 named many sources without links; those are listed without one.
A4: # | B4: Source | C4: Used in | D4: Link
A5: 1 | B5: LBNL 2024 US Data Center Energy Usage Report | C5: Report 12 (Verified) | D5: https://eta-publications.lbl.gov/sites/default/files/2024-12/lbnl-2024-united-states-data-center-energy-usage-report_1.pdf
A6: 2 | B6: Uptime Institute Global Data Center Survey 2025 | C6: Report 12 (Verified); Key numbers | D6: https://datacenter.uptimeinstitute.com/rs/711-RIA-145/images/2025.Annual.Survey.Report.pdf?version=0
A7: 3 | B7: Google: Measuring the environmental impact of delivering AI (arXiv 2508.15734) | C7: Reports 2, 6, 12 | D7: https://arxiv.org/pdf/2508.15734
A8: 4 | B8: Google data-centre efficiency | C8: Report 12 | D8: https://datacenters.google/efficiency/
A9: 5 | B9: Microsoft datacenter efficiency | C9: Report 12 | D9: https://datacenters.microsoft.com/sustainability/efficiency/
A10: 6 | B10: Microsoft: zero-water cooling blog (Dec 2024) | C10: Reports 3, 12 | D10: https://www.microsoft.com/en-us/microsoft-cloud/blog/2024/12/09/sustainable-by-design-next-generation-datacenters-consume-zero-water-for-cooling/
A11: 7 | B11: Li, Yang, Islam & Ren, Making AI Less "Thirsty" (ACM) | C11: Reports 6, 12 | D11: https://dl.acm.org/doi/10.1145/3724499
A12: 8 | B12: NTT DATA ESG environment data | C12: Report 12 | D12: https://www.nttdata.com/global/en/about-us/sustainability/esg-data/environment-data
A13: 9 | B13: Down To Earth: India's digital thirst | C13: Reports 4, 6, 12 | D13: https://www.downtoearth.org.in/science-technology/indias-digital-thirst-what-data-centre-giants-arent-saying-about-their-water-use
A14: 10 | B14: CEEW & Systemiq, Scaling India's Data Centre Ecosystem (Feb 2026) | C14: Reports 9, 11, 12 | D14: https://www.ceew.in/sites/default/files/ceew-data-centre-study-web-ready-final.pdf
A15: 11 | B15: Karnataka DC Policy 2026–31 (The News Minute) | C15: Reports 4, 9, 12 | D15: https://www.thenewsminute.com/karnataka/karnatakas-new-data-centre-policy-puts-water-energy-in-focus-what-does-it-say
A16: 12 | B16: MoEFCC S.O. 3305(E) thermal plant norms (CPCB) | C16: Reports 5, 12 | D16: https://cpcb.nic.in/uploads/Thermal_Power_Plant_overview.pdf
... A58: 54 | B58: WELL Labs; KSPCB; Karnataka IT department (Bengaluru DC water) | C58: Report 4 | D58: (no link captured)
