Workbook

Sheet Index
A1: India data centres: all report tables in one place
A2: 259 tables from Reports 1–12, the simulator and the key-numbers sheet. Click a title to jump to it. Tabs R1–R12 hold every table copied from the full research reports. The "Atlas R1-R9" tab keeps extra tables built from the atlas charts and calculators for Reports 1–9 (chart data, capex build-ups, state scores), and the Simulator and Key numbers tabs hold the atlas model inputs.
A4: # | B4: Report | C4: Table ID | D4: Title (click to open) | E4: Rows | F4: Columns | G4: Source | H4: Sheet | I4: Data basis | J4: How it is used in the atlas | K4: What it is used to derive
A5: 1 | B5: Report 1 · Types of data centre | C5: R1-T01 | D5: Data-centre types by ownership and business model | E5: 6 | F5: 7 | G5: Report 1 (full research report) · 1. Types of Data Centre › 1.1 Deep analysis of the types: what exists, what dominates globally, and why | H5: R1 | I5: Mixed: sourced figures plus estimates | J5: Ch 1 "Type explorer" cards (how it works, cost, strengths, users) and the Type finder rules. | K5: Which business model fits a project size and workload.
A6: 2 | B6: Report 1 · Types of data centre | C6: R1-T02 | D6: Uptime Tiers: redundancy, availability and downtime | E6: 4 | F6: 7 | G6: Report 1 (full research report) · 1. Types of Data Centre › 1.1 Deep analysis of the types: what exists, what dominates globally, and why | H6: R1 | I6: Source-derived (reported, not re-verified) | J6: Ch 1 "What a Tier buys you" downtime clock. | K6: Downtime hours a year = (1 − availability) × 8,760 per Tier.
A7: 3 | B7: Report 1 · Types of data centre | C7: R1-T03 | D7: Cooling approaches: density, efficiency and water | E7: 5 | F7: 6 | G7: Report 1 (full research report) · 1. Types of Data Centre › 1.1 Deep analysis of the types: what exists, what dominates globally, and why | H7: R1 | I7: Mixed: sourced figures plus estimates | J7: Ch 3 cooling comparison text; density limits used in the Rack inspector bands. | K7: Practical rack-density ceiling per cooling method.
A8: 4 | B8: Report 1 · Types of data centre | C8: R1-T04 | D8: Global market share and installed capacity by type (2024–2026) | E8: 11 | F8: 3 | G8: Report 1 (full research report) · 1. Types of Data Centre › 1.1 Deep analysis of the types: what exists, what dominates globally, and why | H8: R1 | I8: Source-derived (reported, not re-verified) | J8: Ch 1 headline numbers and "Who owns the world's capacity" chart; Key numbers. | K8: Global growth and hyperscale share trend to set India in context.
A9: 5 | B9: Report 1 · Types of data centre | C9: R1-T05 | D9: India vs global capacity | E9: 7 | F9: 4 | G9: Report 1 (full research report) · 1. Types of Data Centre › 1.2 Indian perspective: which types to build, why, and how | H9: R1 | I9: Source-derived (reported, not re-verified) | J9: Ch 1 and Overview context; Key numbers (India operational capacity, pipeline). | K9: India's share of global capacity; range of Indian capacity estimates.
A10: 6 | B10: Report 1 · Types of data centre | C10: R1-T06 | D10: Key Indian hubs (Cushman & Wakefield, H1 2026) | E10: 8 | F10: 4 | G10: Report 1 (full research report) · 1. Types of Data Centre › 1.2 Indian perspective: which types to build, why, and how | H10: R1 | I10: Source-derived (reported, not re-verified) | J10: Ch 1 "India by city" chart; Ch 9 map (live and pipeline MW); Ch 10 demand scores; Ch 11 starting point. | K10: City shares, pipeline-to-stock ratios, forecast anchor (1,789 MW).
A11: 7 | B11: Report 1 · Types of data centre | C11: R1-T07 | D11: State policies: key terms | E11: 7 | F11: 4 | G11: Report 1 (full research report) · 1. Types of Data Centre › 1.2 Indian perspective: which types to build, why, and how | H11: R1 | I11: Source-derived (reported, not re-verified) | J11: Superseded by Report 9 tables; feeds Ch 9 policy register. | K11: Early comparison of state incentives.
A12: 8 | B12: Report 2 · AI vs conventional | C12: R2-T01 | D12: Electricity split by subsystem and facility class | E12: 4 | F12: 5 | G12: Report 2 (full research report) · Section 1: Anatomy of Data Centre Consumption › 1.1 Electricity breakdown by subsystem | H12: R2 | I12: Illustrative / framework / author judgement | J12: Ch 2 "Where the power goes, by facility class" chart. | K12: Overhead share of energy by facility class; PUE build-up.
A13: 9 | B13: Report 2 · AI vs conventional | C13: R2-T02 | D13: Server power split: conventional CPU vs AI accelerated | E13: 5 | F13: 3 | G13: Report 2 (full research report) · Section 1: Anatomy of Data Centre Consumption › 1.2 Inside the IT load: CPUs, GPUs, memory, storage and networking | H13: R2 | I13: Illustrative / framework / author judgement | J13: Ch 2 text on IT-load anatomy (reference). | K13: Share of rack power going to accelerators.
A14: 10 | B14: Report 2 · AI vs conventional | C14: R2-T03 | D14: Efficiency metrics: PUE, WUE, CUE and ERE | E14: 4 | F14: 3 | G14: Report 2 (full research report) · Section 1: Anatomy of Data Centre Consumption › 1.3 Efficiency metrics: PUE, WUE, CUE and ERE | H14: R2 | I14: Source-derived (reported, not re-verified) | J14: Ch 2 and Ch 8 metric definitions; Key numbers (PUE 1.54, Google 1.09, MeitY <1.35). | K14: PUE and WUE benchmarks for calculators.
A15: 11 | B15: Report 2 · AI vs conventional | C15: R2-T04 | D15: Water per AI query: a contested range | E15: 4 | F15: 3 | G15: Report 2 (full research report) · Section 1: Anatomy of Data Centre Consumption › 1.4 Water consumption: direct and indirect | H15: R2 | I15: Source-derived (reported, not re-verified) | J15: Ch 6 and Ch 12 "Water per AI prompt" charts. | K15: Water per prompt with different boundaries.
A16: 12 | B16: Report 2 · AI vs conventional | C16: R2-T05 | D16: US data-centre electricity (LBNL 2024) | E16: 4 | F16: 3 | G16: Report 2 (full research report) · Section 1: Anatomy of Data Centre Consumption › 1.6 Global and regional electricity consumption | H16: R2 | I16: Source-derived (reported, not re-verified) | J16: Ch 2 context text (reference only). | K16: US growth path as a comparison for India.
... A263: 259 | B263: Key numbers (all reports) | C263: KEY-T01 | D263: Key numbers cheat sheet | E263: 42 | F263: 3 | G263: Atlas Key numbers (all reports) | H263: Key numbers | I263: Mixed: sourced figures plus estimates | J263: Key numbers cheat sheet (searchable list) at the end of the atlas. | K263: Quick reference for the most-used figures; each row names its source.
A265: Tables per report
B266: Report 1 · Types of data centre | C266: =COUNTIF($B$5:$B$263,B266) -> 7
B267: Report 2 · AI vs conventional | C267: =COUNTIF($B$5:$B$263,B267) -> 9
B268: Report 3 · Cooling | C268: =COUNTIF($B$5:$B$263,B268) -> 15
B269: Report 4 · Bengaluru water and power | C269: =COUNTIF($B$5:$B$263,B269) -> 8
B270: Report 5 · Carbon | C270: =COUNTIF($B$5:$B$263,B270) -> 8
B271: Report 6 · Water impact | C271: =COUNTIF($B$5:$B$263,B271) -> 22
B272: Report 7 · Unit economics | C272: =COUNTIF($B$5:$B$263,B272) -> 24
B273: Report 8 · Green data centres | C273: =COUNTIF($B$5:$B$263,B273) -> 12
B274: Report 9 · State policies | C274: =COUNTIF($B$5:$B$263,B274) -> 4
B275: Report 10 · Where to build | C275: =COUNTIF($B$5:$B$263,B275) -> 22
B276: Report 11 · Forecast to 2035 | C276: =COUNTIF($B$5:$B$263,B276) -> 28
B277: Report 12 · Water and energy | C277: =COUNTIF($B$5:$B$263,B277) -> 28
... B280: Key numbers (all reports) | C280: =COUNTIF($B$5:$B$263,B280) -> 1
B281: Total | C281: =SUM(C266:C280) -> 259

Sheet How to read
A1: How these tables feed the atlas
A2: Every table carries three lines under its title: data basis, how it is used in the atlas, and what it is used to derive. The Index repeats them as filterable columns.
A4: Data basis
A5: Category | B5: Meaning | C5: How to treat it
A6: Source-derived, verified | B6: Figures checked against the primary document during the research (Report 12 labelled these one by one). | C6: Safe to cite; still note the date.
A7: Source-derived (reported, not re-verified) | B7: Figures taken from a named source (consultancy, regulator, company, IEA, etc.) as cited in the report, without a check against the original. | C7: Cite with the source; confirm against the original before decisions.
A8: Mixed: sourced figures plus estimates | B8: A table combining reported numbers with analyst estimates or ranges (for example EHV distances or design temperatures alongside tariffs). | C8: Use the sourced columns as data and the estimated ones as placeholders.
A9: Proxy / estimate | B9: Engineering ranges, analogues, typical values or assumptions standing in for missing Indian data. | C9: Indicative only; replace with measured or official data when available.
A10: Illustrative / framework / author judgement | B10: Scorecards, indices, weights, maturity levels, thresholds and recommendations created by the research series. | C10: A method, not data; change the weights or scores to suit your view.
A11: Calculated (model output) | B11: Results of the series' formulas (worked examples, capex stacks, LCOD, forecasts, rankings, water balances). | C11: Only as good as the inputs; rerun when inputs change.
A13: Count of tables by report and basis (live)
A14: Report | B14: Source-derived, verified | C14: Source-derived (reported, not re-verified) | D14: Mixed: sourced figures plus estimates | E14: Proxy / estimate | F14: Illustrative / framework / author judgement | G14: Calculated (model output) | H14: Total
A15: Report 1 · Types of data centre | B15: =COUNTIFS(Index!$B$5:$B$263,$A15,Index!$I$5:$I$263,B$14) -> 0 | C15: =COUNTIFS(Index!$B$5:$B$263,$A15,Index!$I$5:$I$263,C$14) -> 5 | D15: =COUNTIFS(Index!$B$5:$B$263,$A15,Index!$I$5:$I$263,D$14) -> 2 | E15: =COUNTIFS(Index!$B$5:$B$263,$A15,Index!$I$5:$I$263,E$14) -> 0 | F15: =COUNTIFS(Index!$B$5:$B$263,$A15,Index!$I$5:$I$263,F$14) -> 0 | G15: =COUNTIFS(Index!$B$5:$B$263,$A15,Index!$I$5:$I$263,G$14) -> 0 | H15: =SUM(B15:G15) -> 7
A16: Report 2 · AI vs conventional | B16: =COUNTIFS(Index!$B$5:$B$263,$A16,Index!$I$5:$I$263,B$14) -> 0 | C16: =COUNTIFS(Index!$B$5:$B$263,$A16,Index!$I$5:$I$263,C$14) -> 4 | D16: =COUNTIFS(Index!$B$5:$B$263,$A16,Index!$I$5:$I$263,D$14) -> 2 | E16: =COUNTIFS(Index!$B$5:$B$263,$A16,Index!$I$5:$I$263,E$14) -> 0 | F16: =COUNTIFS(Index!$B$5:$B$263,$A16,Index!$I$5:$I$263,F$14) -> 3 | G16: =COUNTIFS(Index!$B$5:$B$263,$A16,Index!$I$5:$I$263,G$14) -> 0 | H16: =SUM(B16:G16) -> 9
A17: Report 3 · Cooling | B17: =COUNTIFS(Index!$B$5:$B$263,$A17,Index!$I$5:$I$263,B$14) -> 0 | C17: =COUNTIFS(Index!$B$5:$B$263,$A17,Index!$I$5:$I$263,C$14) -> 6 | D17: =COUNTIFS(Index!$B$5:$B$263,$A17,Index!$I$5:$I$263,D$14) -> 6 | E17: =COUNTIFS(Index!$B$5:$B$263,$A17,Index!$I$5:$I$263,E$14) -> 2 | F17: =COUNTIFS(Index!$B$5:$B$263,$A17,Index!$I$5:$I$263,F$14) -> 1 | G17: =COUNTIFS(Index!$B$5:$B$263,$A17,Index!$I$5:$I$263,G$14) -> 0 | H17: =SUM(B17:G17) -> 15
A18: Report 4 · Bengaluru water and power | B18: =COUNTIFS(Index!$B$5:$B$263,$A18,Index!$I$5:$I$263,B$14) -> 0 | C18: =COUNTIFS(Index!$B$5:$B$263,$A18,Index!$I$5:$I$263,C$14) -> 1 | D18: =COUNTIFS(Index!$B$5:$B$263,$A18,Index!$I$5:$I$263,D$14) -> 1 | E18: =COUNTIFS(Index!$B$5:$B$263,$A18,Index!$I$5:$I$263,E$14) -> 1 | F18: =COUNTIFS(Index!$B$5:$B$263,$A18,Index!$I$5:$I$263,F$14) -> 1 | G18: =COUNTIFS(Index!$B$5:$B$263,$A18,Index!$I$5:$I$263,G$14) -> 4 | H18: =SUM(B18:G18) -> 8
A19: Report 5 · Carbon | B19: =COUNTIFS(Index!$B$5:$B$263,$A19,Index!$I$5:$I$263,B$14) -> 0 | C19: =COUNTIFS(Index!$B$5:$B$263,$A19,Index!$I$5:$I$263,C$14) -> 2 | D19: =COUNTIFS(Index!$B$5:$B$263,$A19,Index!$I$5:$I$263,D$14) -> 4 | E19: =COUNTIFS(Index!$B$5:$B$263,$A19,Index!$I$5:$I$263,E$14) -> 0 | F19: =COUNTIFS(Index!$B$5:$B$263,$A19,Index!$I$5:$I$263,F$14) -> 1 | G19: =COUNTIFS(Index!$B$5:$B$263,$A19,Index!$I$5:$I$263,G$14) -> 1 | H19: =SUM(B19:G19) -> 8
A20: Report 6 · Water impact | B20: =COUNTIFS(Index!$B$5:$B$263,$A20,Index!$I$5:$I$263,B$14) -> 0 | C20: =COUNTIFS(Index!$B$5:$B$263,$A20,Index!$I$5:$I$263,C$14) -> 5 | D20: =COUNTIFS(Index!$B$5:$B$263,$A20,Index!$I$5:$I$263,D$14) -> 3 | E20: =COUNTIFS(Index!$B$5:$B$263,$A20,Index!$I$5:$I$263,E$14) -> 1 | F20: =COUNTIFS(Index!$B$5:$B$263,$A20,Index!$I$5:$I$263,F$14) -> 5 | G20: =COUNTIFS(Index!$B$5:$B$263,$A20,Index!$I$5:$I$263,G$14) -> 8 | H20: =SUM(B20:G20) -> 22
A21: Report 7 · Unit economics | B21: =COUNTIFS(Index!$B$5:$B$263,$A21,Index!$I$5:$I$263,B$14) -> 0 | C21: =COUNTIFS(Index!$B$5:$B$263,$A21,Index!$I$5:$I$263,C$14) -> 6 | D21: =COUNTIFS(Index!$B$5:$B$263,$A21,Index!$I$5:$I$263,D$14) -> 3 | E21: =COUNTIFS(Index!$B$5:$B$263,$A21,Index!$I$5:$I$263,E$14) -> 1 | F21: =COUNTIFS(Index!$B$5:$B$263,$A21,Index!$I$5:$I$263,F$14) -> 0 | G21: =COUNTIFS(Index!$B$5:$B$263,$A21,Index!$I$5:$I$263,G$14) -> 14 | H21: =SUM(B21:G21) -> 24
A22: Report 8 · Green data centres | B22: =COUNTIFS(Index!$B$5:$B$263,$A22,Index!$I$5:$I$263,B$14) -> 0 | C22: =COUNTIFS(Index!$B$5:$B$263,$A22,Index!$I$5:$I$263,C$14) -> 5 | D22: =COUNTIFS(Index!$B$5:$B$263,$A22,Index!$I$5:$I$263,D$14) -> 1 | E22: =COUNTIFS(Index!$B$5:$B$263,$A22,Index!$I$5:$I$263,E$14) -> 2 | F22: =COUNTIFS(Index!$B$5:$B$263,$A22,Index!$I$5:$I$263,F$14) -> 3 | G22: =COUNTIFS(Index!$B$5:$B$263,$A22,Index!$I$5:$I$263,G$14) -> 1 | H22: =SUM(B22:G22) -> 12
A23: Report 9 · State policies | B23: =COUNTIFS(Index!$B$5:$B$263,$A23,Index!$I$5:$I$263,B$14) -> 0 | C23: =COUNTIFS(Index!$B$5:$B$263,$A23,Index!$I$5:$I$263,C$14) -> 3 | D23: =COUNTIFS(Index!$B$5:$B$263,$A23,Index!$I$5:$I$263,D$14) -> 0 | E23: =COUNTIFS(Index!$B$5:$B$263,$A23,Index!$I$5:$I$263,E$14) -> 0 | F23: =COUNTIFS(Index!$B$5:$B$263,$A23,Index!$I$5:$I$263,F$14) -> 1 | G23: =COUNTIFS(Index!$B$5:$B$263,$A23,Index!$I$5:$I$263,G$14) -> 0 | H23: =SUM(B23:G23) -> 4
A24: Report 10 · Where to build | B24: =COUNTIFS(Index!$B$5:$B$263,$A24,Index!$I$5:$I$263,B$14) -> 0 | C24: =COUNTIFS(Index!$B$5:$B$263,$A24,Index!$I$5:$I$263,C$14) -> 1 | D24: =COUNTIFS(Index!$B$5:$B$263,$A24,Index!$I$5:$I$263,D$14) -> 16 | E24: =COUNTIFS(Index!$B$5:$B$263,$A24,Index!$I$5:$I$263,E$14) -> 0 | F24: =COUNTIFS(Index!$B$5:$B$263,$A24,Index!$I$5:$I$263,F$14) -> 1 | G24: =COUNTIFS(Index!$B$5:$B$263,$A24,Index!$I$5:$I$263,G$14) -> 4 | H24: =SUM(B24:G24) -> 22
A25: Report 11 · Forecast to 2035 | B25: =COUNTIFS(Index!$B$5:$B$263,$A25,Index!$I$5:$I$263,B$14) -> 0 | C25: =COUNTIFS(Index!$B$5:$B$263,$A25,Index!$I$5:$I$263,C$14) -> 5 | D25: =COUNTIFS(Index!$B$5:$B$263,$A25,Index!$I$5:$I$263,D$14) -> 3 | E25: =COUNTIFS(Index!$B$5:$B$263,$A25,Index!$I$5:$I$263,E$14) -> 5 | F25: =COUNTIFS(Index!$B$5:$B$263,$A25,Index!$I$5:$I$263,F$14) -> 1 | G25: =COUNTIFS(Index!$B$5:$B$263,$A25,Index!$I$5:$I$263,G$14) -> 14 | H25: =SUM(B25:G25) -> 28
A26: Report 12 · Water and energy | B26: =COUNTIFS(Index!$B$5:$B$263,$A26,Index!$I$5:$I$263,B$14) -> 4 | C26: =COUNTIFS(Index!$B$5:$B$263,$A26,Index!$I$5:$I$263,C$14) -> 0 | D26: =COUNTIFS(Index!$B$5:$B$263,$A26,Index!$I$5:$I$263,D$14) -> 6 | E26: =COUNTIFS(Index!$B$5:$B$263,$A26,Index!$I$5:$I$263,E$14) -> 5 | F26: =COUNTIFS(Index!$B$5:$B$263,$A26,Index!$I$5:$I$263,F$14) -> 1 | G26: =COUNTIFS(Index!$B$5:$B$263,$A26,Index!$I$5:$I$263,G$14) -> 12 | H26: =SUM(B26:G26) -> 28
... A29: Key numbers (all reports) | B29: =COUNTIFS(Index!$B$5:$B$263,$A29,Index!$I$5:$I$263,B$14) -> 0 | C29: =COUNTIFS(Index!$B$5:$B$263,$A29,Index!$I$5:$I$263,C$14) -> 0 | D29: =COUNTIFS(Index!$B$5:$B$263,$A29,Index!$I$5:$I$263,D$14) -> 1 | E29: =COUNTIFS(Index!$B$5:$B$263,$A29,Index!$I$5:$I$263,E$14) -> 0 | F29: =COUNTIFS(Index!$B$5:$B$263,$A29,Index!$I$5:$I$263,F$14) -> 0 | G29: =COUNTIFS(Index!$B$5:$B$263,$A29,Index!$I$5:$I$263,G$14) -> 0 | H29: =SUM(B29:G29) -> 1
A30: Total | B30: =SUM(B15:B29) -> 4 | C30: =SUM(C15:C29) -> 74 | D30: =SUM(D15:D29) -> 52 | E30: =SUM(E15:E29) -> 22 | F30: =SUM(F15:F29) -> 28 | G30: =SUM(G15:G29) -> 79 | H30: =SUM(H15:H29) -> 259
A32: Report → atlas chapter → what the atlas derives
A33: Report | B33: Atlas chapter and tools | C33: Main things the atlas derives from it
A34: Report 1 · Types | B34: Ch 1: type explorer, type finder, Tier clock, capacity-share and India-by-city charts | C34: Which type to build; downtime per Tier; India in global context
A35: Report 2 · AI vs conventional | B35: Ch 2: energy split chart, rack inspector, density chart, workload table, comparison tables | C35: Rack power consequences; AI vs conventional design differences
A36: Report 3 · Cooling | B36: Ch 3: cooling chain, warm-water explorer, cooling selector, heat-rejection and liquid tables; simulator PUE/WUE functions | C36: Cooling design per city and density; PUE and WUE inputs
A37: Report 4 · Bengaluru | B37: Ch 4: campus calculator, water comparisons, 1 GW scaling, 24-hour day | C37: Energy, MVA, water and share of Karnataka resources per campus
A38: Report 5 · Carbon | B38: Ch 5: TWh-seven-ways chart, Karnataka hourly curve, load-shift calculator, five-factor scorecard | C38: Carbon and water per TWh by source, time and place
A39: Report 6 · Water impact | B39: Ch 6: tower water balance, seasonal chart, scarcity footprint, impact scorecard, water you can picture | C39: Withdrawal vs consumption; scarcity-weighted impact; thresholds
A40: Report 7 · Unit economics | B40: Ch 7: build-cost chart, capex stacks, LCOD calculator, tornado, GPU-hour calculator; simulator costs | C40: Capex/MW, LCOD, break-even rent, GPU-hour cost, returns
A41: Report 8 · Green | B41: Ch 8: twelve dimensions, green upgrade calculator, abatement chart, PUE thresholds, maturity radar | C41: Payback and abatement cost of going green
A42: Report 9 · State policies | B42: Ch 9: policy table, India map, attractiveness index, validity and incentive charts; simulator incentives | C42: State ranking and incentive value
A43: Report 10 · Where to build | B43: Ch 10: ranking engine (filters, min–max, weights, Monte Carlo), map and city table; worked-example workbook | C43: City scores, tiers and stability by use case
A44: Report 11 · Forecast | B44: Ch 11: forecast engine (CAGR, S-curve, pipeline), electricity, carbon, cost, GPU, water and city outputs | C44: Capacity and impacts to 2035 with uncertainty band
A45: Report 12 · Water & energy | B45: Ch 12: power-vs-water chart, hourly day, 8,760-hour histogram, grid water, cost-vs-water, peaks, tower and site calculators | C45: Direct vs indirect water, peaks, landed power cost by procurement route

Sheet R1
A1: Report 1 · Types of data centre
A2: 7 tables. Source line under each title; "Note" gives the context sentence from the report.
A4: R1-T01 Data-centre types by ownership and business model
A5: Source: Report 1 (full research report) · 1. Types of Data Centre › 1.1 Deep analysis of the types: what exists, what dominates globally, and why
A6: Data basis: Mixed: sourced figures plus estimates
A7: Used in atlas: Ch 1 "Type explorer" cards (how it works, cost, strengths, users) and the Type finder rules.
A8: Used to derive: Which business model fits a project size and workload.
A9: Type | B9: How it works | C9: Typical scale / density | D9: Cost structure | E9: Advantages | F9: Disadvantages | G9: Typical users
A10: Enterprise / on-premises | B10: Organisation owns and runs its own facility (server room up to a corporate campus) | C10: Under 1 MW to about 20 MW; modal rack about 7.5 kW (Uptime 2025) | D10: All capex borne by the owner; opex for power, staff and maintenance; low utilisation is common | E10: Full control, data sovereignty, custom compliance | F10: Poor economies of scale, older and less efficient plant, hard to upgrade for AI density | G10: Banks, government, defence, large manufacturers, hospitals
A11: Retail colocation | B11: Operator leases racks, cages or suites with power, cooling and security; tenant brings servers | C11: Facilities of 5–50 MW; customers take 1 rack to under 1 MW | D11: Tenant pays monthly rent per rack/kW plus interconnection; operator carries building capex | E11: Converts capex to opex, carrier-neutral interconnection, fast deployment | F11: Higher per-kW price, less control, contract lock-in | G11: Enterprises, BFSI, network operators, SaaS firms
A12: Wholesale colocation / build-to-suit | B12: Operator leases whole halls or buildings, often to a single hyperscaler on long leases | C12: 10–100+ MW per building, campuses of hundreds of MW to GW | D12: Operator funds the build (often project-financed against an anchor lease); tenant often pays power at cost plus rent | E12: Speed to market for hyperscalers, bankable long-term cash flows | F12: Concentrated tenant risk, thin margins, power-procurement exposure | G12: AWS, Microsoft, Google, Meta, Oracle, AI labs, neoclouds
A13: Hyperscale (self-built) | B13: Cloud/internet giants design, own and operate their own campuses | C13: Single buildings of 30–100+ MW; campuses of 1 GW+; AI halls at 50–130+ kW/rack | D13: Huge capex funded from balance sheet; lowest unit cost thanks to scale | E13: Lowest cost per MW, custom hardware, best PUE (larger sites average about 1.44, per Uptime 2025) | F13: Very concentrated power and water demand, local opposition, long grid queues | G13: AWS, Microsoft, Google, Meta, Alibaba, Tencent, Oracle
A14: Managed services / cloud | B14: Provider runs the infrastructure and sells compute or storage "as a service" (IaaS/PaaS, managed hosting, GPU-as-a-Service) | C14: Sits on top of hyperscale or colocation capacity | D14: Customer pays per use; provider absorbs capex | E14: Elastic, no hardware ownership, fast access to GPUs | F14: Egress costs, vendor lock-in, data-residency questions | G14: Start-ups, digital natives, enterprises moving to hybrid
A15: Edge / micro | B15: Small facilities close to users or devices (telecom central offices, towers, factory floors, cities) | C15: 50 kW to about 5 MW; micro/containerised units at single-rack scale | D15: Low capex per site but high cost per kW; many sites to manage | E15: Low latency, data reduction, local resilience | F15: Hard to operate at scale, uneven demand, limited GPU density | G15: Telcos (5G/MEC), CDNs/OTT, retail, payments, industrial IoT
A18: R1-T02 Uptime Tiers: redundancy, availability and downtime
A19: Source: Report 1 (full research report) · 1. Types of Data Centre › 1.1 Deep analysis of the types: what exists, what dominates globally, and why
A20: Data basis: Source-derived (reported, not re-verified)
A21: Used in atlas: Ch 1 "What a Tier buys you" downtime clock.
A22: Used to derive: Downtime hours a year = (1 − availability) × 8,760 per Tier.
A23: Uptime Tier | B23: Redundancy | C23: Concurrently maintainable? | D23: Fault tolerant? | E23: Design-intent availability | F23: Approx. annual downtime | G23: Typical use
A24: Tier I – Basic capacity | B24: N, single path | C24: No | D24: No | E24: 99.671% | F24: ~28.8 hours | G24: Small business, dev/test
A25: Tier II – Redundant components | B25: N+1 components, single path | C25: No | D25: No | E25: 99.741% | F25: ~22 hours | G25: Non-critical enterprise
A26: Tier III – Concurrently maintainable | B26: N+1, multiple paths (one active) | C26: Yes | D26: No | E26: 99.982% | F26: ~1.6 hours | G26: Colocation baseline, cloud, BFSI production
A27: Tier IV – Fault tolerant | B27: 2N / 2(N+1), multiple active paths | C27: Yes | D27: Yes | E27: 99.995% | F27: ~26 minutes | G27: Trading, critical health, national systems
A30: R1-T03 Cooling approaches: density, efficiency and water
A31: Source: Report 1 (full research report) · 1. Types of Data Centre › 1.1 Deep analysis of the types: what exists, what dominates globally, and why
A32: Data basis: Mixed: sourced figures plus estimates
A33: Used in atlas: Ch 3 cooling comparison text; density limits used in the Rack inspector bands.
A34: Used to derive: Practical rack-density ceiling per cooling method.
A35: Cooling approach | B35: How it works | C35: Practical rack density | D35: Efficiency | E35: Water use | F35: Status
A36: Air (CRAC/CRAH, hot/cold aisle, economisers) | B36: Chilled or outside air moved through racks | C36: Up to about 15–20 kW/rack (SBI notes air nears its limits beyond about 15 kW) | D36: Fleet average PUE 1.54 (Uptime 2025); new sites about 1.48 | E36: High if evaporative towers are used; low with dry coolers | F36: Still most of the installed base: about 75% use perimeter air (Uptime 2025)
A37: Rear-door heat exchangers / hybrid | B37: Liquid-cooled coil on the rack door removes heat from the exhaust air | C37: About 20–50 kW | D37: Better than room air | E37: Moderate | F37: Most common "first step" into liquid
A38: Direct-to-chip (DLC) | B38: Cold plates on CPUs/GPUs; coolant loop to a CDU; residual air cooling | C38: 30–130+ kW | D38: PUE about 1.1–1.25 achievable | E38: Low with closed loops and dry coolers | F38: Becoming the standard for AI; about 22% of operators used direct liquid cooling in 2025 (Uptime)
A39: Single-phase immersion | B39: Servers submerged in a dielectric fluid | C39: 50–150+ kW | D39: Very low cooling overhead | E39: Very low | F39: Niche; suits edge, crypto and HPC
A40: Two-phase immersion | B40: Fluid boils at the chip and condenses | C40: 100–250+ kW | D40: Lowest overhead | E40: Very low | F40: Early stage; fluid cost and environmental concerns
A43: R1-T04 Global market share and installed capacity by type (2024–2026)
A44: Source: Report 1 (full research report) · 1. Types of Data Centre › 1.1 Deep analysis of the types: what exists, what dominates globally, and why
A45: Data basis: Source-derived (reported, not re-verified)
A46: Used in atlas: Ch 1 headline numbers and "Who owns the world's capacity" chart; Key numbers.
A47: Used to derive: Global growth and hyperscale share trend to set India in context.
A48: Metric | B48: Value | C48: Source and date
A49: Global data centre capacity | B49: ~103 GW (2025) → ~200 GW (2030), 14% CAGR; ~100 GW added 2026–30 | C49: JLL 2026 Global Data Center Outlook (Jan 2026)
A50: Hyperscale share of capacity | B50: 41% (2024) → 44% (Q1 2025) → nearly half, about 48% (early 2026) → 67% projected by 2031 | C50: Synergy Research (2024; Jun 2025; Apr 2026)
A51: Non-hyperscale colocation share | B51: 22% (2024–25) → 20% (2026); absolute capacity still growing | C51: Synergy Research
A52: Enterprise on-premises share | B52: 56% (2018) → 34% (Q1 2025) → 32% (2026) → 19% by 2031; absolute capacity stable and slightly boosted by on-prem GPUs | C52: Synergy Research
A53: Number of hyperscale data centres | B53: 1,189 (Q1 2025); about 800 more in the known pipeline (2026) | C53: Synergy Research
A54: Concentration | B54: 20 metro/state markets hold 60% of hyperscale capacity; Northern Virginia 11%, Beijing 6% | C54: Synergy Research (Aug 2026)
A55: Big three cloud providers' share of hyperscale capacity | B55: 58% | C55: Synergy Research (Q3 2025)
A56: Hyperscale quarterly capex | B56: ~$142 bn in Q3 2025 | C56: Synergy Research via The Register (Dec 2025)
A57: Global occupancy | B57: ~97%; 77% of capacity under construction pre-leased | C57: JLL (Jan 2026)
A58: APAC capacity | B58: 32 GW → 57 GW by 2030; colocation growing ~19% CAGR; on-prem declining 6% | C58: JLL (Jan 2026)
A59: Liquid-cooling adoption | B59: ~22% of operators use direct liquid cooling; ~75% perimeter air | C59: Uptime Institute 2025 survey
A62: R1-T05 India vs global capacity
A63: Source: Report 1 (full research report) · 1. Types of Data Centre › 1.2 Indian perspective: which types to build, why, and how
A64: Note: India vs. global capacity
A65: Data basis: Source-derived (reported, not re-verified)
A66: Used in atlas: Ch 1 and Overview context; Key numbers (India operational capacity, pipeline).
A67: Used to derive: India's share of global capacity; range of Indian capacity estimates.
A68: Metric | B68: India | C68: Global | D68: Source and date
A69: Operational capacity | B69: ~1.5 GW (MeitY/PIB, 2025); 1,123 MW (JLL, H1 2025); ~1.7 GW (CBRE, end-2025); 1,789 MW in top seven markets (C&W, H1 2026) | C69: ~103 GW (2025) | D69: PIB 13 Mar 2026; JLL; CBRE Apr 2026; C&W Sep 2026
A70: Growth | B70: 375 MW (2020) → ~1.5 GW (2025); 440 MW added in 2025; ~500 MW expected in 2026 | C70: 14% CAGR to 2030 | D70: PIB; CBRE
A71: 2030 outlook | B71: 3,860 MW pipeline (509 MW under construction, 3,351 MW planned) to 2030 (C&W); total of ~4.5–6.5 GW (CEEW base cases), ~6.5 GW colocation (SBI), up to ~8 GW (Jefferies) | C71: ~200 GW | D71: C&W; CEEW; SBI; JLL
A72: Development capital needed | B72: US$29.9 bn through 2030 | C72: Up to US$3 trn by 2030 | D72: C&W; JLL
A73: Share of national electricity | B73: ~0.5–0.8% (2024) → ~2.6% (2030) | C73: ~1.5% (2024) → under 3% (2030) | D73: CEEW; IEA
A74: Penetration | B74: ~825,333 people per MW of capacity, among the lowest in APAC | C74: n/a | D74: C&W (Sep 2026)
A75: Colocation vacancy | B75: 14.9% (H1 2026) | C75: ~3% (97% occupancy, per JLL) | D75: C&W; JLL
A78: R1-T06 Key Indian hubs (Cushman & Wakefield, H1 2026)
A79: Source: Report 1 (full research report) · 1. Types of Data Centre › 1.2 Indian perspective: which types to build, why, and how
A80: Note: Key hubs (Cushman & Wakefield, H1 2026)
A81: Data basis: Source-derived (reported, not re-verified)
A82: Used in atlas: Ch 1 "India by city" chart; Ch 9 map (live and pipeline MW); Ch 10 demand scores; Ch 11 starting point.
A83: Used to derive: City shares, pipeline-to-stock ratios, forecast anchor (1,789 MW).
A84: Hub | B84: Operational (MW) | C84: Share of 3,860 MW pipeline | D84: Why it is there
A85: Mumbai / Navi Mumbai | B85: 890 (about 50%; expected to pass 1 GW by end-2026) | C85: 45% (1,726 MW) | D85: Most subsea cables, BFSI demand, power availability
A86: Chennai | B86: 214 | C86: 9% (368 MW) | D86: Second subsea cable hub; Tamil Nadu policy
A87: Delhi NCR / Noida | B87: 183 | C87: 10% (387 MW) | D87: Northern demand centre, government, UP incentives
A88: Bengaluru | B88: 162 | C88: 3% (100 MW) | D88: IT/SaaS demand; constrained by water and land
A89: Hyderabad | B89: 151 | C89: 18% (710 MW) | D89: Inland, low seismic risk, Telangana power policy, Microsoft/AWS regions
A90: Pune | B90: 133 | C90: 7% (258 MW) | D90: Mumbai overflow, AWS/Microsoft presence
A91: Kolkata | B91: 22 | C91: 2% | D91: Eastern gateway; WB policy promotes edge
A92: Visakhapatnam (emerging) | B92: Small today | C92: Gigawatt-scale campuses announced | D92: New east-coast subsea gateway, Andhra Pradesh incentives
A95: R1-T07 State policies: key terms
A96: Source: Report 1 (full research report) · 1. Types of Data Centre › 1.2 Indian perspective: which types to build, why, and how
A97: Note: State policies (key terms)
A98: Data basis: Source-derived (reported, not re-verified)
A99: Used in atlas: Superseded by Report 9 tables; feeds Ch 9 policy register.
A100: Used to derive: Early comparison of state incentives.
A101: State | B101: Policy | C101: Key incentives | D101: Notes
A102: Maharashtra | B102: IT/ITeS Policy 2023 (data centres treated as IT units, with essential-service status) | C102: 100% stamp-duty exemption; electricity-duty exemption (described as permanent in 2023, while a June 2026 notification cites 20 years); ₹1/unit power subsidy for 5 years outside Zone I; renewable open access | D102: Hosts about 50% of capacity; green data centre parks policy reported
A103: Tamil Nadu | B103: Data Centre Policy 2021 | C103: Eligibility above ₹500 crore and at least 30% renewables; 100% electricity-tax subsidy for 5 years; dual grid for 50 MW+; land and stamp-duty concessions | D103: Policy window ended March 2026; no extension notified as of April 2026
A104: Telangana | B104: Data Centres Policy 2016 | C104: Power at cost of generation; dual grid; exemption from power cuts; renewable open access; building-fee and lease-rental rebates | D104: S&P Global rates it India's most attractive data centre policy package
A105: Uttar Pradesh | B105: DC Policy 2021 → new policy approved 6 Jul 2026 | C105: 2021: capital and interest subsidies, 100% stamp duty, 10-year electricity-duty waiver, wheeling/transmission relief (about ₹21,343 crore of projects approved). 2026: targets 2 GW and more than ₹2 trillion, covers edge data centres, AI-compute and green incentives, 50% renewables target by 2030 | D105: Noida is the main northern hub
A106: West Bengal | B106: DC Policy 2021 | C106: 100% stamp duty and registration; 5-year electricity-duty waiver; industrial tariff; dual grid; preferential incentives for edge data centres in IT/industrial parks | D106: 5-year term ran to about September 2026
A107: Andhra Pradesh | B107: DC Policy 4.0 (2024–29) | C107: 100% net SGST reimbursement or 10% capital subsidy; 100% stamp duty; industrial tariff; dual grid via PPP with VGF; custom packages for mega projects over 50 MW | D107: Target given as 200 MW in the G.O. and "up to 1 GW" in the annexure; Vizag is the anchor
A108: Gujarat | B108: IT/ITeS Policy 2022–27 | C108: Capex support of 25% up to ₹150 crore for greenfield Tier III+ data centres; ₹1/unit power subsidy for 5 years; 100% electricity-duty reimbursement for 5 years | D108: Jamnagar mega-campus

Sheet R2
A1: Report 2 · AI vs conventional
A2: 9 tables. Source line under each title; "Note" gives the context sentence from the report.
A4: R2-T01 Electricity split by subsystem and facility class
A5: Source: Report 2 (full research report) · Section 1: Anatomy of Data Centre Consumption › 1.1 Electricity breakdown by subsystem
A6: Note: Typical percentage splits by facility class. These are the author's synthesis, derived from PUE ranges and the IEA component shares. They are indicative, not measured.
A7: Data basis: Illustrative / framework / author judgement
A8: Used in atlas: Ch 2 "Where the power goes, by facility class" chart.
A9: Used to derive: Overhead share of energy by facility class; PUE build-up.
A10: Subsystem | B10: Legacy/small enterprise (PUE about 1.8–2.0) | C10: Typical enterprise/colo (PUE about 1.5–1.6) | D10: Hyperscale cloud (PUE about 1.1–1.2) | E10: AI liquid-cooled (PUE about 1.1–1.3)
A11: IT load (servers, storage, network) | B11: 50–55% | C11: 62–67% | D11: 83–91% | E11: 77–90%
A12: Cooling (chillers, CRAH/CRAC, pumps, towers, fans) | B12: 30–40% | C12: 25–30% | D12: 5–10% | E12: 7–15% (CDUs, pumps, dry coolers, residual air)
A13: Power conversion and distribution losses (UPS, transformers, PDUs) | B13: 8–12% | C13: 6–8% | D13: 2–5% | E13: 3–6%
A14: Lighting and other (security, offices, humidification) | B14: 2–5% | C14: 1–3% | D14: about 1% | E14: about 1%
A17: R2-T02 Server power split: conventional CPU vs AI accelerated
A18: Source: Report 2 (full research report) · Section 1: Anatomy of Data Centre Consumption › 1.2 Inside the IT load: CPUs, GPUs, memory, storage and networking
A19: Note: Applying the IEA shares to IT load alone, a typical facility's IT power splits about 85% servers, about 7% storage and about 7% networking. Within a server, the split depends on the class:
A20: Data basis: Illustrative / framework / author judgement
A21: Used in atlas: Ch 2 text on IT-load anatomy (reference).
A22: Used to derive: Share of rack power going to accelerators.
A23: Component | B23: Conventional CPU server (indicative) | C23: AI accelerated server/rack
A24: CPUs | B24: about 40–55% of server power | C24: about 10–15% (host CPUs, e.g. Grace)
A25: GPUs/accelerators | B25: 0% (or a small inference card) | C25: about 60–75% (e.g. 72 × B200 at about 1.0–1.2 kW = about 72–86 kW of a 120 kW NVL72 rack)
A26: Memory (DRAM/HBM) | B26: about 15–25% | C26: HBM is counted in the GPU package; host DRAM is a few %
A27: Local storage (SSD/HDD) | B27: about 5–10% | C27: a few %
A28: Fans, PSU losses, NICs | B28: about 10–20% | C28: Switch trays (NVLink), NICs/DPUs and PSU losses about 10–15%; fans are minimal with liquid cooling
A31: R2-T03 Efficiency metrics: PUE, WUE, CUE and ERE
A32: Source: Report 2 (full research report) · Section 1: Anatomy of Data Centre Consumption › 1.3 Efficiency metrics: PUE, WUE, CUE and ERE
A33: Data basis: Source-derived (reported, not re-verified)
A34: Used in atlas: Ch 2 and Ch 8 metric definitions; Key numbers (PUE 1.54, Google 1.09, MeitY <1.35).
A35: Used to derive: PUE and WUE benchmarks for calculators.
A36: Metric | B36: Definition | C36: Benchmarks
A37: PUE (Power Usage Effectiveness) | B37: Total facility energy ÷ IT energy | C37: Uptime 2025 global weighted average 1.54 (1.58 in 2023, 1.56 in 2024). Facilities built in the last five years: 1.48. Sites over 20 MW: about 1.44. Many new high-latitude sites: 1.3 or better. Google fleet: 1.09 (2025). MeitY AI-cloud tenders in India require below 1.35.
A38: WUE (Water Usage Effectiveness) | B38: Site water (L) ÷ IT energy (kWh) | C38: Microsoft FY24: 0.30 L/kWh, down 39% from 0.49 in 2021. Microsoft's regional values range from about 1.52 (Arizona) to 0.02 (Singapore), as reported secondhand.
A39: CUE (Carbon Usage Effectiveness) | B39: kgCO₂e ÷ IT kWh | C39: Determined mainly by the grid mix and whether emissions are counted location-based or market-based
A40: ERE (Energy Reuse Effectiveness) | B40: (Total energy − reused energy) ÷ IT energy | C40: Can fall below 1.0 with district-heat export, which matters for liquid-cooled AI halls producing 40–60 °C return water
A43: R2-T04 Water per AI query: a contested range
A44: Source: Report 2 (full research report) · Section 1: Anatomy of Data Centre Consumption › 1.4 Water consumption: direct and indirect
A45: Note: Per-AI-query water: a contested range.
A46: Data basis: Source-derived (reported, not re-verified)
A47: Used in atlas: Ch 6 and Ch 12 "Water per AI prompt" charts.
A48: Used to derive: Water per prompt with different boundaries.
A49: Estimate | B49: Water per query | C49: Scope
A50: UC Riverside, "Making AI Less Thirsty" (Li, Yang, Islam, Ren) | B50: 500 mL per about 10–50 medium GPT-3 responses (about 10–50 mL each); GPT-3 training about 5.4 million L total, of which 700,000 L on site | C50: Scope 1 + 2, GPT-3-era hardware, Microsoft US data centres
A51: Google Gemini (May 2025) | B51: 0.26 mL (0.15 mL under a narrower method) | C51: On-site cooling only
A52: OpenAI (Altman, June 2025) | B52: about 0.32 mL | C52: Unspecified, likely on-site
A53: Mistral Le Chat LCA | B53: about 45 mL per 400-token response | C53: Full lifecycle
A56: R2-T05 US data-centre electricity (LBNL 2024)
A57: Source: Report 2 (full research report) · Section 1: Anatomy of Data Centre Consumption › 1.6 Global and regional electricity consumption
A58: Note: LBNL 2024 *United States Data Center Energy Usage Report* (December 2024):
A59: Data basis: Source-derived (reported, not re-verified)
A60: Used in atlas: Ch 2 context text (reference only).
A61: Used to derive: US growth path as a comparison for India.
A62: Year | B62: US data-centre electricity | C62: Share of US electricity
A63: 2014 | B63: 58 TWh | C63: —
A64: 2018 | B64: 76 TWh | C64: 1.9%
A65: 2023 | B65: 176 TWh | C65: 4.4%
A66: 2028 (scenarios) | B66: 325–580 TWh | C66: 6.7–12.0%
A69: R2-T06 Energy per workload
A70: Source: Report 2 (full research report) · Section 1: Anatomy of Data Centre Consumption › 1.7 Energy per workload
A71: Data basis: Source-derived (reported, not re-verified)
A72: Used in atlas: Ch 2 "Energy per workload" table.
A73: Used to derive: Energy per query/training run; continuous MW for inference.
A74: Workload | B74: Energy | C74: Source/notes
A75: Google web search | B75: about 0.3 Wh | C75: Google's oft-cited 2009 figure; likely lower today
A76: Median Gemini Apps text prompt | B76: 0.24 Wh (0.10 Wh active-chip-only), 0.03 gCO₂e | C76: Google, May 2025; 33× lower energy and 44× lower carbon than May 2024. Not independently verified, and prompt length is undisclosed.
A77: ChatGPT average query | B77: about 0.34 Wh | C77: Sam Altman, June 2025; no methodology
A78: GPT-4o typical query (500 output tokens) | B78: about 0.3 Wh | C78: Epoch AI, February 2025 (replacing the 2023 figure of about 3 Wh)
A79: Long-input query (10k / 100k tokens) | B79: about 2.5 Wh / about 40 Wh | C79: Epoch AI
A80: Reasoning/agentic queries | B80: several to tens of Wh | C80: Third-party benchmarks; high uncertainty
A83: R2-T07 Master comparison: AI vs conventional data centres
A84: Source: Report 2 (full research report) · Section 2: AI Data Centre vs Conventional Data Centre › 2.1 Master comparison table
A85: Data basis: Mixed: sourced figures plus estimates
A86: Used in atlas: Ch 2 "Conventional vs AI" comparison table.
A87: Used to derive: Design differences that drive cooling, power and capex choices.
A88: Attribute | B88: Conventional (enterprise/colo/cloud) | C88: AI data centre (training/inference)
A89: Primary workloads | B89: Web, databases, ERP, storage, virtualised and cloud VMs, streaming | C89: Large-model training (synchronous, weeks to months); inference (latency-sensitive, bursty); fine-tuning
A90: Compute | B90: x86/Arm CPU servers, about 300–1,000 W per server | C90: GPUs/TPUs/ASICs: H100 700 W; B200 1,000–1,200 W; B300 about 1.4 kW; 8-GPU HGX node about 5.6–10 kW
A91: Rack density | B91: about 5–15 kW (Uptime: few above 30 kW; average about 7–8 kW) | C91: about 40 kW (H100 air-cooled) → 120–132 kW (GB200 NVL72) → 135–142 kW (GB300) → about 190–230 kW (Vera Rubin, 2026) → about 600 kW to 1 MW (Kyber, from 2027)
A92: Cooling | B92: Air (CRAH/CRAC, hot/cold aisle containment), chillers, evaporative towers | C92: Direct-to-chip liquid (CDUs, facility water loops), rear-door heat exchangers, immersion; residual air about 10–15%
A93: Power distribution | B93: 400/415 V AC to rack, 12 V server PSUs, centralised UPS | C93: 415/480 V AC with 54 VDC busbars and power shelves now; 800 VDC from about 2027; BESS for smoothing; on-site gas generation and nuclear PPAs
A94: Networking | B94: North–south dominant; 10–100 GbE; leaf–spine | C94: East–west dominant; NVLink scale-up (72 → 576 GPUs); InfiniBand or Ultra Ethernet scale-out at 400–800G per GPU; optics-heavy; many times more fibre
A95: Facility | B95: 1–50 MW (the IEA treats 25 MW as conventional); raised floors | C95: 100 MW to multi-GW campuses; slab floors with rack positions over 1.3 t; taller halls for overhead busways and piping
A96: Siting | B96: Latency-first, close to users and internet exchanges | C96: Power-first for training (cheap, available GW); metro or edge for inference
A97: Capex per MW | B97: JLL shell and core about $11.3m/MW (2026 global average). India: INR 50–55 crore/MW (SBI) | C97: Plus up to $25m/MW tenant AI fit-out (JLL), before GPUs. India: up to INR 75 crore/MW (SBI)
A98: Reliability | B98: Tier III/IV, 2N power, concurrent maintainability | C98: Training: increasingly N+1 or Tier II/III-like, relying on checkpoints. Inference: Tier III+
A99: Load profile | B99: Flat, diurnal and variable; low utilisation | C99: Training: sustained near-peak with sub-second synchronised swings. Inference: bursty
... A103: Grid and regulatory exposure | B103: Moderate | C103: High: NERC Level 3 alert, large-load tariffs, interconnection queues, local opposition
A106: R2-T08 Compute hardware and power
A107: Source: Report 2 (full research report) · Section 2: AI Data Centre vs Conventional Data Centre › 2.3 Compute hardware and power
A108: Data basis: Mixed: sourced figures plus estimates
A109: Used in atlas: Ch 2 "Rack density and chip power" chart and Rack inspector.
A110: Used to derive: kW per rack and per GPU used in sizing.
A111: Platform | B111: Power | C111: Notes
A112: Nvidia H100 SXM | B112: 700 W | C112: 8-GPU node about 5.6 kW (GPUs) to about 10 kW (node); racks about 30–40 kW
A113: Nvidia B200 | B113: 1,000 W (HGX) to 1,200 W (NVL72) | C113: Air-cooled HGX B200 racks about 60 kW
A114: GB200 NVL72 | B114: about 120 kW (Nvidia); 132 kW nominal (HPE: 115 kW liquid + 17 kW air); peak electrical design power about 192 kW | C114: 72 GPUs + 36 Grace CPUs; about 1.36 t; eight 33 kW power shelves
A115: GB300 NVL72 | B115: 135 kW (Nvidia Mission Control); 142 kW (Nvidia/Vertiv reference) | C115: B300 at about 1.4 kW per GPU
A116: Vera Rubin NVL144 (2026) | B116: about 190–230 kW (industry reports) | C116: Transitional AC/54 VDC or 800 VDC input
A117: Rubin Ultra / Kyber (2027+) | B117: about 600 kW (GTC 2025), designed for up to 1 MW racks | C117: Kyber redesigned at GTC 2026; SemiAnalysis reports a possible slip to 2028
A118: Google TPU (Trillium, Ironwood); AWS Trainium | B118: Lower per chip than Nvidia's flagships; liquid-cooled pods at scale | C118: Google says Ironwood is 30× more efficient than its first TPU
...

Sheet R3
A1: Report 3 · Cooling
A2: 15 tables. Source line under each title; "Note" gives the context sentence from the report.
A4: R3-T01 Accelerator power trend per GPU
A5: Source: Report 3 (full research report) · 1. Fundamentals › 1.1 Why cooling is needed
A6: Note: Accelerator power trend (per GPU):
A7: Data basis: Mixed: sourced figures plus estimates
A8: Used in atlas: Ch 3 cooling chain and GPU power figures.
A9: Used to derive: Why air cooling stops working as GPUs pass ~1 kW.
A10: GPU | B10: Year | C10: Max TDP | D10: Cooling implication
A11: Nvidia H100 SXM | B11: 2022–23 | C11: 700 W | D11: Air-coolable (HGX); DLC optional
A12: Nvidia B200 | B12: 2024–25 | C12: 1,000 W (up to ~1,200 W in GB200 configurations) | D12: Air HGX options exist; GB200 NVL72 rack is liquid
A13: Nvidia B300 (Blackwell Ultra) | B13: H2 2025 | C13: 1,400 W (liquid bin); 1,100 W air bin | D13: GB300 NVL72 requires DLC; DGX B300 has an air-cooled 14.5 kW variant
A14: Nvidia Rubin (Vera Rubin NVL72/NVL144) | B14: H2 2026 | C14: ~1,800–2,300 W (industry estimates; not formally confirmed) | D14: 100% liquid; 45°C inlet water
A15: Rubin Ultra (Kyber NVL576) | B15: H2 2027 | C15: — | D15: ~600 kW per rack, 100% liquid, no fans, 800 VDC
A16: Leading GPUs (Dell'Oro projection) | B16: 2029 | C16: >4,000 W | D16: Two-phase or embedded cooling likely needed
A19: R3-T02 Heat transfer properties of cooling fluids
A20: Source: Report 3 (full research report) · 1. Fundamentals › 1.2 Heat transfer properties: why liquid wins
A21: Note: Heat removed is Q = ṁ·cp·ΔT. What matters is how much heat a given volume of fluid can carry per degree of temperature rise. The values below are standard engineering values at about 25°C.
A22: Data basis: Source-derived (reported, not re-verified)
A23: Used in atlas: Ch 3 "Why liquid wins" chart.
A24: Used to derive: Flow needed to move heat with air vs water.
A25: Fluid | B25: Specific heat (kJ/kg·K) | C25: Density (kg/m³) | D25: Volumetric heat capacity (kJ/m³·K) | E25: Relative to air | F25: Notes
A26: Air | B26: ~1.0 | C26: ~1.2 | D26: ~1.2 | E26: 1× | F26: Low thermal conductivity (~0.026 W/m·K)
A27: Water | B27: ~4.18 | C27: ~1,000 | D27: ~4,180 | E27: ~3,500× | F27: Conductivity ~0.6 W/m·K; conductive and corrosive, so loops must be sealed and treated
A28: PG25 (25% propylene glycol) | B28: ~3.9 | C28: ~1,020 | D28: ~4,000 | E28: ~3,300× | F28: Standard technology cooling system (TCS) fluid for cold plates; biocide and freeze protection
A29: Synthetic or hydrocarbon dielectric oil (single-phase immersion) | B29: ~1.9–2.3 | C29: ~800–850 | D29: ~1,600–1,900 | E29: ~1,400× | F29: Higher viscosity means slower convection
A30: Fluorocarbon or HFO dielectric (two-phase) | B30: ~1.1–1.3 | C30: ~1,400–1,700 | D30: ~1,700–2,000 (sensible) | E30: — | F30: Boiling absorbs latent heat (~90–140 kJ/kg); heat transfer coefficient 5–10× single-phase
A33: R3-T03 ASHRAE air-cooled classes (IT inlet air)
A34: Source: Report 3 (full research report) · 1. Fundamentals › 1.3 ASHRAE TC 9.9 thermal guidelines (5th edition, 2021)
A35: Note: Air-cooled classes (IT inlet air):
A36: Data basis: Source-derived (reported, not re-verified)
A37: Used in atlas: Ch 3 reference (ASHRAE classes).
A38: Used to derive: Allowable inlet temperatures; economiser hours.
A39: Class | B39: Recommended | C39: Allowable dry-bulb | D39: Typical use
A40: A1 | B40: 18–27°C | C40: 15–32°C | D40: Enterprise and mission-critical
A41: A2 | B41: 18–27°C | C41: 10–35°C | D41: Volume servers
A42: A3 | B42: 18–27°C | C42: 5–40°C | D42: Extended-range, chillerless designs
A43: A4 | B43: 18–27°C | C43: 5–45°C | D43: Extreme economisation
A44: H1 (high-density) | B44: 18–22°C | C44: 15–25°C | D44: Tightly integrated, high-power air-cooled systems that cannot meet A2
A47: R3-T04 ASHRAE liquid-cooling W classes
A48: Source: Report 3 (full research report) · 1. Fundamentals › 1.3 ASHRAE TC 9.9 thermal guidelines (5th edition, 2021)
A49: Note: Liquid-cooling W classes (facility water supply temperature): the 5th edition renamed W1–W5 by their upper temperature limit. All classes share a 2°C lower bound.
A50: Data basis: Source-derived (reported, not re-verified)
A51: Used in atlas: Ch 3 "Warm-water explorer" (W32–W45 setpoints).
A52: Used to derive: Which heat rejection works at a given facility water temperature.
A53: Class (old name) | B53: Facility water supply | C53: Typical heat rejection
A54: W17 (W1) | B54: 2–17°C | C54: Chillers, with economiser assist
A55: W27 (W2) | B55: 2–27°C | C55: Chillers with large economiser share
A56: W32 (W3) | B56: 2–32°C | C56: Cooling towers or dry coolers; chillers for trim
A57: W40 (new) | B57: 2–40°C | C57: Mostly chiller-free
A58: W45 (W4) | B58: 2–45°C | C58: "Typically operated without chillers": dry coolers year-round in most climates
A59: W+ (W5) | B59: >45°C | C59: Heat reuse and district heating
A62: R3-T05 Key cooling metrics
A63: Source: Report 3 (full research report) · 1. Fundamentals › 1.5 Key metrics
A64: Data basis: Mixed: sourced figures plus estimates
A65: Used in atlas: Ch 3 and simulator PUE/WUE reasoning (reference).
A66: Used to derive: Typical PUE/WUE ranges for calculators.
A67: Metric | B67: Definition | C67: Typical values / notes
A68: PUE | B68: Total facility energy ÷ IT energy | C68: Legacy air: 1.5–1.8; good modern air with economisers: 1.2–1.4; DLC: 1.05–1.2; immersion: ~1.03–1.08 (vendor-reported). The SBI report says cooling "can account for up to 40 percent of total energy usage" in Indian facilities.
A69: pPUE (partial PUE) | B69: (IT + subsystem energy) ÷ IT energy for one subsystem | C69: A cooling pPUE of 1.05–1.15 is excellent
A70: WUE | B70: Annual site water (L) ÷ IT energy (kWh) | C70: 0 (dry) to more than 2 L/kWh (fully evaporative); US average 1.8 L/kWh (LBNL, Shehabi et al., 2016)
A71: kW per rack | B71: Cooling capacity delivered per rack | C71: Uptime 2025: average modal density ~9 kW (up from 8.3 kW); AI racks 40–230 kW, heading to 600 kW+
A72: ΔT | B72: Temperature rise across a coil, server or loop | C72: Air: 10–20 K; TCS: ~10 K. Bigger ΔT means less flow and less pump or fan energy.
A73: Approach temperature | B73: Gap between leaving fluid and its heat sink | C73: Towers: 3–5 K over wet-bulb; dry coolers: 5–10 K over dry-bulb; CDU HX: 2–4 K
A74: Chiller COP / kW per ton | B74: Cooling output ÷ electrical input; 1 ton = 3.517 kW | C74: Water-cooled centrifugal: ~0.5–0.6 kW/ton (COP ~6–7); air-cooled screw: ~1.0–1.2 kW/ton (COP ~3)
A75: IPLV / NPLV | B75: Weighted part-load efficiency (100/75/50/25% load) | C75: Matters because data centre chillers rarely run at full load. India's ECBC data-centre guidance cites, for example, centrifugal chillers ≥1,580 kWr at COP 6.3 and IPLV 7.0.
A78: R3-T06 Chiller types
A79: Source: Report 3 (full research report) · 3. Chilled-water plants and heat rejection › 3.1 Chiller types
A80: Data basis: Mixed: sourced figures plus estimates
A81: Used in atlas: Reference only (chiller choice in Ch 3 text).
A82: Used to derive: Chiller efficiency assumptions.
A83: Type | B83: Compressor | C83: Size range | D83: Typical full-load efficiency | E83: Notes
A84: Air-cooled scroll | B84: Scroll | C84: 50–500 kW | D84: ~1.1–1.3 kW/ton | E84: Small sites, edge
A85: Air-cooled screw | B85: Screw | C85: 300–2,000 kW | D85: ~1.0–1.2 kW/ton | E85: No tower water; often with integrated free-cooling coils
A86: Water-cooled screw | B86: Screw | C86: 500–3,500 kW | D86: ~0.6–0.7 kW/ton | E86: Needs towers
A87: Water-cooled centrifugal | B87: Centrifugal | C87: 1,000–10,000+ kW | D87: ~0.5–0.6 kW/ton | E87: Best at scale
A88: Magnetic-bearing centrifugal (e.g., Danfoss Turbocor compressors) | B88: Oil-free, variable speed | C88: 300–5,000 kW | D88: Full load ~0.55; IPLV can approach ~0.3–0.35 kW/ton | E88: Excellent part-load efficiency and low maintenance
A89: Free-cooling chillers | B89: Any, plus integrated dry coils | C89: — | D89: Compressors off when ambient is ~8–10 K below return water | E89: Very effective at higher water temperatures
A92: R3-T07 Liquid cooling comparison
A93: Source: Report 3 (full research report) · 4. Liquid cooling types › 4.7 Liquid cooling comparison
A94: Data basis: Mixed: sourced figures plus estimates
A95: Used in atlas: Ch 3 "Liquid cooling compared" table.
A96: Used to derive: Density, PUE and maturity per liquid technology.
A97: Attribute | B97: Single-phase DLC | C97: Two-phase DLC | D97: Single-phase immersion | E97: Two-phase immersion | F97: RDHx (active)
A98: Practical rack density | B98: 50–250 kW+ (with air assist) | C98: 100–300 kW+ | D98: 100–250 kW per tank | E98: 200 kW+ per tank | F98: 40–75 kW
A99: Heat to liquid | B99: 70–98% | C99: 70–95% | D99: ~100% | E99: ~100% | F99: 100% at the door (air-side)
A100: Facility water class | B100: W32–W45 | C100: W32–W45 | D100: W32–W45 | E100: W32–W45 | F100: W17–W27 (needs colder water)
A101: PUE (reported range) | B101: 1.05–1.20 | C101: 1.04–1.15 | D101: 1.03–1.08 | E101: 1.01–1.05 | F101: 1.15–1.35
A102: Fluid | B102: PG25 / water (cheap) | C102: Dielectric refrigerant ($$) | D102: Hydrocarbon or synthetic oil ($–$$) | E102: Fluorocarbon or HFO ($$$) | F102: Water
A103: Serviceability | B103: Server-like; QDs | C103: Server-like; pressurised | D103: Lift-out, drain | E103: Sealed tank | F103: Easy
A104: Weight / floor | B104: Heavy racks (1.5–3 t) | C104: Heavy racks | D104: Heavy tanks, low floor density | E104: Heavy tanks | F104: Moderate
A105: OEM support / warranty | B105: Mainstream (Nvidia reference) | C105: Emerging | D105: Improving; check per OEM | E105: Limited | F105: Mainstream
A106: Maturity (2026) | B106: Mainstream for AI | C106: Early commercial | D106: Niche but proven | E106: Niche; PFAS risk | F106: Mature
A107: OCP / standards | B107: OCP ACS cold plate, CDU, UQD specs; ORv3 | C107: OCP ACS two-phase workstream | D107: OCP ACS immersion specs | E107: OCP ACS immersion | F107: OCP Door HX workstream
A110: R3-T08 Natural and alternative cooling
A111: Source: Report 3 (full research report) · 5. Natural and alternative cooling
A112: Data basis: Mixed: sourced figures plus estimates
A113: Used in atlas: Ch 3 text on natural cooling; Ch 12 seawater option.
A114: Used to derive: Relevance of seawater and free cooling for India.
A115: Approach | B115: Flagship examples | C115: How it works | D115: Relevance to India
...

Sheet R4
A1: Report 4 · Bengaluru water and power
A2: 8 tables. Source line under each title; "Note" gives the context sentence from the report.
A4: R4-T01 Assumptions for the three Bengaluru cases
A5: Source: Report 4 (full research report) · 1. Assumptions
A6: Data basis: Proxy / estimate
A7: Used in atlas: Ch 4 campus calculator presets; simulator defaults.
A8: Used to derive: Input assumptions for the three Bengaluru cases.
A9: Parameter | B9: Case A: Colo/enterprise | C9: Case B: Hyperscale/cloud | D9: Case C: AI campus
A10: Design IT load | B10: 20 MW | C10: 50 MW | D10: 100 MW
A11: Cooling | B11: Water-cooled chillers + cooling towers (with water-side economiser) | C11: B1: chillers + cooling towers; B2: adiabatic/hybrid dry coolers | D11: DLC (~80% to liquid) + dry coolers with adiabatic assist
A12: Annual PUE (central / range) | B12: 1.45 / 1.30–1.60 | C12: 1.35 / 1.25–1.45 | D12: 1.20 / 1.15–1.25
A13: Average utilisation of design IT | B13: 70% / 60–85% | C13: 75% / 65–85% | D13: 80% / 70–90%
A14: Design-day PUE (for contract demand) | B14: 1.6 | C14: 1.5 | D14: 1.3
A15: On-site WUE (L/kWh IT) | B15: 1.8 / 1.5–2.0 | C15: B1: 1.6; B2: 0.4 | D15: Dry 0.05; adiabatic 0.2; (evaporative alt. 1.6)
A16: Staff on site | B16: ~150 | C16: ~300 | D16: ~300
A17: Grid water intensity | B17: 1.5 L/kWh (range 1.0–2.5) | C17: same | D17: same
A20: R4-T02 Power calculations by case
A21: Source: Report 4 (full research report) · 2. Power calculations
A22: Note: Contract demand (MVA) ≈ Design IT × design-day PUE ÷ power factor (0.95), plus ~3–5% for offices and losses
A23: Data basis: Calculated (model output)
A24: Used in atlas: Ch 4 calculator outputs (MU, MVA, homes, % of state demand); Key numbers (841 MU, 140 MVA).
A25: Used to derive: Energy, contract demand and share of Karnataka demand per case.
B26: Case A (20 MW) | C26: Case B (50 MW) | D26: Case C (100 MW)
A27: IT energy | B27: 20×0.70×8,760 = 122.6 GWh | C27: 50×0.75×8,760 = 328.5 GWh | D27: 100×0.80×8,760 = 700.8 GWh
A28: Facility energy (central) | B28: 122.6×1.45 = 177.8 MU | C28: 328.5×1.35 = 443.5 MU | D28: 700.8×1.20 = 841.0 MU
A29: Sensitivity range | B29: 136.7–238.3 MU | C29: 355.9–539.8 MU | D29: 705.2–985.5 MU
A30: Average draw | B30: 20.3 MW | C30: 50.6 MW | D30: 96.0 MW
A31: Design peak | B31: 32 MW | C31: 75 MW | D31: 130 MW
A32: Contract demand | B32: ~34–35 MVA | C32: ~80 MVA | D32: ~140 MVA
A33: Supply voltage (KERC norms) | B33: 110 kV | C33: 220 kV | D33: 220 kV, dedicated substation, dual feed
A34: Installed transformer capacity (2N) | B34: ~70 MVA | C34: ~160 MVA | D34: ~280 MVA
A35: Bengaluru household equivalent (1,800 kWh/yr) | B35: ~98,800 | C35: ~246,400 | D35: ~467,200
A36: Share of Karnataka energy (92,550 MU, FY25) | B36: 0.19% | C36: 0.48% | D36: 0.91%
A37: Share of BESCOM sales (~37,000 MU, est.) | B37: 0.48% | C37: 1.2% | D37: 2.3%
A38: Share of state household use (16,089 MU) | B38: 1.1% | C38: 2.8% | D38: 5.2%
... A40: Energy bill at HT-2a (Rs 6.70/kWh + Rs 365/kVA/month) | B40: ~Rs 134 cr/yr | C40: ~Rs 332 cr/yr | D40: ~Rs 625 cr/yr
A43: R4-T03 On-site water by case
A44: Source: Report 4 (full research report) · 3. Water calculations › 3.2 On-site water by case
A45: Note: Formula: annual on-site water (L) = IT energy (kWh) × WUE + staff × 45 L × 365 + landscaping. MLD = annual ML ÷ 365. Population equivalent = MLD × 10⁶ ÷ 135.
A46: Data basis: Calculated (model output)
A47: Used in atlas: Ch 4 water bars and "Water you can picture" (Ch 6).
A48: Used to derive: On-site MLD and people-equivalent per case.
A49: Case / cooling | B49: Cooling water | C49: Domestic + landscaping | D49: Total on-site | E49: Range | F49: People at 135 LPCD
A50: A (WUE 1.8) | B50: 122.6 GWh×1.8 = 220.8 ML/yr = 0.605 MLD | C50: ~0.02 MLD | D50: ~0.62 MLD (226 ML/yr) | E50: 0.43–0.82 MLD | F50: ~4,600
A51: B1 evaporative (1.6) | B51: 525.6 ML/yr = 1.44 MLD | C51: ~0.03 MLD | D51: ~1.47 MLD | E51: 1.1–1.9 MLD | F51: ~10,900
A52: B2 adiabatic (0.4) | B52: 131.4 ML/yr = 0.36 MLD | C52: ~0.03 MLD | D52: ~0.39 MLD | E52: 0.2–0.6 MLD | F52: ~2,900
A53: C dry/closed-loop (0.05) | B53: 35.0 ML/yr = 0.096 MLD | C53: ~0.03 MLD | D53: ~0.13 MLD | E53: 0.06–0.2 MLD | F53: ~930
A54: C adiabatic assist (0.2) | B54: 140.2 ML/yr = 0.38 MLD | C54: ~0.03 MLD | D54: ~0.41 MLD | E54: 0.3–0.6 MLD | F54: ~3,050
A55: C if built with cooling towers (1.6) | B55: 1,121 ML/yr = 3.07 MLD | C55: ~0.03 MLD | D55: ~3.10 MLD | E55: 2.6–3.6 MLD | F55: ~23,000
A58: R4-T04 Indirect water embedded in grid electricity
A59: Source: Report 4 (full research report) · 3. Water calculations › 3.3 Indirect water embedded in grid electricity
A60: Note: Using Raichur's reported actual of ~4.9 m³/MWh would push this towards 2.5. Raichur sits on the Krishna and has been shut during water shortages.
A61: Data basis: Calculated (model output)
A62: Used in atlas: Ch 4 power-station water bar; simulator grid water (KA 1.5 L/kWh).
A63: Used to derive: Indirect water per case.
B64: Case A | C64: Case B | D64: Case C
A65: Indirect water (1.5 L/kWh) | B65: 177.8 GWh → 267 ML/yr = 0.73 MLD | C65: 443.5 GWh → 665 ML/yr = 1.82 MLD | D65: 841 GWh → 1,262 ML/yr = 3.46 MLD
A66: Total footprint (on-site + indirect) | B66: ~1.35 MLD | C66: B1 ~3.3 / B2 ~2.2 MLD | D66: dry ~3.6 / adiabatic ~3.9 MLD
A67: With 100% solar/wind supply | B67: ~0.62 MLD | C67: B1 1.47 / B2 0.39 | D67: 0.13–0.41
A70: R4-T05 Comparison with other Bengaluru and Karnataka water users
A71: Source: Report 4 (full research report) · 4. Comparison with other Bengaluru and Karnataka users
A72: Data basis: Mixed: sourced figures plus estimates
A73: Used in atlas: Ch 4 "Compared with other users" chart.
A74: Used to derive: Data-centre water in context of other users.
A75: User (illustrative scale) | B75: Water (MLD) | C75: Per-unit norm | D75: Power (MU/yr) | E75: Source / status
A76: Case A, 20 MW colo | B76: 0.62 | C76: 1.8 L/kWh IT | D76: 178 | E76: This model
A77: Case B1, 50 MW evaporative | B77: 1.47 | C77: 1.6 L/kWh IT | D77: 444 | E77: This model
A78: Case C, 100 MW DLC | B78: 0.13–0.41 | C78: 0.05–0.2 L/kWh IT | D78: 841 | E78: This model
A79: IT campus, 10 million sq ft (Manyata/ITPL scale, ~100,000 staff) | B79: ~5.5–6.5 (4.5 domestic at 45 LPCD + HVAC towers) | C79: 45 LPCD/employee | D79: ~185 (≈200 kWh/m²/yr) | E79: Estimate from norms
A80: Apartment complex, 1,000 flats | B80: ~0.61 | C80: 135 LPCD × 4.5 persons | D80: ~18 | E80: Norm-based
A81: 500-bed hospital | B81: ~0.23 | C81: ~450 L/bed/day (NBC) | D81: ~15–25 | E81: Norm-based estimate
A82: 300-room luxury hotel | B82: ~0.3 | C82: ~1,000 L/room/day | D82: ~10–15 | E82: Industry-typical estimate
A83: Large mall, ~1 million sq ft | B83: ~0.3–0.5 | C83: — | D83: ~25–35 | E83: Estimate
A84: Brewery, 2 million hl/yr | B84: ~1.7 | C84: UBL: 2.93 kL/kL (FY24), 3.10 kL/kL (FY25) | D84: ~15–20 | E84: UBL reports; plant size illustrative
A85: Soft-drink bottler, 1 million kL/yr | B85: ~4–6 | C85: ~1.5–2.2 L/L industry-typical | D85: ~20–30 | E85: Estimate
A86: Toyota Kirloskar, Bidadi (capacity ~342,000 vehicles) | B86: ~4.7 total (1.73 million m³/yr), ~89–90% recycled or rainwater | C86: 2.94 m³/vehicle (2016-17) | D86: 100% renewable since FY2021 | E86: TKM disclosures
A87: BEL (Bengaluru) | B87: ~2 MLD of BWSSB treated water | C87: — | D87: — | E87: Deccan Herald via BWSSB
A88: 18-hole golf course (dry season) | B88: ~1.5–2.5 | C88: ~5 mm/day on ~40–50 ha | D88: <5 | E88: Estimate
A89: Garment factory (cut-make-trim), 2,000 workers | B89: ~0.1 | C89: Domestic-type use; wet processing 100–200 L/kg elsewhere | D89: ~5–10 | E89: Estimate
A90: BMRCL Namma Metro (96 km) | B90: Small (stations, depot washing) | C90: — | D90: ~65 lakh units/month in 2018-19 (~78 MU/yr); now plausibly ~200 MU; Blue Line alone projected at 152 GWh | E90: BMRCL (2019), IISc–BMRCL study
... A93: Pharma/biotech (Biocon), HAL | B93: Not publicly disaggregated | C93: — | D93: — | E93: Data gap
A96: R4-T06 Where Bengaluru data centres get water today
A97: Source: Report 4 (full research report) · 5. Where Bengaluru data centres get water today
A98: Data basis: Source-derived (reported, not re-verified)
A99: Used in atlas: Ch 4 "The city's water" table.
A100: Used to derive: Sources and prices of water in Bengaluru.
A101: Source | B101: Status for data centres | C101: Key facts
A102: BWSSB Cauvery (Stages I–V) | B102: Used for a few; poorly metered | C102: Stages I–IV ~1,450 MLD; Stage V adds 775 MLD (commissioned Oct 2024), but connection uptake is slow (<1.2 lakh of 4 lakh targeted connections after 18 months). Cauvery allocation is capped. BWSSB industrial tariff Rs 99/kL. Five data centres receive ~129 kL/month in BWSSB records.
A103: Groundwater/borewells | B103: Likely the dominant source (WELL Labs view) | C103: All Bengaluru Urban and Rural assessment units are over-exploited. Bangalore East is at 378.85% (Karnataka Dynamic Ground Water Resources report; 395.0% in IN-GRES 2025-26 data), Devanahalli at 169%, with "no net groundwater available for future use". The whole area is notified under the Karnataka Ground Water Act 2011, so every borewell needs a KGWA/BWSSB permit.
A104: Private tankers | B104: Back-up; unregulated | C104: Tanker water is mostly borewell water from peri-urban villages, which moves the depletion elsewhere.
A105: Treated wastewater (STP/tertiary) | B105: Under-used; no mandate | C105: BWSSB STP capacity ~1,348.5 MLD. Reuse ~825 MLD environmental and ~30 MLD commercial. K&C Valley sends 440 MLD and H-N Valley 210 MLD (secondary treated) to Kolar and Chikkaballapur. Treated water sells at Rs 10–15/kL. Apartment STPs may sell 50% of their output. BWSSB's chair has said there is no mandate for data centres to use recycled water.
A106: Rainwater harvesting / on-site STP | B106: Supplementary | C106: Useful for domestic use and landscaping. Too small and seasonal for evaporative cooling.
A109: R4-T07 Scenarios: added IT capacity vs water (75% utilisation)
A110: Source: Report 4 (full research report) · 6. Will data centre water cause scarcity? › 6.2 Scenarios (75% utilisation; IT energy = 18,000 kWh/day per MW)
A111: Data basis: Calculated (model output)
A112: Used in atlas: Ch 4 "Scaling to 1 GW" chart; Key numbers (~32 MLD).
A113: Used to derive: City-wide water impact of the 1 GW target.
A114: Added IT capacity | B114: Evaporative, WUE 1.8 | C114: Adiabatic, WUE 0.4 | D114: Dry/DLC, WUE 0.05 | E114: Indirect (PUE 1.3, 1.5 L/kWh), outside city
A115: 100 MW | B115: 3.2 MLD (0.11%) | C115: 0.7 MLD (0.02%) | D115: 0.09 MLD | E115: 3.5 MLD
A116: 500 MW | B116: 16.2 MLD (0.54%) | C116: 3.6 MLD (0.12%) | D116: 0.45 MLD | E116: 17.6 MLD
...

Sheet R5
A1: Report 5 · Carbon
A2: 8 tables. Source line under each title; "Note" gives the context sentence from the report.
A4: R5-T01 Lifecycle carbon intensity by technology
A5: Source: Report 5 (full research report) · 1. SOURCE — What Generates the Electron › 1.1 Lifecycle carbon intensity by technology
A6: Data basis: Source-derived (reported, not re-verified)
A7: Used in atlas: Ch 5 "Lifecycle carbon by source" bars.
A8: Used to derive: Carbon of procurement options.
A9: Source | B9: IPCC AR5 lifecycle median (min–max), gCO₂e/kWh | C9: UNECE 2021 range, gCO₂e/kWh | D9: Direct (combustion) share | E9: India-specific note
A10: Coal (pulverised) | B10: 820 (740–910) | C10: 751 (IGCC, US) – 1,095 (PC, China) | D10: Direct 760 (670–870) | E10: Indian subcritical units on high-ash coal: about 0.9–1.1 tCO₂/MWh at the busbar; UNECE notes a plant-by-plant global study at about 1,130 g
A11: Oil | B11: ~720 (secondary compilations) | C11: — | D11: Mostly direct | E11: Negligible in Indian grid
A12: Gas CCGT | B12: 490 (410–650) | C12: 403–513 (92–220 with CCS) | D12: Direct 370 (350–490) | E12: Indian gas fleet runs at low PLF; mostly peaking/balancing
A13: Biomass (dedicated) | B13: 230 (130–420) | C13: — | D13: Biogenic accounting contested | E13: Bagasse co-gen in Karnataka/Maharashtra
A14: Solar PV (utility) | B14: 48 (18–180) | C14: 8–83 | D14: 0 direct | E14: Upstream manufacturing mostly on coal-heavy Chinese grid
A15: CSP | B15: 27 (AR5) | C15: 27–122 | D15: 0 | E15: Marginal in India
A16: Geothermal | B16: 38 (6–79) | C16: — | D16: Some CO₂ from geofluid | E16: Not deployed
A17: Hydropower | B17: 24 (1–2,200) | C17: 6–147 | D17: 0 | E17: Tropical reservoirs can emit large biogenic CH₄; upper tail is real for shallow, warm reservoirs
A18: Wind onshore / offshore | B18: 11 / 12 | C18: 7.8–16 / 12–23 | D18: 0 | E18: Karnataka and Tamil Nadu are major onshore wind states
A19: Nuclear | B19: 12 (3.7–110) | C19: 5.1–6.4 | D19: 0 | E19: NPCIL fleet incl. Kaiga (Karnataka)
A22: R5-T02 Water withdrawal vs consumption by generation source
A23: Source: Report 5 (full research report) · 1. SOURCE — What Generates the Electron › 1.2 Water: withdrawal vs consumption by source
A24: Note: Once-through cooling withdraws a great deal but consumes relatively little. Cooling towers withdraw less but evaporate more.
A25: Data basis: Mixed: sourced figures plus estimates
A26: Used in atlas: Ch 5 "Water consumed by source" bars; grid water in calculators.
A27: Used to derive: Indirect water per kWh by source.
A28: Technology / cooling | B28: Consumption, L/MWh (approx., NREL Macknick et al. 2012 medians, converted from gal/MWh) | C28: Withdrawal, L/MWh | D28: Comment
A29: Coal, cooling tower | B29: ~1,800–2,600 (US); 2,800–4,000+ actual in India | C29: ~2,500–4,000 (US); ~4,000 India | D29: NREL notes tower-cooled plants sit near the ~1,000 gal/MWh (~3,800 L) upper bound
A30: Coal, once-through | B30: ~400–1,000 | C30: 70,000–200,000 (CSE, India) | D30: High thermal-pollution and intake impacts
A31: Coal/gas, dry cooling | B31: ~0–450 (India dry-cooled coal: 450–650 L/MWh) | C31: Low | D31: Efficiency penalty (higher CO₂/MWh)
A32: Nuclear, cooling tower | B32: ~2,500–2,700 | C32: ~4,000–5,000 | D32: Lowest carbon, among highest water
A33: Nuclear, once-through / seawater | B33: ~1,000 (largely seawater) | C33: ~100,000–170,000 | D33: Coastal sites (Kudankulam, Tarapur) avoid freshwater stress
A34: Gas CCGT, cooling tower | B34: ~700–1,000 | C34: ~1,000 | D34: Only the steam cycle (about one-third of output) needs cooling
A35: Gas CCGT, dry | B35: ~10 | C35: ~10
A36: Solar PV | B36: ~20–100 (panel cleaning; higher in dusty Indian conditions) | C36: same | D36: Robotic dry cleaning cuts this further
A37: Wind | B37: ~0–5 | C37: ~0
A38: CSP (trough, wet tower) | B38: ~3,000–3,500 | C38: ~3,500 | D38: Wettest renewable
A39: Biopower (steam, tower) | B39: ~2,000 (operations; crop irrigation can add orders of magnitude) | C39: —
A40: Hydro (reservoir evaporation) | B40: ~13,000 (China avg) to ~245,000 (Mekonnen & Hoekstra 35-plant avg); global mean ~79,000 | C40: Not meaningful | D40: Highly contested (see below)
A43: R5-T03 Country grid carbon intensity
A44: Source: Report 5 (full research report) · 3. LOCATION — Which Grid, Which Margin, Which Basin › 3.1 Country grids (operational, annual average)
A45: Data basis: Mixed: sourced figures plus estimates
A46: Used in atlas: Ch 5 "1 TWh, seven ways" chart.
A47: Used to derive: Carbon of the same TWh on different grids.
A48: Grid | B48: Approx. intensity, gCO₂(e)/kWh | C48: Source/year | D48: 1 TWh ≈
A49: India | B49: 670 (2025); 708 (2024, CO₂-only) | C49: Ember GER 2026/2025 | D49: 0.67–0.71 MtCO₂
A50: China | B50: ~550 | C50: Ember (approx.) | D50: ~0.55 Mt
A51: Asia average | B51: 544 | C51: Ember 2025 | D51: 0.54 Mt
A52: World | B52: 458 (2025); 473 (2024) | C52: Ember | D52: 0.46 Mt
A53: United States | B53: ~370 | C53: Ember (approx.) | D53: ~0.37 Mt
A54: EU-27 | B54: ~210–240 | C54: Ember (approx.) | D54: ~0.22 Mt
A55: France | B55: ~30–60 | C55: Ember/RTE (approx.) | D55: ~0.03–0.06 Mt
A56: Norway | B56: ~20–30 | C56: (approx.) | D56: ~0.02–0.03 Mt
A59: R5-T04 India emission-factor types: average vs marginal
A60: Source: Report 5 (full research report) · 3. LOCATION — Which Grid, Which Margin, Which Basin › 3.3 Average vs marginal; attributional vs consequential
A61: Data basis: Mixed: sourced figures plus estimates
A62: Used in atlas: Ch 5 text on average vs marginal factors.
A63: Used to derive: Which factor to use for reporting vs siting.
A64: Metric | B64: Value (India) | C64: Use
A65: Weighted average (WAEF), FY24-25 | B65: 0.710 t/MWh | C65: Location-based Scope 2; CCTS
A66: Operating margin (OM), FY23-24 | B66: ~0.9+ t/MWh (fossil-only) | C66: Short-run displacement
A67: Build margin (BM), FY23-24 | B67: 0.552 t/MWh | C67: What new capacity looks like
A68: Combined margin (CM), FY23-24 | B68: 0.757 t/MWh | C68: Offset baselines
A69: Short-run marginal at evening peak | B69: ~0.95–1.1 t/MWh (est.) | C69: Consequential impact of new load
A72: R5-T05 Hyperscaler Scope 2: location-based vs market-based
A73: Source: Report 5 (full research report) · 4. CARBON INTENSITY — Definitions, Trajectory and Data-Centre Metrics › 4.4 Hyperscaler disclosures: location-based vs market-based
A74: Data basis: Source-derived (reported, not re-verified)
A75: Used in atlas: Ch 5 Microsoft Scope 2 chart.
A76: Used to derive: Gap between location- and market-based claims.
A77: Company | B77: Disclosure | C77: Location-based | D77: Market-based | E77: Takeaway
A78: Microsoft (2025 report, FY24) | B78: Scope 2, tCO₂e | C78: 4,328,916 (FY20) → 9,955,368 (FY24), +130%; +23% y/y | D78: 456,119 → 259,090, −43% | E78: Electricity use 10.77 → 29.83 TWh. Market-based fell while location-based more than doubled. Asia location-based Scope 2 rose from 0.91 to 2.51 Mt
A79: Microsoft (2026 report, FY25) | B79: Scope 2 | C79: 12030556 | D79: 2707428 | E79: Market-based jump reflects dropping unbundled RECs; not comparable with earlier years
A80: Google (2025 report, CY2024) | B80: Data-centre electricity +27% y/y | C80: (location-based rose with load) | D80: Data-centre energy emissions −12% | E80: 66% hourly CFE; ~12% in APAC; >25 clean projects (2.5 GW) came online
A83: R5-T06 Grid-average water intensity
A84: Source: Report 5 (full research report) · 5. WATER INTENSITY — The Grid's Hidden Water › 5.2 Grid-average water intensity
A85: Data basis: Mixed: sourced figures plus estimates
A86: Used in atlas: Grid water intensity used in Ch 4–6 and simulator (1.5–2.2 L/kWh).
A87: Used to derive: Indirect water per kWh.
A88: Grid | B88: Consumption intensity | C88: Basis
A89: India, all thermal + non-hydro RE (2014) | B89: 2.09 L/kWh (withdrawal 15.9 L/kWh) | C89: IRENA/WRI 2018; *excludes hydro*
A90: India 2027–2030 projections | B90: 1.57–1.94 L/kWh | C90: IRENA/CEA scenarios
A91: India, freshwater thermal only (2018) | B91: ~1.8 L/kWh | C91: Derived: 2.39 bn m³ ÷ ~1,300 TWh (estimate)
A92: India incl. hydro evaporation | B92: Several L/kWh, highly allocation-dependent | C92: One multi-model study says hydro is about one-third of Indian power-sector water consumption
A93: Karnataka mix (used in this series) | B93: ~1.5 L/kWh (excl. hydro) | C93: Estimate: ~45–50% coal at ~3.3 L/kWh + small PV cleaning
A94: US data-centre-weighted indirect (2023) | B94: ~4.5 L/kWh (incl. hydro evaporation) | C94: LBNL 2024 US Data Center Energy Usage Report, as widely cited
A97: R5-T07 Worked matrix: carbon and water per TWh by scenario
A98: Source: Report 5 (full research report) · SYNTHESIS — "Every TWh Is Not the Same": Worked Matrix
A99: Note: For grid cases, losses are 8% for HT supply. For on-site/adjacent supply, losses are about 3–4% (ignored below for simplicity).
A100: Data basis: Calculated (model output)
A101: Used in atlas: Ch 5 "1 TWh of data-centre load, seven ways" chart (carbon and water).
A102: Used to derive: Carbon and water per TWh by supply scenario.
A103: # | B103: Scenario | C103: EF used (t/MWh) | D103: CO₂ per TWh | E103: EWIF (L/kWh) | F103: Water consumed per TWh | G103: Stress weight (basin where water is lost) | H103: Scarcity-weighted (bn L-eq)
A104: a | B104: Indian grid average (CEA WAEF 0.710, +8% losses) | C104: 0.77 | D104: ~770,000 t | E104: 2.17 | F104: ~2.2 bn L | G104: 4 (mixed; ~40% of thermal in high stress) | H104: ~8.7
A105: b | B105: Karnataka consumption mix (est. 0.50, +8%) | C105: 0.54 | D105: ~540,000 t (range 430–600k) | E105: 1.6 | F105: ~1.6 bn L | G105: 4–5 (Krishna/Raichur, Ballari) | H105: ~6.5–8
A106: c | B106: Marginal coal, Indian evening peak (1.0 at part load, +8%) | C106: 1.09 | D106: ~1,090,000 t | E106: 3.8–4.3 (3.5–4.0 at plant) | F106: ~3.8–4.3 bn L | G106: 4–5 | H106: ~15–21
A107: d | B107: Karnataka solar hours, grid — average basis (~0.25–0.30) / marginal basis (coal backing down, ~0.95) | C107: 0.30 / 1.03 | D107: ~300,000 t (avg) / ~1,000,000 t (marginal); ~0 on curtailment days | E107: ~0.8 (avg) | F107: ~0.8 bn L (avg) | G107: 4–5 | H107: ~3–4
A108: e | B108: 24/7 hybrid RE + BESS via group captive/open access (90% hourly CFE; lifecycle ~40 g for the RE part; 10% residual grid at 0.77) | C108: ~0.11 lifecycle (~0.08 operational) | D108: ~110,000 t lifecycle; 100% CFE → ~40,000 t | E108: 0.09 RE + 0.22 residual | F108: ~0.3 bn L | G108: 4–5 (residual only) | H108: ~1.2
A109: f1 | B109: France (nuclear-dominant grid) | C109: 0.03–0.06 | D109: ~30,000–60,000 t | E109: ~1–2.5 (many plants on rivers/sea) | F109: ~1–2.5 bn L | G109: 2–3 (Rhône/Loire summer stress) | H109: ~3–6
A110: f2 | B110: Nordic hydro (Norway) | C110: 0.02–0.03 | D110: ~20,000–30,000 t | E110: 0 (run-of-river) to >10 (gross-evaporation allocation) | F110: contested: ~0–10+ bn L | G110: 1 | H110: ~0–10
A111: g | B111: US PJM / Northern Virginia (~0.37–0.40) | C111: 0.38 | D111: ~380,000–420,000 t | E111: ~2 (thermo-electric) to 4.5 (LBNL DC-weighted incl. hydro) | F111: ~2–4.5 bn L | G111: 2 | H111: ~4–9
A112: h | B112: Gas CCGT (IPCC lifecycle 490; direct ~370) | C112: 0.49 | D112: ~490,000 t (direct ~370,000) | E112: 0.75 (tower) / 0.01 (dry) | F112: ~0.75 bn L (tower) | G112: site-specific (2–5) | H112: ~1.5–3.8
A113: i | B113: Nuclear with cooling towers | C113: 0.006–0.012 | D113: ~6,000–12,000 t | E113: 2.5–2.7 | F113: ~2.5–2.7 bn L | G113: site-specific; inland Indian sites 4–5 | H113: ~10–13
...

Sheet R6
A1: Report 6 · Water impact
A2: 22 tables. Source line under each title; "Note" gives the context sentence from the report.
A4: R6-T01 Withdrawal vs consumption: definitions by framework
A5: Source: Report 6 (full research report) · 1. How much water? › 1.1 Withdrawal vs consumption: definitions and why both matter
A6: Data basis: Source-derived (reported, not re-verified)
A7: Used in atlas: Ch 6 framing (reference).
A8: Used to derive: Separate withdrawal, consumption, discharge.
A9: Framework | B9: Withdrawal | C9: Consumption | D9: Other key terms
A10: USGS | B10: Water removed from ground or surface sources | C10: Water evaporated, transpired, incorporated into products or otherwise removed from the immediate water environment | D10: Return flow
A11: GRI 303 (2018) | B11: 303-3: all water drawn from all sources, split freshwater (≤1,000 mg/L TDS) and "other" | C11: 303-5: withdrawal − discharge (± storage change) | D11: 303-4 discharge by destination and treatment; all broken out for water-stressed areas
A12: ISO 14046 (2014) | B12: Water use | C12: Water not returned to the drainage basin (evaporated, integrated, transferred) | D12: Water scarcity footprint
A13: Water Footprint Network | B13: — | C13: Blue: surface or groundwater consumed. Green: soil rainwater. Grey: virtual dilution volume for pollutants | D13: —
A16: R6-T02 Cooling water by system
A17: Source: Report 6 (full research report) · 1. How much water? › 1.2 Cooling water
A18: Data basis: Mixed: sourced figures plus estimates
A19: Used in atlas: Ch 6 water balance and simulator WUE values.
A20: Used to derive: Site WUE by cooling system.
A21: System | B21: Mechanism | C21: Site water (L/kWh of IT energy) | D21: Notes
A22: Open cooling towers + water-cooled chillers | B22: Latent heat (about 2,400 kJ/kg → about 1.5 L per kWh of heat) | C22: 1.4–2.5 withdrawal; 1.1–1.8 consumption | D22: Bengaluru's moderate wet-bulb suits towers; lowest PUE
A23: Direct / indirect evaporative air handlers | B23: Evaporation into air | C23: 0.3–1.5 | D23: Seasonal
A24: Adiabatic hybrid dry coolers | B24: Dry coils; sprays above about 28–32°C | C24: 0.05–0.4 | D24: Low average, high peaks
A25: Air-cooled chillers / dry coolers | B25: Sensible heat only | C25: ≈0–0.05 | D25: PUE higher by about 0.1–0.2
A26: Closed-loop DLC + dry coolers | B26: Warm water (35–45°C) to cold plates | C26: 0.01–0.15 | D26: One-time fill about 1.5–3 L/kW (often 25% propylene glycol)
A27: Chilled-water make-up | B27: Closed-loop losses | C27: <0.01 | D27: Quality matters more than volume
A30: R6-T03 Non-cooling water uses (50 MW campus)
A31: Source: Report 6 (full research report) · 1. How much water? › 1.3 Non-cooling water
A32: Data basis: Proxy / estimate
A33: Used in atlas: Ch 6 water balance (non-cooling 14.6 ML/yr).
A34: Used to derive: Non-cooling water allowance.
A35: Use | B35: 50 MW campus magnitude | C35: Comment
A36: Domestic / staff (about 300 people at the 45 L per head per day office norm) | B36: ≈13.5 m³/day | C36: About 80% returns as sewage; on-site STP reuse
A37: Cleaning, housekeeping | B37: 3–10 m³/day | C37: —
A38: Humidification | B38: 0–20 m³/day, seasonal | C38: Dry months (January–March, relative humidity 25–40%) need humidification; the monsoon needs dehumidification, which yields recoverable condensate
A39: Landscaping | B39: 5–20 m³/day | C39: Should use STP or rainwater
A40: Fire suppression | B40: Hundreds of m³ stored; 1–5 m³/week testing | C40: Storage, not consumption
A41: Diesel generator cooling | B41: Closed radiator loops; negligible | C41: —
A42: RO reject | B42: 20–35% of RO feed | C42: Raises withdrawal and discharge, not consumption
A43: Construction | B43: Tens of thousands of m³ over 18–36 months (estimate) | C43: Meta reports construction water separately; Yotta's Greater Noida site had a 50 KLD STP-water connection for construction (DTE)
A46: R6-T04 Freshwater vs recycled water sources (Bengaluru)
A47: Source: Report 6 (full research report) · 1. How much water? › 1.4 Freshwater vs recycled water
A48: Data basis: Mixed: sourced figures plus estimates
A49: Used in atlas: Ch 6 water balance source options; simulator water sources.
A50: Used to derive: Source choice and cycles of concentration.
A51: Source | B51: Bengaluru status | C51: Cooling-tower issues | D51: Implications
A52: BWSSB potable (Cauvery) | B52: Industrial tariff about ₹99/kL | C52: Low TDS allows high CoC | D52: Diverts drinking water; last resort
A53: Groundwater (borewell or tanker) | B53: All Bengaluru Urban taluks over-exploited | C53: TDS 500–1,500 mg/L; silica 20–60 mg/L limits CoC to about 3–4 | D53: Highest local impact; KGWA permits
A54: Tertiary treated wastewater (TTW) | B54: Growing; K&C Valley already sends treated water to Kolar and Chikkaballapur tanks | C54: Ammonia, phosphate, biofouling; needs UF/RO | D54: Has downstream claimants
A55: Rainwater | B55: About 900 mm/yr; a 10 ha roof yields about 80,000 m³/yr | C55: Ideal make-up | D55: About 13% of a 50 MW evaporative plant's need
A56: Seawater | B56: Not available in Bengaluru | C56: Corrosion | D56: Coastal sites only
A59: R6-T05 Daily and annual water demand by capacity and cooling
A60: Source: Report 6 (full research report) · 1. How much water? › 1.5 Daily and annual demand: worked examples
A61: Note: Assumptions: 80% average load, so 1 MW = 19.2 MWh/day = 7,008 MWh/yr of IT energy. WUE is withdrawal-based (L/kWh = m³/MWh).
A62: Data basis: Calculated (model output)
A63: Used in atlas: Ch 6 and Ch 12 reference values.
A64: Used to derive: Daily and annual water per MW and design.
A65: IT capacity | B65: Evaporative, CoC 5 (WUE 1.80) | C65: Adiabatic (0.40) | D65: Dry / DLC (0.05) | E65: WELL Labs basis (26 ML/MW/yr)
A66: 1 MW | B66: 34.6 m³/d · 12.6 ML/yr | C66: 7.7 m³/d · 2.8 ML/yr | D66: 1.0 m³/d · 0.35 ML/yr | E66: 71 m³/d · 26 ML/yr
A67: 20 MW | B67: 0.69 MLD · 252 ML/yr | C67: 154 m³/d · 56 ML/yr | D67: 19 m³/d · 7 ML/yr | E67: 1.42 MLD · 520 ML/yr
A68: 50 MW | B68: 1.73 MLD · 631 ML/yr | C68: 384 m³/d · 140 ML/yr | D68: 48 m³/d · 17.5 ML/yr | E68: 3.56 MLD · 1,300 ML/yr
A69: 100 MW | B69: 3.46 MLD · 1,261 ML/yr | C69: 768 m³/d · 280 ML/yr | D69: 96 m³/d · 35 ML/yr | E69: 7.12 MLD · 2,600 ML/yr
A72: R6-T06 Water balance: 50 MW evaporative facility at different CoC
A73: Source: Report 6 (full research report) · 2. Water balance › 2.3 Worked balance: 50 MW Bengaluru hyperscale facility (evaporative)
A74: Note: Annual balance (ML/yr):
A75: Data basis: Calculated (model output)
A76: Used in atlas: Ch 6 "Cooling-tower water balance" calculator.
A77: Used to derive: Withdrawal, consumption, discharge at each CoC.
A78: Stream | B78: CoC 3 (hard borewell) | C78: CoC 5 (potable or softened) | D78: CoC 8 | E78: CoC 8 on TTW + RO (75% recovery) | F78: ZLD
A79: Evaporation | B79: 504.6 | C79: 504.6 | D79: 504.6 | E79: 504.6 | F79: 504.6
A80: Blowdown | B80: 252.3 | C80: 126.2 | D80: 72.1 | E80: 72.1 | F80: 0
A81: Drift | B81: 1.2 | C81: 1.2 | D81: 1.2 | E81: 1.2 | F81: 1.2
A82: Tower make-up | B82: 758.1 | C82: 632 | D82: 577.9 | E82: 577.9 | F82: ≈506
A83: RO reject | B83: — | C83: — | D83: — | E83: 192.6 | F83: 0
A84: Non-cooling | B84: 14.6 | C84: 14.6 | D84: 14.6 | E84: 14.6 | F84: 14.6
A85: Withdrawal | B85: 772.7 (2.12 MLD) | C85: 646.6 (1.77 MLD) | D85: 592.5 (1.62 MLD) | E85: 785.1 (2.15 MLD) | F85: ≈525 (1.44 MLD)
A86: Discharge | B86: 264 | C86: 137.9 | D86: 83.8 | E86: 276.4 | F86: ≈0
A87: Consumption | B87: 508.7 (1.39 MLD) | C87: 508.7 | D87: 508.7 | E87: 508.7 | F87: ≈525
A88: Consumption ÷ withdrawal | B88: 66% | C88: 79% | D88: 86% | E88: 65% | F88: ≈100%
A89: Site WUE, withdrawal | B89: 2.21 | C89: 1.85 | D89: 1.69 | E89: 2.24 | F89: 1.5
A90: Site WUE, consumption | B90: 1.45 | C90: 1.45 | D90: 1.45 | E90: 1.45 | F90: 1.5
A93: R6-T07 Water balance: 100 MW AI facility (DLC + adiabatic)
A94: Source: Report 6 (full research report) · 2. Water balance › 2.4 Worked balance: 100 MW AI facility (DLC + adiabatic dry coolers)
A95: Note: Inputs: 100 MW × 85% = 744,600 MWh/yr of IT energy; PUE 1.15; all heat to dry coolers. Adiabatic sprays run about 1,000 h/yr (an illustrative assumption, mostly March–May afternoons) at about 1.0 L/kWh.
A96: Data basis: Calculated (model output)
A97: Used in atlas: Ch 6 text; Ch 12 Example C reasoning.
A98: Used to derive: DLC water and peak factor (3.5×).
A99: Item | B99: Calculation | C99: Annual
A100: Adiabatic water | B100: 85,000 kW × 1,000 h × 1.0 L/kWh | C100: 85 ML
A101: Non-cooling | B101: 30 m³/d | C101: 11 ML
A102: Coolant top-up | B102: — | C102: ≈1 ML
A103: Total withdrawal | B103: — | C103: ≈97 ML/yr (0.27 MLD)
A104: Site WUE | B104: 97 ML ÷ 744,600 MWh | C104: ≈0.13 L/kWh
A105: Consumption | B105: — | C105: ≈80 ML
A106: One-time fill | B106: 1.5–3 L/kW × 100 MW | C106: 150–300 m³
A107: Peak day (May) | B107: 10 h × 90 MW × 1.0 + 30 m³ | C107: ≈0.93 MLD (peak ÷ average ≈ 3.5)
A108: Off-site (grid) | B108: 744,600 × 1.15 × 1.5 L/kWh | C108: ≈1,284 ML/yr (3.5 MLD), about 13× on-site
A111: R6-T08 Water measurement and accounting standards
A112: Source: Report 6 (full research report) · 2. Water balance › 2.5 Measurement and accounting standards
A113: Note: Meters: M1 intake by source (borewell telemetry, tanker logs); M2 RO permeate and reject; M3 tower make-up; M4 blowdown; M5 humidifier feed; M6 domestic and STP; M7 reuse; M8 final discharge. Add conductivity for continuous CoC and 15-minute logging.
A114: Data basis: Source-derived (reported, not re-verified)
A115: Used in atlas: Reference only (metering and standards).
...

Sheet R7
A1: Report 7 · Unit economics
A2: 24 tables. Source line under each title; "Note" gives the context sentence from the report.
A4: R7-T01 Construction cost index by market (Turner & Townsend)
A5: Source: Report 7 (full research report) · 1. CAPEX (₹) › 1.1 Global and Indian benchmarks
A6: Note: Turner & Townsend Data Centre Construction Cost Index 2025–26 (52 markets, traditional air-cooled cloud data centre, US$ per watt; construction only):
A7: Data basis: Source-derived (reported, not re-verified)
A8: Used in atlas: Ch 7 "Build cost around the world" chart; Key numbers.
A9: Used to derive: Mumbai cost advantage; forecast base cost.
A10: Market | B10: US$/W | C10: ₹ crore/MW (at ₹90/$) | D10: Comment
A11: Tokyo | B11: 15.2 | C11: 137 | D11: Most expensive
A12: Singapore | B12: 14.5 | C12: 131 | D12: 2nd
A13: Zurich | B13: 14.2 | C13: 128 | D13: 3rd
A14: Silicon Valley | B14: 13.3 | C14: 120 | D14: Largest US premium
A15: New Jersey | B15: 12.9 | C15: 116
A16: Oslo | B16: 12.4 | C16: 112 | D16: 7th
A17: London | B17: 12 | C17: 108
A18: Frankfurt | B18: 11.6 | C18: 104
A19: Atlanta | B19: 9.9 | C19: 89
A20: Phoenix / Columbus | B20: 9.8 | C20: 88
A21: Charlotte | B21: 9.5 | C21: 86
A22: Mumbai | B22: 6.64 | C22: 60 | D22: 51st of 52
A25: R7-T02 Land prices in Indian data-centre hubs
A26: Source: Report 7 (full research report) · 1. CAPEX (₹) › 1.2 Land and buildings
A27: Note: Land prices per acre in Indian data centre hubs. Transaction-based figures are labelled. The rest are estimates or come from low-quality sources.
A28: Data basis: Mixed: sourced figures plus estimates
A29: Used in atlas: Ch 7 "Land and power" table; simulator land prices.
A30: Used to derive: Land share of capex by hub.
A31: Hub | B31: ₹ crore/acre | C31: Evidence
A32: Navi Mumbai (TTC MIDC, Airoli, Mahape, Ghansoli) | B32: 15–40 greenfield; up to ~80 for in-fill with structures | C32: STT GDC paid ₹282 crore for 14,093 m² (~3.5 acres) with an existing 6,828 m² building (May 2026), ≈₹81 crore/acre. Brookfield paid ₹600 crore for 30 acres in Ghansoli (2021), ≈₹20 crore/acre.
A33: Thane / Palava (MMR periphery) | B33: 12–35 | C33: AWS: ~40–45 acres at Palava for ₹500–600 crore (≈₹12–14 crore/acre). Amazon: 54 acres in Thane for ₹1,870 crore (≈₹35 crore/acre).
A34: Chennai (Ambattur, Oragadam, Siruseri) | B34: 8–15 Ambattur; 3–8 Oragadam (estimate) | C34: A secondary blog source gives ₹8–15 crore/acre; treat as indicative.
A35: Hyderabad | B35: 2–6 | C35: Microsoft bought 48 acres for ₹267 crore (2024), ≈₹5.6 crore/acre.
A36: Noida / Greater Noida | B36: 3–10 (estimate, not verified) | C36: Authority allotment rates vary; check YEIDA and GNIDA schedules.
A37: Bengaluru Whitefield | B37: 10–25 (estimate, not verified)
A38: Bengaluru Devanahalli / Hoskote | B38: 4–10 (estimate, not verified)
A39: Pune (Hinjewadi, Chakan, Talegaon) | B39: 5–15 (estimate, not verified)
A42: R7-T03 Servers, storage and GPU prices
A43: Source: Report 7 (full research report) · 1. CAPEX (₹) › 1.3 Servers, storage and GPUs (IT capex)
A44: Data basis: Mixed: sourced figures plus estimates
A45: Used in atlas: Ch 7 GPU calculator (HGX prices); simulator GPU capex.
A46: Used to derive: IT capex per MW and per GPU.
A47: Item | B47: Price (USD) | C47: India landed (₹, at ₹90/$) | D47: Notes
A48: CPU server, dual-socket 1U/2U cloud node | B48: US$9–22k (estimate) | C48: ₹8–20 lakh | D48: Not verified; varies hugely with configuration
A49: Storage | B49: ~₹45–90 lakh per PB raw (estimate) | D49: Not verified
A50: H100 SXM card | B50: US$25–40k | C50: ₹22–36 lakh | D50: Multiple 2026 price guides
A51: H100 HGX 8-GPU server | B51: US$250–320k | C51: ₹2.25–2.9 crore
A52: H200 HGX 8-GPU server | B52: ~US$300–330k (estimate) | C52: ~₹2.7–3.0 crore | D52: H200 cards quoted at US$30–35k
A53: B200 HGX 8-GPU server | B53: US$400–500k (DGX B200 lists ~US$515k) | C53: ₹3.6–4.5 crore
A54: GB200 NVL72 rack | B54: US$3.0M (HSBC); US$3.1M bare / US$3.9M all-in (SemiAnalysis) | C54: ₹27–35 crore | D54: 72 GPUs, ~120–135 kW
A55: GB300 NVL72 rack | B55: US$3.7–4.0M (Loop Capital) vs US$6.0–6.5M (Tom's Hardware supply chain, March 2026); ~US$5.0M purchase / US$5.7M deployed (Data Gravity) | C55: ₹33–58 crore | D55: Estimates disagree; Supermicro datasheet lists 132–140 kW
A58: R7-T04 Soft costs, interest during construction and contingency
A59: Source: Report 7 (full research report) · 1. CAPEX (₹) › 1.8 Soft costs, interest during construction and contingency
A60: Data basis: Proxy / estimate
A61: Used in atlas: Capex stacks (soft costs, contingency, IDC).
A62: Used to derive: Soft-cost share of capex.
A63: Item | B63: Typical share | C63: Our base
A64: Design, permits, project management (PMC), commissioning | B64: 5–8% of hard cost | C64: 5–6%
A65: Contingency | B65: 5–10% | C65: 5–6.5%
A66: Interest during construction (IDC) | B66: 18–24-month build; ~70% debt at ~9.5%; average 50% drawn | C66: ≈5–6% of facility cost
A69: R7-T05 Capex breakdown: 20 MW Tier III colocation
A70: Source: Report 7 (full research report) · 1. CAPEX (₹) › 1.9 Breakdown tables for the three cases
A71: Note: (a) 20 MW Tier III colocation (Navi Mumbai/Chennai-type; air-cooled chilled water; 2N electrical, N+1 DG; multi-storey on 5 acres at ₹20 crore/acre)
A72: Data basis: Calculated (model output)
A73: Used in atlas: Ch 7 "Line by line" table (Case A) and capex chart; simulator colo capex ₹56.1 cr/MW.
A74: Used to derive: Capex per MW for a colo.
A75: Item | B75: ₹ crore/MW | C75: ₹ crore (20 MW) | D75: Share of facility capex
A76: Land (0.25 acre/MW) | B76: 5 | C76: 100 | D76: —
A77: Shell and core, civil/structural | B77: 8.5 | C77: 170 | D77: 15.2%
A78: Electrical (substation share, transformers, switchgear, 2N UPS, PDUs, busway) | B78: 22 | C78: 440 | D78: 39.2%
A79: Cooling (chillers, towers/adiabatic, CRAH, piping) | B79: 10 | C79: 200 | D79: 17.8%
A80: Backup (DG N+1 ~42 MVA, fuel) | B80: 4.2 | C80: 84 | D80: 7.5%
A81: Fire, BMS/DCIM, security, low-voltage | B81: 2 | C81: 40 | D81: 3.6%
A82: Networking (meet-me rooms, fibre entry, cabling) | B82: 1 | C82: 20 | D82: 1.8%
A83: Hard cost subtotal | B83: 47.7 | C83: 954 | D83: 85.0%
A84: Design, permits, PMC (~6%) | B84: 3 | C84: 60 | D84: 5.3%
A85: Contingency (~5%) | B85: 2.5 | C85: 50 | D85: 4.5%
A86: Interest during construction | B86: 2.9 | C86: 58 | D86: 5.2%
A87: Facility total (excl. land) | B87: 56.1 | C87: 1122 | D87: 100%
A88: Total incl. land | B88: 61.1 | C88: 1,222 (≈US$136M) | D88: Land = 8%
A91: R7-T06 Capex breakdown: 50 MW hyperscale build-to-suit
A92: Source: Report 7 (full research report) · 1. CAPEX (₹) › 1.9 Breakdown tables for the three cases
A93: Note: (b) 50 MW hyperscale build-to-suit (Hyderabad/Chennai-type; developer delivers shell and M&E, tenant supplies IT; 20 acres at ₹8 crore/acre)
A94: Data basis: Calculated (model output)
A95: Used in atlas: Ch 7 "Line by line" (Case B); simulator hyperscale ₹39.2 cr/MW.
A96: Used to derive: Capex per MW for hyperscale.
A97: Item | B97: ₹ crore/MW | C97: ₹ crore (50 MW) | D97: Share of facility capex
A98: Land (0.4 acre/MW) | B98: 3.2 | C98: 160 | D98: —
A99: Shell and core | B99: 5.5 | C99: 275 | D99: 14.0%
A100: Electrical (incl. 220 kV substation) | B100: 15.5 | C100: 775 | D100: 39.5%
A101: Cooling | B101: 7.5 | C101: 375 | D101: 19.1%
A102: Backup (DG) | B102: 3.3 | C102: 165 | D102: 8.4%
A103: Fire, BMS, security | B103: 1.4 | C103: 70 | D103: 3.6%
A104: Networking / meet-me rooms | B104: 0.3 | C104: 15 | D104: 0.8%
A105: Hard cost subtotal | B105: 33.5 | C105: 1675 | D105: 85.5%
A106: Soft costs (5%) | B106: 1.7 | C106: 85 | D106: 4.3%
A107: Contingency (5%) | B107: 1.7 | C107: 85 | D107: 4.3%
A108: Interest during construction | B108: 2.3 | C108: 115 | D108: 5.9%
A109: Facility total | B109: 39.2 | C109: 1960 | D109: 100%
A110: Total incl. land | B110: 42.4 | C110: 2,120 (≈US$236M) | D110: Land = 7.5%
A113: R7-T07 Capex breakdown: 100 MW AI campus incl. GPUs
...

Sheet R8
A1: Report 8 · Green data centres
A2: 12 tables. Source line under each title; "Note" gives the context sentence from the report.
A4: R8-T01 Twelve dimensions of a green data centre
A5: Source: Report 8 (full research report) · 1. What is a "green data centre"? › 1.2 The twelve dimensions
A6: Data basis: Illustrative / framework / author judgement
A7: Used in atlas: Ch 8 "Twelve dimensions" grid.
A8: Used to derive: Definition of green for India.
A9: # | B9: Dimension | C9: Core metric(s) | D9: What "green" looks like (India-tailored) | E9: Why it matters
A10: 1 | B10: Energy efficiency | C10: PUE (ISO/IEC 30134-2) | D10: ≤1.30 annualised (air); ≤1.20 (liquid-cooled AI) | E10: Overhead energy is pure waste
A11: 2 | B11: Carbon-free energy | C11: REF, hourly CFE score, CUE | D11: ≥70–80% hourly-matched CFE; CUE ≤0.3 kgCO₂/IT-kWh | E11: India's grid factor 0.710 tCO₂/MWh makes power the dominant footprint
A12: 3 | B12: Water | C12: WUE (site), source WUE | D12: ≤0.2 L/kWh freshwater; treated wastewater for any evaporative trim | E12: Bengaluru water stress
A13: 4 | B13: Embodied carbon (building) | C13: kgCO₂e/m² or /MW (EN 15978-style LCA) | D13: 30–40% below baseline via low-clinker concrete, recycled steel, hybrid timber | E13: Grows in share as grids decarbonise
A14: 5 | B14: IT hardware Scope 3 | C14: kgCO₂e per server/GPU, lifecycle | D14: Supplier EPDs/PCFs; extended refresh cycles | E14: Now the largest share for hyperscalers
A15: 6 | B15: Circularity | C15: % IT assets reused/refurbished; e-waste diversion | D15: ≥90% assets reused or recycled through authorised E-Waste (Management) Rules 2022 channels | E15: Avoids manufacturing emissions and hazardous waste
A16: 7 | B16: Heat reuse | C16: ERF (ISO/IEC 30134-6), ERE | D16: "Heat-reuse ready" design; absorption cooling or process heat where offtake exists | E16: Turns waste into a product
A17: 8 | B17: Refrigerants | C17: GWP of charge, leakage rate | D17: Low-GWP (HFO, natural refrigerants); chiller-less where possible | E17: HFC leakage is a hidden Scope 1 source
A18: 9 | B18: Land and biodiversity | C18: Footprint, green cover, heat-island | D18: Brownfield/industrial-park siting; native landscaping | E18: Social licence, local heat
A19: 10 | B19: Backup power | C19: Diesel litres/yr, run-hours | D19: HVO-ready gensets, BESS for short events, fuel cells long term | E19: Diesel is local pollution and Scope 1
A20: 11 | B20: Grid-friendliness | C20: Demand response, flexibility MW | D20: BESS/UPS grid services; schedulable AI training | E20: Helps integrate renewables
A21: 12 | B21: Social licence | C21: Disclosure, local water/power impact, jobs | D21: Public site-level dashboards; community water commitments | E21: Without it, moratoria follow (Amsterdam, Dublin, Singapore 2019)
A24: R8-T02 Green vs greenwashing: a quick test
A25: Source: Report 8 (full research report) · 1. What is a "green data centre"? › 1.3 Green vs greenwashing: a quick test
A26: Data basis: Illustrative / framework / author judgement
A27: Used in atlas: Ch 8 "Spotting greenwashing" table.
A28: Used to derive: Credibility test for claims.
A29: Claim | B29: Credible if… | C29: Greenwashing red flag
A30: "100% renewable" | B30: Hourly or at least monthly matching, same grid region, additional (new) capacity, location-based Scope 2 also disclosed | C30: Annual matching with unbundled RECs/I-RECs from old hydro elsewhere
A31: "Carbon neutral" | B31: Deep reductions first; removals (not avoidance offsets) for residuals | C31: Cheap avoidance offsets netted against growing emissions
A32: "PUE 1.2" | B32: Annualised, measured at the utility meter boundary (ISO/IEC 30134-2 Category 2/3), at real load | C32: Design PUE at 100% load, or a single cool-season month
A33: "Water positive" | B33: Site-level WUE disclosed; replenishment in the *same* basin | C33: Global replenishment credits while a Bengaluru site draws borewells
A34: "Green certified" | B34: Operational certification with measured data | C34: Design-stage label only, never re-verified
A37: R8-T03 Core green metrics and formulas
A38: Source: Report 8 (full research report) · 2. Metrics and standards › 2.1 Core metrics and formulas
A39: Data basis: Source-derived (reported, not re-verified)
A40: Used in atlas: Ch 8 metric definitions (reference).
A41: Used to derive: CUE, ERF, CFE formulas.
A42: Metric | B42: Formula | C42: Standard | D42: Notes
A43: PUE | B43: Total facility energy ÷ IT equipment energy | C43: ISO/IEC 30134-2 (The Green Grid, 2007) | D43: Ideal 1.0; global weighted average 1.54 (Uptime 2025)
A44: WUE | B44: Annual site water (L) ÷ IT energy (kWh) | C44: ISO/IEC 30134-9 | D44: Karnataka policy uses this definition; the EU uses freshwater input
A45: CUE | B45: Total CO₂ from facility energy ÷ IT energy = grid EF × PUE (for grid-only supply) | C45: ISO/IEC 30134-8 | D45: Bengaluru grid-only at PUE 1.5: 0.710 × 1.5 = 1.07 kgCO₂/IT-kWh
A46: ERF | B46: Reused energy ÷ total facility energy | C46: ISO/IEC 30134-6 | D46: German EnEfG requires 10→20% for new sites
A47: ERE | B47: (Total energy – reused energy) ÷ IT energy | C47: The Green Grid | D47: Can be <1.0 with heat reuse
A48: REF | B48: Renewable energy ÷ total facility energy | C48: ISO/IEC 30134-3 | D48: Annual; does not capture timing
A49: 24/7 CFE score | B49: Σ_h min(load_h, CFE supply_h) ÷ Σ_h load_h | C49: Google/UN 24/7 CFE Compact methodology | D49: The honest metric; Google fleet ≈65% (2025)
A50: ITEEsv / ITEUsv | B50: IT equipment energy efficiency / utilisation for servers | C50: ISO/IEC 30134-4/-5 | D50: Captures the compute side that PUE ignores
A51: GEC | B51: Green energy share of facility energy | C51: ISO/IEC 30134 family (Japan-originated) | D51: Similar in spirit to REF
A54: R8-T04 Certifications compared
A55: Source: Report 8 (full research report) · 2. Metrics and standards › 2.3 Certifications
A56: Data basis: Source-derived (reported, not re-verified)
A57: Used in atlas: Reference only (certifications).
A58: Used to derive: Which label to pursue.
A59: Certification | B59: Scope | C59: Strength | D59: Weakness
A60: LEED (v4/v4.1 BD+C Data Centers; v5) | B60: Building lifecycle; energy modelled against ASHRAE 90.4 | C60: Globally recognised by tenants | D60: Design-stage heavy; weak on hourly carbon
A61: BREEAM | B61: Building sustainability (UK/EU) | C61: Strong on materials, ecology | D61: Less used in India
A62: IGBC Green Data Center Rating System (CII) | B62: Design and Operational certification; enterprise, colo, hyperscale, edge, campuses | C62: India-specific; aims to improve national average PUE by 20–25% | D62: Voluntary; few disclosed operational ratings
A63: GRIHA | B63: Indian green building (TERI/MNRE) | C63: Government projects | D63: No DC-specific variant of note
A64: BCA-IMDA Green Mark for DCs 2024 | B64: Singapore | C64: Platinum is now a licence condition | D64: Singapore-specific
A65: Uptime Tier + Sustainability assessments | B65: Resilience; operational sustainability | C65: Credible with enterprise buyers | D65: Tier is resilience, not green
A66: ISO 50001 / 14001 / 14064 | B66: Energy management, environmental management, GHG verification | C66: Process discipline; EnEfG requires EMS | D66: Not a performance threshold
A67: ENERGY STAR (US) | B67: Top-quartile operational energy | C67: Performance-based | D67: US only
A70: R8-T05 Indian standards and policy instruments
A71: Source: Report 8 (full research report) · 2. Metrics and standards › 2.4 Indian standards and policy instruments
A72: Data basis: Source-derived (reported, not re-verified)
A73: Used in atlas: Ch 8 "Rules elsewhere" (India row) and Ch 9 central framework.
A74: Used to derive: Indian policy instruments status.
A75: Instrument | B75: Status (Oct 2026) | C75: Relevance
A76: BEE / ECBC & Super ECBC | B76: PUE benchmarks aligned with ECBC classes | C76: Building-level; no binding DC PUE cap
A77: MeitY tenders | B77: AI cloud infrastructure tenders (since 2024) require PUE <1.35 | C77: De facto public-procurement standard
A78: TRAI | B78: Recommendations on a regulatory framework for data centres (incl. green measures) | C78: Advisory
A79: IGBC Green DC | B79: Voluntary design/operational certification | C79: Market signalling
A80: SEBI BRSR / BRSR Core | B80: Listed companies disclose energy, water, emissions; assurance phased in | C80: Covers listed operators and parents (Bharti, Adani, Reliance, Sify via US listing etc.)
A81: Carbon Credit Trading Scheme | B81: Compliance market: ~490 obligated entities in 7 industrial sectors; first CCC trading expected ~October 2026 | C81: Data centres are *not* obligated entities; the offset mechanism and price signal matter
A82: Draft National Data Centre Policy | B82: Announced 2020; MeitY revived consultations (economic zones, single window, RE use) | C82: No binding green thresholds yet
A83: State DC policies | B83: Karnataka 2026–31 (PUE/WUE reporting + incentives); UP 2026 (50% RE target for new DCs by 2030, green "booster" interest subsidy); others | C83: States are leading on green conditions
A84: Draft Climate Finance Taxonomy | B84: DEA draft framework, May 2025 (comments to 25 June 2025); sectoral annexes pending | C84: Inclusion of DCs with PUE/CFE criteria would unlock cheaper capital
A87: R8-T06 Design levers with quantified savings
A88: Source: Report 8 (full research report) · 3. Design levers with quantified savings
A89: Note: The table below ranks levers for an Indian air-and-liquid hybrid facility. Savings are indicative ranges drawn from engineering practice and the series' prior reports. These are estimates, not measured Indian fleet data.
A90: Data basis: Proxy / estimate
A91: Used in atlas: Reference for green upgrade assumptions.
A92: Used to derive: Savings per design lever.
A93: Lever | B93: Typical impact | C93: Cost/complexity | D93: India note
A94: Site selection (climate, RE access, water, grid) | B94: 0.05–0.15 PUE; large water and carbon effects | C94: Low if early | D94: Bengaluru's mild, elevated climate beats Chennai/Mumbai for free cooling; Hoskote park pairs Pavagada solar + 60 MLD treated water
A95: Hot/cold-aisle containment | B95: 10–20% cooling energy | C95: Low | D95: Table stakes
A96: Raised supply air temperature (ASHRAE recommended 18–27 °C) | B96: 2–4% chiller energy per °C | C96: Low | D96: Germany will require 27 °C inlet from 2028
A97: Free cooling / economisers, dry coolers | B97: 0.05–0.15 PUE in Bengaluru | C97: Medium | D97: Many hours below 24 °C wet-bulb
A98: Direct-to-chip liquid cooling (DLC) | B98: Removes ~70–80% of heat with warm water (30–45 °C); enables PUE 1.1–1.2 | C98: Medium-high | D98: Essential for 50–130 kW AI racks
A99: Immersion cooling | B99: PUE ~1.03–1.1; no fans | C99: High; ecosystem immature | D99: Niche/edge
A100: High-efficiency UPS / eco-mode | B100: 2–4% of facility energy | C100: Low-medium | D100: Eco-mode at 99% efficiency vs ~94–96% double-conversion
A101: Low-loss transformers, 415 V / higher-voltage distribution; 800 VDC for AI racks | B101: 1–3% | C101: Medium | D101: 800 VDC is emerging with next-generation GPU racks
A102: Lithium-ion UPS batteries | B102: Smaller footprint, longer life | C102: Medium | D102: Fire-safety design essential
A103: Server utilisation, virtualisation, consolidation | B103: Can halve IT energy per workload | C103: Low (software) | D103: The biggest lever that PUE does not see
A104: Efficient chips (ARM, accelerators), power capping | B104: 10–30% per workload | C104: Medium | D104: Procurement criterion: SS 715-type standards
... A110: Treated wastewater (TTW) for cooling | B110: Cuts freshwater to near zero | C110: Medium (treatment plant) | D110: Karnataka reimburses treated-water charges
A113: R8-T07 Renewable procurement options in India
A114: Source: Report 8 (full research report) · 4. Renewable and carbon-free energy procurement › 4.1 Procurement options in India
A115: Data basis: Mixed: sourced figures plus estimates
A116: Used in atlas: Ch 8 "Buying clean power in India" table; simulator RE price.
A117: Used to derive: Landed cost of clean power routes.
A118: Route | B118: How it works | C118: Typical landed cost (est.) | D118: Pros | E118: Cons
...

Sheet R9
A1: Report 9 · State policies
A2: 4 tables. Source line under each title; "Note" gives the context sentence from the report.
A4: R9-T01 Central framework instruments
A5: Source: Report 9 (full research report) · Part A — Central Framework
A6: Data basis: Source-derived (reported, not re-verified)
A7: Used in atlas: Ch 9 "The central framework" table.
A8: Used to derive: National levers vs state levers.
A9: Instrument | B9: Status (Oct 2026) | C9: What it does / implication
A10: Draft National Data Centre Policy (MeitY) | B10: Released 5 Nov 2020 for comments (deadline extended to 30 Nov 2020); never notified. MeitY has resumed industry consultations; one market-research release describes a "finalised draft" with up to 20-year conditional tax exemptions, but this is unverified. | C10: Proposed four Data Centre Economic Zones (DCEZs), single-window clearance, infrastructure status, and support for indigenous servers, storage, networking and cooling. Lacked enforceable mandates. Treat "imminent" claims sceptically: it has been pending for nearly six years.
A11: Infrastructure status | B11: In the Harmonised Master List of Infrastructure sub-sectors since 11 Oct 2022 | C11: Applies to data centres of at least 5 MW IT load. Eases long-tenor bank and ECB financing. The Finance Act 2026 tax-holiday definition does not use the 5 MW threshold, so a facility can qualify under one and not the other.
A12: Union Budget 2026–27 (1 Feb 2026) | B12: Enacted in the Finance Act; subordinate notifications on qualifying criteria still pending (Norton Rose Fulbright) | C12: Tax holiday until 31 March 2047 for foreign companies that provide cloud services globally using India-based data-centre services. Indian customers must be served through an Indian reseller. A 15% cost-plus safe harbour applies to related Indian data-centre service providers, and IT services generally move to a 15.5% safe harbour. This is the most important central incentive, but it benefits foreign cloud firms and Indian colocation operators indirectly and has no green conditions.
A13: DPDP Act 2023 / DPDP Rules 2025 | B13: Rules notified 14 Nov 2025 | C13: "Soft localisation": cross-border transfers are allowed unless the government blacklists a country. Demand for local hosting comes more from sector rules — RBI payment-data localisation (all payment data stored in India) and the SEBI Cloud Framework 2023 (data and logs on Indian servers) — than from the DPDP regime itself.
A14: MeitY cloud empanelment (GI Cloud / MeghRaj) | B14: Ongoing | C14: Government workloads must use MeitY-empanelled cloud service providers hosted in audited Indian data centres. This creates steady sovereign demand, especially for Tier III facilities. *(Not re-verified in this research.)*
A15: IndiaAI Mission | B15: Ongoing | C15: Subsidised GPU compute procured from private data-centre operators. It shapes demand for high-density, liquid-cooled capacity. *(Not re-verified in this research.)*
A16: Green Energy Open Access Rules 2022 (MoP) | B16: In force | C16: Lowered the open-access threshold to 100 kW and capped additional surcharges, enabling corporate renewable procurement. CEEW stakeholders still name high cross-subsidy surcharge (CSS) and additional surcharge, inconsistent banking rules and sudden withdrawal of waivers as the main barriers.
A17: ISTS charges waiver | B17: Being phased down for projects commissioned after mid-2025 *(general knowledge, not re-verified)* | C17: Makes inter-state renewable PPAs dearer over time, so state-level wheeling and banking concessions matter more.
A18: TRAI recommendations on data centres, CDNs and interconnect exchanges | B18: Issued Nov 2022 (often cited as 2023); not implemented by statute | C18: Recommended a legal framework, a single-window system, a data-centre-specific building-code category and incentives. Industry still asks for a National Building Code category for data centres.
A19: CEA/MoP draft guidance on power for data centres | B19: *Not verified in this research.* | C19: Flagged as a gap: no publicly verified central power-supply standard for data centres was found.
A20: SEZ route | B20: Available | C20: Data centres can be set up in IT/ITeS SEZs, for example the 2.7 ha SEZ portion of RackBank's Nava Raipur park. The Budget's IFSC tax-holiday extension (20 of 25 years) helps GIFT City-type locations.
A21: GST | B21: Standard rate on data-centre/colocation services *(not re-verified)* | C21: States compete through SGST reimbursement, which is the reason "net SGST reimbursement" appears in almost every policy.
A24: R9-T02 Telangana named projects
A25: Source: Report 9 (full research report) · Part B — State-by-State Deep Dive › 4. Telangana — the inland AI challenger
A26: Note: Implementation: According to Knight Frank India's "India Data Centre Market Update 2025", Hyderabad live capacity rose from 60.9 MW (2022) to 151.4 MW (end-2025), with a 1.9 GW committed pipeline, second only to Mumbai. AWS, which runs three availability zones in the city, holds 46% of live IT capacity. Named projects:
A27: Data basis: Source-derived (reported, not re-verified)
A28: Used in atlas: Ch 9 Telangana detail; Ch 10 demand context.
A29: Used to derive: Hyderabad pipeline evidence.
A30: Project | B30: Size / investment | C30: Details
A31: AWS | B31: ₹60,000 crore | C31: Foundation stone July 2026
A32: TCS HyperVault | B32: Up to 1 GW, up to ₹70,000 crore | C32: 264 acres, Future City; announced September 2026
A33: CtrlS | B33: 400 MW, ₹10,000 crore | C33: MoU 2025
A34: NTT DATA–Neysa | B34: 400 MW, ₹10,500 crore | C34: MoU 2025
A35: Microsoft India South Central region | B35: — | C35: Launched 2026
A38: R9-T03 Master comparison of state policies
A39: Source: Report 9 (full research report) · Part C — Master Comparison Table
A40: Data basis: Source-derived (reported, not re-verified)
A41: Used in atlas: Ch 9 policy register table, map detail panel and validity chart; simulator incentives.
A42: Used to derive: Incentives and green conditions by state.
A43: State | B43: Instrument / status | C43: Target | D43: Capex / interest | E43: Power | F43: Land / stamp | G43: Green conditions | H43: Validity
A44: Maharashtra | B44: IT/ITeS 2023 + IGDCP GRs (Oct 2024; Jun 2026) — active | C44: 20 parks; 30–40 GW by 2047 | D44: IPS 75% of fixed capital investment (≥₹60k cr); 4% interest, ₹25 cr/yr | E44: ED 20 yrs; ₹1/unit 10–20 yrs | F44: Stamp duty 100% (IGDCP); any-zone siting | G44: 51% RE (cut from 100%) | H44: IT policy to 2028; GR open-ended
A45: Tamil Nadu | B45: DC Policy 2021 — lapsed 31.3.2026 | C45: — | D45: — | E45: Electricity tax 100%, 5 yrs | F45: Stamp duty 50–100%; 50% land (Cat C) | G45: ≥30% RE eligibility | H45: Expired
A46: Karnataka | B46: Sustainable DC Policy 2026–31 — approved Sept 2026 | C46: 1 GW; ₹1,300.45 cr outlay | D46: Capital subsidy; R&D 50% up to ₹15 cr | E46: ED exemption; wheeling reimbursement | F46: Parks on 30+30-yr lease | G46: PUE/WUE reporting; ₹20 cr PUE; WUE & treated-water reimbursement | H46: 2031
A47: Telangana | B47: DC Policy 2016 + bespoke deals | C47: ~5 GW by 2029–30 (stated) | D47: Lease rental 25%; R&D | E47: Power incentives; dual grid | F47: Land subsidy (govt land); 50% building fee | G47: None | H47: Legacy
A48: Andhra Pradesh | B48: DC Policy 4.0, G.O.Ms.6 (14.11.2024) | C48: 200 MW–1 GW (policy); 6.5 GW (claimed) | D48: 100% SGST on capital goods or 10% P&M; mega >50 MW/>₹5k cr bespoke | E48: Industrial tariff; T&W case-by-case | F48: Stamp duty 100% first sale; land discount (mega) | G48: Seawater cooling; "70% RE" (stated, not notified) | H48: 2029 or new policy
A49: Uttar Pradesh | B49: DC Policy 2026 (replaced 2021) | C49: +2 GW; ₹2 lakh cr | D49: 7% up to ₹20 cr (+₹5 cr AI); 60% interest (+₹10 cr AI) | E49: ED 10 yrs; T&W relief; dual grid | F49: 25–50% land; stamp duty 100% | G49: PUE/green-cert booster; 50% RE by 2030 | H49: ~2031 (assumed)
A50: Gujarat | B50: DC Policy 2026–29 + IT/ITeS 2022–27 | C50: 7.5 GW; ₹6 lakh cr | D50: 2.5% capex (Dholera); 4% interest, ₹25 cr/yr; cap 75% of fixed capital investment | E50: ₹1/unit 20 yrs; ED 20 yrs | F50: Stamp duty & registration 100% | G50: 51% RE | H50: 2029
A51: Haryana | B51: DC Policy 2022 | C51: 115–120 DCs; ₹7,500 cr | D51: Net SGST 50–75%, 10 yrs | E51: ED 20 yrs; power bill ≤25% of SGST | F51: Stamp duty 100% | G51: None | H51: ~2029 (verify)
A52: West Bengal | B52: DC Policy 2021 (No. 490-ITE) | C52: 400 MW by 2025 | D52: — | E52: ED 5 yrs; dual grid | F52: Stamp duty & registration 100% | G52: Captive water treatment | H52: Lapsing ~Sept 2026
A53: Odisha | B53: DC Policy 2022 | C53: — | D53: 20% up to ₹25 cr; 5% interest | E53: 30% bill 5 yrs; ED 10 yrs; captive-RE T&W 100% | F53: Stamp duty 100/50% | G53: Clean-green subsidy; carbon framing | H53: Verify
A54: Rajasthan | B54: DC Policy 2025 | C54: 300 MW; ₹20,000 cr | D54: Asset-creation ₹10–20 cr/yr; 5% interest | E54: Banking/T&W 100% waiver; ED 7 yrs | F54: Stamp duty, conversion exemptions | G54: ZLD, recycling, green-building; green incentive ₹12.5 cr | H54: ~2030
A55: Madhya Pradesh | B55: IT/ITeS & ESDM 2023 | C55: — | D55: 25% up to ₹125 cr (anchors) | E55: Tariff rebate; ED | F55: Stamp reimbursement | G55: Green DC support (vague) | H55: ~2028
A56: Bihar | B56: IT Policy 2024 | C56: — | D56: 30% up to ₹30 cr or interest | E56: 25% tariff 5 yrs | F56: Lease subsidy | G56: None | H56: ~2029
A59: R9-T04 State attractiveness index
A60: Source: Report 9 (full research report) · Part D — Attractiveness Index
A61: Note: Methodology (author's weighted judgment, 0–10 per factor). Weights: power cost and reliability 25%; renewable access 15%; connectivity (subsea/IX/fibre) 15%; incentives 15%; land and park readiness 10%; water security 10%; regulatory ease and policy stability 10%. Scores reflect the evidence above, not a published index.
A62: Data basis: Illustrative / framework / author judgement
A63: Used in atlas: Ch 9 attractiveness index (sliders) and map colouring; Ch 10 policy factor.
A64: Used to derive: Weighted state ranking.
A65: Rank | B65: State | C65: Power | D65: RE | E65: Connectivity | F65: Incentives | G65: Land | H65: Water | I65: Regulatory | J65: Weighted
A66: 1 | B66: Maharashtra | C66: 8 | D66: 6 | E66: 10 | F66: 8 | G66: 6 | H66: 6 | I66: 8 | J66: 7.8
A67: 2 | B67: Telangana | C67: 8 | D67: 7 | E67: 6 | F67: 7 | G67: 9 | H67: 6 | I67: 7 | J67: 7.2
A68: 3 | B68: Andhra Pradesh | C68: 7 | D68: 9 | E68: 7 | F68: 9 | G68: 7 | H68: 5 | I68: 6 | J68: 7.3
A69: 4 | B69: Tamil Nadu | C69: 7 | D69: 8 | E69: 10 | F69: 4 | G69: 6 | H69: 4 | I69: 5 | J69: 6.8
A70: 5 | B70: Uttar Pradesh | C70: 7 | D70: 5 | E70: 6 | F70: 8 | G70: 7 | H70: 6 | I70: 8 | J70: 6.7
A71: 6 | B71: Gujarat | C71: 7 | D71: 9 | E71: 4 | F71: 9 | G71: 8 | H71: 4 | I71: 7 | J71: 6.8
A72: 7 | B72: Karnataka | C72: 6 | D72: 8 | E72: 5 | F72: 6 | G72: 6 | H72: 4 | I72: 7 | J72: 6
A73: 8 | B73: Haryana | C73: 6 | D73: 4 | E73: 6 | F73: 7 | G73: 4 | H73: 4 | I73: 7 | J73: 5.5
A74: 9 | B74: West Bengal | C74: 6 | D74: 4 | E74: 6 | F74: 5 | G74: 6 | H74: 7 | I74: 4 | J74: 5.4
A75: 10 | B75: Odisha | C75: 7 | D75: 6 | E75: 4 | F75: 7 | G75: 7 | H75: 7 | I75: 6 | J75: 6.2
A76: 11 | B76: Rajasthan | C76: 6 | D76: 10 | E76: 2 | F76: 8 | G76: 8 | H76: 2 | I76: 6 | J76: 5.9
A77: 12 | B77: Madhya Pradesh | C77: 6 | D77: 6 | E77: 3 | F77: 7 | G77: 7 | H77: 5 | I77: 6 | J77: 5.6

Sheet R10
A1: Report 10 · Where to build
A2: 22 tables. Source line under each title; "Note" gives the context sentence from the report.
A4: R10-T01 Market context: capacity by city, H1 2026
A5: Source: Report 10 (Part 10 research report) · Key Findings
A6: Note: 1. Market context (reported). Cushman & Wakefield's H1 2026 update puts operational capacity at 1,789 MW across seven markets, with 3,860 MW more due by 2030 (509 MW under construction and 3,351 MW planned). By city:
A7: Data basis: Source-derived (reported, not re-verified)
A8: Used in atlas: Ch 10 context; Ch 1/9 city capacity.
A9: Used to derive: Market size and pipeline by city.
A10: Market | B10: Operational (MW) | C10: Upcoming (MW)
A11: Mumbai | B11: 890 | C11: 1726
A12: Chennai | B12: 214 | C12: 368
A13: Delhi NCR | B13: 183 | C13: 387
A14: Bengaluru | B14: 162 | C14: 100
A15: Hyderabad | B15: 151 | C15: 710
A16: Pune | B16: 133 | C16: 258
A17: Kolkata | B17: 22 | C17: 84
A20: R10-T02 Effective tariff by state at 80% load factor
A21: Source: Report 10 (Part 10 research report) · Key Findings
A22: Note: 6. Tariffs vary by about ₹2.7/kWh across states. Over 20 years at 100 MW, that gap is worth more than any capex incentive. Effective cost is computed at 80% load factor, as energy charge + demand charge ÷ 584 h:
A23: Data basis: Mixed: sourced figures plus estimates
A24: Used in atlas: Ch 10 power score (tariff half); city detail panel.
A25: Used to derive: Tariff score = 10 × (8.70 − x) ÷ (8.70 − 5.96).
A26: State | B26: Tariff basis | C26: Effective ₹/kWh
A27: Odisha | B27: EHT, ₹250/kVA, 580/470 paise slabs | C27: ≈ ₹5.96 (cheapest)
A28: Kerala | B28: EHT 220 kV ₹5.55, demand charge estimated | C28: ≈ ₹6.23
A29: Haryana | B29: 132 kV | C29: ≈ ₹7.1
A30: Uttar Pradesh | B30: NIDP HV-2 | C30: ≈ ₹7.41
A31: Telangana | B31: 132 kV | C31: ≈ ₹7.51
A32: Karnataka | B32: HT-2(a) | C32: ≈ ₹7.61
A33: Madhya Pradesh | B33: HV-3 132 kV | C33: ≈ ₹8.2
A34: Tamil Nadu | B34: HT-I | C34: ≈ ₹8.54
A35: Maharashtra | B35: HT-I(A) | C35: ≈ ₹8.7
A38: R10-T03 Factor weights by use case
A39: Source: Report 10 (Part 10 research report) · Method
A40: Note: Weights.
A41: Data basis: Illustrative / framework / author judgement
A42: Used in atlas: Ch 10 weight presets (balanced, AI, interconnection, sustainability).
A43: Used to derive: Use-case rankings.
A44: Factor | B44: Default | C44: AI campus | D44: Interconnect | E44: Sustainability
A45: Power | B45: 25 | C45: 40 | D45: 15 | E45: 20 (RE-access score replaces tariff)
A46: Connectivity | B46: 15 | C46: 5 | D46: 30 | E46: 5
A47: Latency | B47: 10 | C47: 5 | D47: 20 | E47: 5
A48: Water | B48: 15 | C48: 15 | D48: 5 | E48: 30
A49: Climate | B49: 5 | C49: 5 | D49: 0 | E49: 15
A50: Hazards | B50: 10 | C50: 10 | D50: 10 | E50: 10
A51: Land | B51: 5 | C51: 10 | D51: 2 | E51: 5
A52: Policy | B52: 10 | C52: 7 | D52: 5 | E52: 5
A53: Demand/talent | B53: 5 | C53: 3 | D53: 13 | E53: 5
A56: R10-T04 Inter-hub distances and latency
A57: Source: Report 10 (Part 10 research report) · Method
A58: Note: Latency formula. RTT (ms) ≈ 2 × d × 1.4 ÷ 200 = 0.014 × d (km). Inter-hub baselines:
A59: Data basis: Calculated (model output)
A60: Used in atlas: Ch 10 latency formula drawer.
A61: Used to derive: RTT = 0.014 × km.
A62: Route | B62: Distance | C62: RTT
A63: Mumbai–Delhi | B63: 1,150 km | C63: 16.1 ms
A64: Mumbai–Chennai | B64: 1,030 km | C64: 14.4 ms
A65: Mumbai–Bengaluru | B65: 845 km | C65: 11.8 ms
A66: Delhi–Chennai | B66: 1,760 km | C66: 24.6 ms
A67: Delhi–Bengaluru | B67: 1,740 km | C67: 24.4 ms
A68: Chennai–Bengaluru | B68: 290 km | C68: 4.1 ms
A71: R10-T05 Latency table: great-circle km to four hubs and mean RTT
A72: Source: Report 10 (Part 10 research report) · Latency table (great-circle km to Mumbai / Delhi / Chennai / Bengaluru → mean RTT)
A73: Data basis: Calculated (model output)
A74: Used in atlas: Ch 10 latency factor (recomputed in the atlas with haversine).
A75: Used to derive: Latency score per city.
A76: City | B76: M | C76: D | D76: C | E76: B | F76: Mean RTT (ms) | G76: Score
A77: Anantapur | B77: 705 | C77: 1547 | D77: 338 | E77: 190 | F77: 9.7 | G77: 10
A78: Bengaluru / Hoskote | B78: 845 | C78: 1740 | D78: 290 | E78: 0–25 | F78: 10.1–10.2 | G78: 10.0–9.9
A79: Hyderabad | B79: 620 | C79: 1250 | D79: 520 | E79: 500 | F79: 10.1 | G79: 10
A80: Hosur | B80: 850 | C80: 1760 | D80: 260 | E80: 35 | F80: 10.2 | G80: 9.9
A81: Pune | B81: 120 | C81: 1170 | D81: 910 | E81: 735 | F81: 10.3 | G81: 9.9
A82: Sri City | B82: 980 | C82: 1700 | D82: 55 | E82: 250 | F82: 10.4 | G82: 9.8
A83: Navi Mumbai | B83: 15 | C83: 1150 | D83: 1020 | E83: 835 | F83: 10.6 | G83: 9.7
A84: Chennai | B84: 0–1,030 | C84: 1760 | D84: 0 | E84: 290 | F84: 10.8 | G84: 9.6
A85: Nashik | B85: 140 | C85: 1040 | D85: 1040 | E85: 900 | F85: 10.9 | G85: 9.6
A86: Amaravati | B86: 856 | C86: 1385 | D86: 381 | E86: 504 | F86: 10.9 | G86: 9.6
A87: Mysuru | B87: 820 | C87: 1810 | D87: 385 | E87: 125 | F87: 11 | G87: 9.5
A88: Goa (Verna) | B88: 428 | C88: 1508 | D88: 735 | E88: 479 | F88: 11 | G88: 9.4
A89: Warangal | B89: 760 | C89: 1180 | D89: 560 | E89: 640 | F89: 11 | G89: 9.5
A90: Mangaluru | B90: 710 | C90: 1760 | D90: 580 | E90: 300 | F90: 11.7 | G90: 9
A91: Nagpur | B91: 685 | C91: 860 | D91: 925 | E91: 900 | F91: 11.8 | G91: 9
A92: Indore | B92: 510 | C92: 667 | D92: 1167 | E92: 1098 | F92: 12.1 | G92: 8.8
A93: Bhopal | B93: 663 | C93: 594 | D93: 1170 | E93: 1142 | F93: 12.5 | G93: 8.5
A94: Coimbatore | B94: 1000 | C94: 1960 | D94: 430 | E94: 225 | F94: 12.7 | G94: 8.4
A95: Dholera | B95: 360 | C95: 850 | D95: 1330 | E95: 1170 | F95: 13 | G95: 8.2
A96: Ahmedabad / GIFT | B96: 440 | C96: 775 | D96: 1380 | E96: 1230 | F96: 13.4 | G96: 8
... A99: Kochi | B99: 1080 | C99: 2060 | D99: 545 | E99: 355 | F99: 14.1 | G99: 7.5
A100: Jamnagar / Jaipur | B100: 480 / 920 | C100: 950 / 240 | D100: 1,530 / 1,600 | E100: 1,350 / 1,560 | F100: 15.1 | G100: 6.9
A101: Jharsuguda | B101: 1201 | C101: 1022 | D101: 1051 | E101: 1197 | F101: 15.6 | G101: 6.5
A102: Thoothukudi | B102: 1270 | C102: 2200 | D102: 530 | E102: 470 | F102: 15.6 | G102: 6.6
A103: Thiruvananthapuram | B103: 1200 | C103: 2210 | D103: 620 | E103: 490 | F103: 15.8 | G103: 6.5
A104: Jodhpur | B104: 795 | C104: 540 | D104: 1700 | E104: 1570 | F104: 16.1 | G104: 6.3
A105: Delhi / Noida / Gurugram / Greater Noida | B105: 1,130–1,150 | C105: 0–60 | D105: 1,720–1,760 | E105: 1,700–1,740 | F105: 16.2–16.3 | G105: 6.1
A106: Lucknow / Kanpur | B106: 1190 | C106: 420 | D106: 1550 | E106: 1580 | F106: 16.6 | G106: 6
A107: Bhubaneswar | B107: 1365 | C107: 1274 | D107: 996 | E107: 1195 | F107: 16.9 | G107: 5.8
A108: Ranchi | B108: 1380 | C108: 1006 | D108: 1257 | E108: 1410 | F108: 17.7 | G108: 5.3
A109: Patna / Dehradun | B109: 1,457 / 1,350 | C109: 860 / 205 | D109: 1,479 / 1,930 | E109: 1,607 / 1,926 | F109: 18.9 | G109: 4.5
A110: Digha / Kharagpur | B110: 1552 | C110: 1297 | D110: 1213 | E110: 1412 | F110: 19.2 | G110: 4.3
A111: Mohali / Baddi | B111: 1380 | C111: 240 | D111: 1990 | E111: 1960 | F111: 19.5 | G111: 4.2
...

Sheet R11
A1: Report 11 · Forecast to 2035
A2: 28 tables. Source line under each title; "Note" gives the context sentence from the report.
A4: R11-T01 Historical capacity series
A5: Source: Report 11 (Part 11 research report) · 1. Capacity (MW IT): data, three models, comparison, backtest › 1.1 Historical series
A6: Data basis: Mixed: sourced figures plus estimates
A7: Used in atlas: Ch 11 history points on the capacity chart.
A8: Used to derive: Fitted CAGR (27.9%) and logistic rate.
A9: Year-end | B9: Harmonised base series used for fitting (MW IT) | C9: Reported points (source) | D9: Label
A10: 2019 | B10: 375 | C10: 350 (JLL); about 400 (C&W) | D10: E from R
A11: 2020 | B11: 450 | C11: 375 (MeitY, Parliament reply, Mar 2026); 520 (JM Financial via CEEW, broader definition) | D11: E from R
A12: 2021 | B12: 560 | C12: 499 at H1 2021 (JLL); 824 at end-2021 (C&W, colocation stock, inconsistent with C&W's later series) | D12: E from R
A13: 2022 | B13: 720 | C13: 722 (JLL) | D13: R
A14: 2023 | B14: 977 | C14: 977 at H2 2023 (C&W; 258 MW built in 2023, +105% YoY); 950 in FY24 (ICRA) | D14: R
A15: 2024 | B15: 1200 | C15: 1,030 (JLL); about 1,150 in Dec 2024 (ICRA); 1,255 (CBRE) | D15: E from R
A16: H1 2025 | B16: – | C16: 1,280 (C&W); 1,263 in Apr 2025 (Colliers); 1,123 (JLL) | D16: R
A17: 2025 | B17: 1611 | C17: 1,789 − 178 (C&W, derived); about 1,500 (MeitY); about 1.7 GW (CBRE); 387 MW added in 2025 (Rubix) | D17: E from R
A18: H1 2026 | B18: 1789 | C18: C&W: 1,789 across 7 markets, 147 facilities, 33 providers, 14.9% vacancy; JLL: 1,637 MW (2026 Mid-Year Report, June 2026); PIB factsheet (14 Sep 2026): 1.57 GW as of Aug 2026 | D18: R
A19: 2026E | B19: 2000 | C19: CBRE: about 2 GW by end-2026; C&W: Mumbai to exceed 1 GW by end-2026 | D19: E
A22: R11-T02 CAGR model: forward scenarios from 1,611 MW
A23: Source: Report 11 (Part 11 research report) · 1. Capacity (MW IT): data, three models, comparison, backtest › 1.2 Model (a): CAGR, C(t) = C₀(1+g)^t
A24: Note: Forward scenarios from C₀ = 1,611 MW (end-2025) [M]:
A25: Data basis: Calculated (model output)
A26: Used in atlas: Ch 11 CAGR model option.
A27: Used to derive: Capacity path under constant growth.
A28: g | B28: 2027 | C28: 2028 | D28: 2030 | E28: 2033 | F28: 2035
A29: Low 18% | B29: 2243 | C29: 2647 | D29: 3686 | E29: 6055 | F29: 8431
A30: Base 25% | B30: 2517 | C30: 3146 | D30: 4916 | E30: 9602 | F30: 15003
A31: High 32% | B31: 2807 | C31: 3705 | D31: 6456 | E31: 14849 | F31: 25872
A34: R11-T03 Logistic model parameters
A35: Source: Report 11 (Part 11 research report) · 1. Capacity (MW IT): data, three models, comparison, backtest › 1.3 Model (b): logistic S-curve, C(t) = K / (1 + e^(−r(t − t₀)))
A36: Note: t₀ = 2025 + ln(K/1,611 − 1) / r
A37: Data basis: Proxy / estimate
A38: Used in atlas: Ch 11 S-curve sliders (K, r).
A39: Used to derive: Logistic midpoint t₀.
A40: Parameter | B40: Low | C40: Base | D40: High
A41: K (MW) | B41: 12000 | C41: 25000 | D41: 45000
A42: r (/yr) | B42: 0.24 | C42: 0.26 | D42: 0.3
A43: t₀ | B43: 2032.8 | C43: 2035.3 | D43: 2036
A46: R11-T04 Logistic model output (MW)
A47: Source: Report 11 (Part 11 research report) · 1. Capacity (MW IT): data, three models, comparison, backtest › 1.3 Model (b): logistic S-curve, C(t) = K / (1 + e^(−r(t − t₀)))
A48: Note: Logistic output (MW) [M]:
A49: Data basis: Calculated (model output)
A50: Used in atlas: Ch 11 S-curve model option.
A51: Used to derive: Capacity path to 2035.
A52: Year | B52: Low | C52: Base | D52: High
A53: 2026 | B53: 1975 | C53: 2051 | D53: 2146
A54: 2027 | B54: 2403 | C54: 2596 | D54: 2850
A55: 2028 | B55: 2897 | C55: 3266 | D55: 3763
A56: 2029 | B56: 3457 | C56: 4077 | D56: 4936
A57: 2030 | B57: 4076 | C57: 5044 | D57: 6417
A58: 2031 | B58: 4745 | C58: 6171 | D58: 8249
A59: 2032 | B59: 5447 | C59: 7458 | D59: 10465
A60: 2033 | B60: 6166 | C60: 8884 | D60: 13062
A61: 2034 | B61: 6879 | C61: 10425 | D61: 16008
A62: 2035 | B62: 7568 | C62: 12030 | D62: 19215
A65: R11-T05 Forecast conversion evidence (backtest)
A66: Source: Report 11 (Part 11 research report) · 1. Capacity (MW IT): data, three models, comparison, backtest › 1.4 Model (c): pipeline conversion, C(t+1) = C(t) + Σ P_stage(t − L) × c_stage
A67: Note: Conversion evidence:
A68: Data basis: Mixed: sourced figures plus estimates
A69: Used in atlas: Ch 11 haircut KPI (0.58–0.87×).
A70: Used to derive: Delivery haircut on forecasts.
A71: Source and date | B71: Forecast | C71: Outcome | D71: Ratio | E71: Label
A72: JLL H1 2021 update | B72: 499 → 1,008 MW by 2023 (+509) | C72: JLL's 2023 figure was not published in our sources. Interpolated between 722 (2022) and 1,030 (2024) it is about 875; C&W reports 977 | D72: Additions about 0.74; level about 0.87 | E72: E
A73: JLL (about 2023) | B73: +681 MW to 1,318 MW by end-2024 | C73: 1,030 MW (JLL 2024) | D73: Additions 0.58; level 0.78 | E73: R/M
A74: C&W, Feb 2022 | B74: "over 1.0 GW incremental … in various stages of construction, expected to start operations over the next 4–5 years" | C74: About 1,070 MW added from end-2022 to H1 2026 | D74: About 1.0 within 4.5 years | E74: R/M
A75: ICRA, Oct 2024 | B75: 950 MW (FY24) → 2,000–2,100 MW by Mar 2027 | C75: On track on C&W's basis (1,789 at H1 2026); marginal on JLL's basis (1,637 MW at June 2026) | D75: About 0.9–1.0 (provisional) | E75: M
A76: Arizton / ResearchAndMarkets | B76: 3.5 GW by 2030 (Feb 2025), revised to 4.8 GW (Jul 2025) | C76: Forecast inflated by 37% in 5 months | D76: n/a | E76: R
A77: CEEW / Systemiq | B77: "Only about 50% of the USD ~95 bn worth of capital committed … between 2019 and 2025 has a …" (text truncated in source) | C77: Treated as a conversion ceiling for announcements of about 50% | D77: about 0.5 | E77: R (partial)
A80: R11-T06 Pipeline conversion parameters
A81: Source: Report 11 (Part 11 research report) · 1. Capacity (MW IT): data, three models, comparison, backtest › 1.4 Model (c): pipeline conversion, C(t+1) = C(t) + Σ P_stage(t − L) × c_stage
A82: Note: Parameters [E]:
A83: Data basis: Proxy / estimate
A84: Used in atlas: Ch 11 pipeline-conversion sliders.
A85: Used to derive: Expected delivered MW from pipeline.
A86: Stage | B86: Conversion c | C86: Lag L
A87: Under construction | B87: Low 0.85 / Base 0.95 / High 1.0 | C87: 1–2 years
A88: Planned | B88: Low 0.40 / Base 0.60 / High 0.80 | C88: 2–4 years (base 3)
A89: MoU / announced only | B89: 0.2–0.5 | C89: 3–5 years
A92: R11-T07 Pipeline-conversion path to 2030 (MW)
A93: Source: Report 11 (Part 11 research report) · 1. Capacity (MW IT): data, three models, comparison, backtest › 1.4 Model (c): pipeline conversion, C(t+1) = C(t) + Σ P_stage(t − L) × c_stage
A94: Note: High: 1,789 + 509 + 2,681 = 4,979 MW, plus about 1,000 MW of gigawatt-campus phases outside C&W's 7 markets (Visakhapatnam, Jamnagar) [E] = about 6,000 MW.
A95: Data basis: Calculated (model output)
A96: Used in atlas: Ch 11 pipeline model option.
A97: Used to derive: Capacity to 2030.
A98: Path (MW) | B98: 2026 | C98: 2027 | D98: 2028 | E98: 2029 | F98: 2030
A99: Low | B99: 1950 | C99: 2250 | D99: 2650 | E99: 3100 | F99: 3560
A100: Base | B100: 1990 | C100: 2450 | D100: 3050 | E100: 3650 | F100: 4280
A101: High | B101: 2050 | C101: 2800 | D101: 3800 | E101: 4900 | F101: 6000
A104: R11-T08 Integrated capacity path 2026–2035 (MW IT)
A105: Source: Report 11 (Part 11 research report) · 1. Capacity (MW IT): data, three models, comparison, backtest › 1.5 Integrated capacity path
A106: Note: 2031–2035: the logistic model, with the base case trimmed by about 10% to stay consistent with the conversion haircut.
A107: Data basis: Calculated (model output)
A108: Used in atlas: Ch 11 integrated base case (default chart).
A109: Used to derive: Base / low / high capacity path.
A110: MW IT | B110: 2026 | C110: 2027 | D110: 2028 | E110: 2029 | F110: 2030 | G110: 2031 | H110: 2032 | I110: 2033 | J110: 2034 | K110: 2035
A111: Low | B111: 1950 | C111: 2250 | D111: 2650 | E111: 3100 | F111: 3600 | G111: 4200 | H111: 4800 | I111: 5450 | J111: 6100 | K111: 6800
A112: Base | B112: 2000 | C112: 2500 | D112: 3100 | E112: 3850 | F112: 4700 | G112: 5700 | H112: 6850 | I112: 8100 | J112: 9450 | K112: 10800
A113: High | B113: 2100 | C113: 2850 | D113: 3800 | E113: 4950 | F113: 6400 | G113: 8200 | H113: 10300 | I113: 12800 | J113: 15600 | K113: 18800
A116: R11-T09 Published forecasts compared
A117: Source: Report 11 (Part 11 research report) · 1. Capacity (MW IT): data, three models, comparison, backtest › 1.6 Published forecasts compared
...

Sheet R12
A1: Report 12 · Water and energy
A2: 28 tables. Source line under each title; "Note" gives the context sentence from the report.
A4: R12-T01 Water definitions and metrics
A5: Source: Report 12 (Part 12 research report) · 1. Direct (on-site) water › 1.1 Definitions and metrics
A6: Data basis: Source-derived, verified
A7: Used in atlas: Ch 12 definitions; Data register.
A8: Used to derive: Report withdrawal and consumption separately.
A9: Term | B9: Definition | C9: Unit | D9: Label
A10: Withdrawal | B10: Water taken from any source (municipal, groundwater, tanker, STP-treated) | C10: kL, m³ | D10: [Verified: LBNL24; WRI]
A11: Consumption | B11: Withdrawal minus discharge; mostly evaporation and drift | C11: kL | D11: [Verified: LBNL24 — "permanently removed from the immediate water cycle"]
A12: Discharge | B12: Blowdown, RO reject, sanitary sewage returned | C12: kL | D12: [Proxy: water-balance convention]
A13: WUE (site) | B13: Annual site water ÷ annual IT energy. Microsoft: "annual liters of water used for humidification and cooling" ÷ IT kWh | C13: L/kWh_IT | D13: [Verified: MSFT; LBNL24]
A14: WUE (source) | B14: Site WUE plus water used to generate the electricity consumed | C14: L/kWh_IT | D14: [Verified: LBNL24 — "source WUE accounts for the water required to generate the electricity"]
A15: Basis caveat | B15: NTT computes WUE as withdrawal ÷ IT energy; Microsoft's 0.30 is described as a "withdrawal WUE" | C15: — | D15: [Verified: NTT; MSFT blog]
A16: ISO/IEC 30134-9 | B16: International WUE standard (site and source categories) | C16: — | D16: [Proxy: text not reviewed — obtain from ISO/BIS]
A17: EU EED reporting (Delegated Reg. 2024/1364) | B17: Sites ≥500 kW IT report total water input (W_IN, m³) and potable water input (W_IN-POT, m³); first returns due 15 Sep 2024, then 15 May 2025 and yearly | C17: m³ | D17: [Verified: EU24]
A18: EU rating scheme (draft) | B18: A–G energy and water labels auto-generated from 15 Aug 2027; water grade from freshwater intake ÷ IT energy | C18: — | D18: [Verified-secondary: EU24]
A21: R12-T02 Cooling-tower water components and physics
A22: Source: Report 12 (Part 12 research report) · 1. Direct (on-site) water › 1.2 Components and physics
A23: Data basis: Proxy / estimate
A24: Used in atlas: Ch 12 "Inside a cooling tower" calculator.
A25: Used to derive: Tower WUE vs cycles of concentration.
A26: Component | B26: Formula / rule | C26: Low | D26: Typical | E26: High | F26: Unit | G26: Label
A27: Latent heat of vaporisation | B27: h_fg | C27: 2,257 (100 °C) | D27: 2,430 (30 °C) | E27: 2,450 (20 °C) | F27: kJ/kg | G27: [Proxy: steam tables]
A28: Pure-evaporation water per kWh of heat | B28: 3,600 ÷ h_fg | C28: 1.47 | D28: 1.48 | E28: 1.6 | F28: L/kWh_th | G28: [Model]
A29: Latent share of tower heat rejection | B29: f_lat | C29: 0.75 | D29: 0.85 | E29: 0.95 | F29: — | G29: [Proxy: tower practice]
A30: Evaporation | B30: E = Q_rej × f_lat × 3,600/h_fg | C30: 1.1 | D30: 1.26 | E30: 1.5 | F30: L/kWh_th | G30: [Model]
A31: Heat rejected per kWh IT (water-cooled chillers) | B31: 1 + compressor + pump/fan heat | C31: 1.15 | D31: 1.25 | E31: 1.35 | F31: kWh_th/kWh_IT | G31: [Proxy: chiller COP 5–7]
A32: Blowdown | B32: B = E ÷ (CoC − 1) | C32: E/9 (CoC 10) | D32: E/3 (CoC 4) | E32: E/1 (CoC 2, hard water) | F32: L/kWh_th | G32: [Model]
A33: Drift | B33: 0.001–0.005% of circulation (~86 L/kWh_th at ΔT 10 K) | C33: 0.0009 | D33: 0.002 | E33: 0.004 | F33: L/kWh_th | G33: [Model: 3,600/(4.19×10)]
A34: Tower make-up | B34: M = E + B + D | C34: 1.3 | D34: 1.7 | E34: 3 | F34: L/kWh_th | G34: [Model]
A35: Tower-based WUE | B35: M × Q_rej/IT | C35: 1.5 | D35: 2.1 | E35: 3.5 | F35: L/kWh_IT | G35: [Model]; NTT evaporative 1.42–2.93 [Verified: NTT]
A36: Humidification (air-cooled halls) | B36: — | C36: 0 | D36: 0.01 | E36: 0.05 | F36: L/kWh_IT | G36: [Proxy: LBNL24 "occasional humidification"]
A37: RO reject | B37: feed × (1 − recovery); recovery 65–80% | C37: 0.25 | D37: 0.4 | E37: 0.55 | F37: L per L permeate | G37: [Proxy]
A38: Domestic/sanitary | B38: 45 L/person/day × staff | C38: 0.005 | D38: 0.01 | E38: 0.02 | F38: L/kWh_IT at >10 MW | G38: [Proxy: NBC/CPHEEO norms]
A39: Landscaping | B39: 2–5 L/m²/day of green area | C39: — | D39: — | E39: — | F39: — | G39: [Proxy; use STP water]
A40: DG radiator cooling | B40: Closed loop | C40: 0 | D40: ~0 | E40: ~0 | F40: — | G40: [Proxy]
A41: Fire systems | B41: One-time fill plus tests; storage per NBC/TAC | C41: — | D41: — | E41: — | F41: kL storage | G41: [Proxy: NBC Part 4]
A44: R12-T03 Published WUE and water values
A45: Source: Report 12 (Part 12 research report) · 1. Direct (on-site) water › 1.3 Published WUE and water values
A46: Data basis: Source-derived, verified
A47: Used in atlas: Ch 12 power-vs-water chart (fleet dots); Data register verified figures.
A48: Used to derive: Benchmark WUE/PUE.
A49: Entity / scope | B49: Value | C49: Year | D49: Label
A50: US all data centres, average site WUE | B50: ~0.36 L/kWh through 2023; 0.45–0.48 after 2023 | C50: 2023 / 2028 | D50: [Verified: LBNL24]
A51: US direct water consumption | B51: 66 billion L (2023); 21.2 billion L (2014); hyperscale 60–124 billion L in 2028 | C51: — | D51: [Verified: LBNL24]
A52: US hyperscale aggregate median WUE | B52: 0.32 L/kWh (0.40 if adiabatic runs at 0.2) | C52: 2023 | D52: [Verified: LBNL24]
A53: Hyperscale adiabatic systems (self-reported) | B53: 0.1–0.3 L/kWh | C53: — | D53: [Verified: LBNL24]
A54: Microsoft global WUE / PUE | B54: 0.30 / 1.16 (FY24); 0.27 / 1.17 (FY25) | C54: FY24–25 | D54: [Verified: MSFT]
A55: Microsoft Asia-Pacific WUE / PUE | B55: 0.03 / 1.25 (FY24); 0.25 / 1.28 (FY25) | C55: FY24–25 | D55: [Verified: MSFT]
A56: Microsoft zero-water-for-cooling design | B56: Avoids >125 million L/yr per datacenter | C56: from Aug 2024 | D56: [Verified: MSFT blog]
A57: Microsoft India sites | B57: On-site WUE 0.000 L/kWh (dry cooling) in Li et al.'s table | C57: — | D57: [Verified: LI]
A58: Google fleet PUE | B58: 1.09 (2025) | C58: 2025 | D58: [Verified: GOOG25]
A59: Google WUE used in Gemini analysis | B59: 1.15 L/kWh (fleet) | C59: 2024 | D59: [Verified-secondary: MDPI reconstruction of GOOG25]
A60: NTT DATA WUE, whole portfolio | B60: 1.01 / 0.65 / 0.72 L/kWh | C60: FY22 / 23 / 24 | D60: [Verified: NTT]
A61: NTT DATA WUE, evaporative sites | B61: 2.93 / 2.77 / 1.42 L/kWh | C61: FY22 / 23 / 24 | D61: [Verified: NTT]
A62: NTT DATA PUE | B62: 1.40 / 1.38 / 1.38 | C62: FY22 / 23 / 24 | D62: [Verified: NTT]
A63: Equinix global / evaporative sites WUE | B63: 0.91 / 1.41 L/kWh | C63: 2025 | D63: [Verified-secondary: Equinix 2025 report via Wikipedia]
A64: CtrlS total water | B64: 409,037 kL (2023-24) vs 468,330 kL (2022-23); no WUE | C64: — | D64: [Verified: DTE]
A65: Nxtra, CtrlS | B65: No published WUE | C65: 2025 | D65: [Verified: DTE]
A66: Yotta | B66: Claims "extremely low WUE", no number | C66: 2025 | D66: [Verified: DTE]
A67: India sector | B67: DCs ≈ 0.5% of national electricity (2025); ~271 DCs (Jan 2026); a 100 MW hyperscale "can take ~2 million litres of water per day" | C67: 2025–26 | D67: [Verified: CEEW]
A68: India sector share of water | B68: ~0.02–0.03% of national water demand | C68: 2025 | D68: [Verified-secondary: CEEW author in Scroll]
A69: India siting | B69: ~75% of DCs in water-stressed regions; ~25 million L per MW per year | C69: 2026 | D69: [Verified-secondary: DTE Apr 2026 via Substack]
A72: R12-T04 Water per AI query
A73: Source: Report 12 (Part 12 research report) · 1. Direct (on-site) water › 1.4 Water per AI query
A74: Data basis: Mixed: sourced figures plus estimates
A75: Used in atlas: Ch 12 "Water behind one AI prompt" chart.
A76: Used to derive: Per-prompt water with grid water.
A77: Estimate | B77: Energy | C77: Water | D77: Scope | E77: Label
A78: Google Gemini median text prompt (May 2025) | B78: 0.24 Wh | C78: 0.26 mL (0.15 mL narrow method); 0.03 gCO₂e | D78: On-site only | E78: [Verified: GOOG25]
A79: OpenAI average ChatGPT query (Altman, Jun 2025) | B79: 0.34 Wh | C79: ~0.32 mL | D79: Undisclosed method | E79: [Verified-secondary: Towards Data Science]
A80: Li et al., GPT-3 medium request, India | B80: — | C80: 19.7 mL (0 on-site + 19.7 off-site); 25.4 requests per 500 mL; PUE 1.430, EWIF 3.445 L/kWh | D80: On-site + grid | E80: [Verified: LI]
A81: Gemini-like prompt, dry-cooled Indian DC | B81: 0.24 Wh | C81: 0.24×10⁻³ kWh × (0.03 + 3.0) = 0.73 mL | D81: On-site + grid | E81: [Model]
A82: Same, evaporative Indian DC | B82: 0.24 Wh | C82: 0.24×10⁻³ × (2.0 + 3.0) = 1.2 mL | D82: On-site + grid | E82: [Model]
A85: R12-T05 Water intensity of electricity generation
A86: Source: Report 12 (Part 12 research report) · 2. Indirect (off-site) water › 2.1 Water intensity of generation
A87: Data basis: Mixed: sourced figures plus estimates
A88: Used in atlas: Ch 12 "Where grid water comes from" chart.
A89: Used to derive: Water intensity by generation source.
A90: Technology | B90: Consumption | C90: Withdrawal | D90: Label
A91: Indian coal, once-through (legacy) | B91: small | C91: 70–200 m³/MWh (CSE); 80–160 m³/MWh | D91: [Verified: PowerLine/CSE; SD23]
A92: Indian coal, closed-loop towers (actual) | B92: 2.8–3.4 m³/MWh, about twice the world average of 1.2–1.5 | C92: ~4 m³/MWh average (CSE) | D92: [Verified: SD23; PowerLine/CSE]
A93: MoEFCC norm, existing CT plants | B93: ≤3.5 m³/MWh (by 7 Dec 2017) | C93: — | D93: [Verified: MOEF15]
A94: MoEFCC norm, plants after 1 Jan 2017 | B94: 2.5 m³/MWh with ZLD (2015), relaxed to 3.0 m³/MWh in June 2018 | C94: — | D94: [Verified: MOEF15 amendments]
A95: FGD additional consumption | B95: ~0.3 m³/MWh | C95: — | D95: [Verified: PowerLine/CSE]
A96: Coal with air-cooled condenser | B96: 0.45–0.65 m³/MWh | C96: — | D96: [Verified: SD23]
A97: Nuclear with towers (US median) | B97: 672 gal/MWh = 2.54 L/kWh | C97: higher than coal | D97: [Verified: NREL]
A98: Tower-cooled thermal, upper bound | B98: ~1,000 gal/MWh ≈ 3.8 L/kWh | C98: — | D98: [Verified: NREL]
A99: Gas CCGT with tower | B99: ~0.7–0.8 L/kWh | C99: ~1 L/kWh | D99: [Proxy: NREL medians via secondary sources]
A100: Hydro, reservoir evaporation (contested) | B100: ~17 L/kWh gross; NREL excludes hydro "due to the wide range of estimates" | C100: — | D100: [Verified-secondary: NREL caption + citing literature]
A101: Solar PV (cleaning) | B101: <0.19 L/kWh; Indian dry robots lower | C101: — | D101: [Verified-secondary: NREL-derived]
... A103: Coastal seawater once-through plants | B103: Freshwater ≈ 0 | C103: Seawater 70–200 L/kWh | D103: [Proxy: per plant]
A106: R12-T06 Indian grid-average water intensity, FY25
A107: Source: Report 12 (Part 12 research report) · 2. Indirect (off-site) water › 2.2 Indian grid-average water intensity
A108: Note: Generation base for FY2024-25: total 1,824 BU, thermal 1,363 BU (74.7%) [Verified: CREA], and RE 403.64 BU (22.13%, which appears to include large hydro) [Verified: MNRE25]. Nuclear is the residual, about 3%; large hydro about 8% [Proxy: residual allocation].
A109: Data basis: Calculated (model output)
A110: Used in atlas: Ch 12 grid-water chart and calculator default (3.0 L/kWh).
A111: Used to derive: Indian grid water intensity.
A112: Source | B112: Share | C112: Consumption intensity (L/kWh) | D112: Contribution (L/kWh generated)
...

Sheet Atlas R1-R9
A1: Atlas-derived tables for Reports 1–9 (charts and calculators)
A2: 67 tables. Source line under each title; "Note" gives the context sentence from the report.
A4: ATL-T01 Report 1: Five ways to classify a data centre
A5: Source: Atlas Ch 1 (from Report 1)
A6: Data basis: Illustrative / framework / author judgement
A7: Used in atlas: Shown in atlas Ch 1 Types (chart, table or calculator data built from the report).
A8: Used to derive: Same purpose as the matching report table; restated in the form the atlas displays.
A9: Axis | B9: Question It Answers | C9: Main Categories
A10: Business model | B10: Who owns and pays? | C10: Enterprise, retail colo, wholesale colo, hyperscale, managed/cloud, edge
A11: Workload | B11: What runs inside? | C11: General cloud, AI/HPC "AI factories", sovereign/government
A12: Physical form | B12: How is it built? | C12: Traditional, modular/prefab, underground, underwater (experimental)
A13: Reliability | B13: How often can it fail? | C13: Uptime Tier I–IV; ANSI/TIA-942 Rated 1–4
A14: Cooling | B14: How is heat removed? | C14: Air, rear-door, direct-to-chip, immersion (see chapter 3)
A17: ATL-T02 Report 1: Six data-centre business models
A18: Source: Atlas Ch 1 (from Report 1); industry sources
A19: Data basis: Mixed: sourced figures plus estimates
A20: Used in atlas: Shown in atlas Ch 1 Types (chart, table or calculator data built from the report).
A21: Used to derive: Same purpose as the matching report table; restated in the form the atlas displays.
A22: Type | B22: Size | C22: How it works | D22: Cost | E22: Strengths | F22: Weaknesses | G22: Typical users | H22: Direction
A23: Enterprise on-prem | B23: <1–20 MW | C23: An organisation owns and runs its own facility, from a server room to a corporate campus. | D23: All capex on the owner; low utilisation is common; modal rack ~7.5 kW. | E23: Full control, data sovereignty, custom compliance. | F23: Poor scale economics, older plant, hard to upgrade for AI. | G23: Banks, government, defence, hospitals, manufacturers. | H23: Share 56% (2018) → 32% (2026) → 19% (2031).
A24: Retail colocation | B24: 1 rack – 1 MW | C24: Operator leases racks, cages or suites with power, cooling and security; the tenant brings servers. | D24: Monthly rent per rack/kW plus cross-connects; India ~₹10,000–20,000 per kW-month all-in, 1.5–2.5× wholesale. | E24: Capex becomes opex, carrier-neutral interconnection, fast. | F24: Higher per-kW price, contract lock-in. | G24: Enterprises, BFSI, networks, SaaS. | H24: Where Indian banks move from captive rooms.
A25: Wholesale colo / BTS | B25: 10–100+ MW halls | C25: Operator leases whole halls or buildings, often to one hyperscaler on a long lease. | D25: Operator funds the build against an anchor lease; power passed through. India ~₹6,000–7,500/kW-month for 5 MW+. | E25: Speed for hyperscalers, bankable cash flows; best risk-adjusted Indian return (~14–15%). | F25: Tenant concentration, thin margins. | G25: AWS, Microsoft, Google, Meta, AI labs. | H25: Hyperscalers take 60–70% of new Indian colo demand.
A26: Hyperscale self-build | B26: 30 MW – 1 GW+ | C26: Cloud giants design, own and operate their own campuses. | D26: Balance-sheet capex; lowest unit cost; self-build ~13–27% cheaper than leasing in India. | E26: Lowest cost per MW, custom hardware, best PUE (~1.44 for &gt;20 MW sites). | F26: Concentrated power and water draw, local opposition, grid queues. | G26: AWS, Microsoft, Google, Meta, Alibaba, Oracle. | H26: 41% (2024) → 48% (2026) → ~67% (2031).
A27: AI factory / GPU cloud | B27: 50 MW – 5 GW | C27: Facilities built around thousands of networked accelerators for training and inference. | D27: IT dominates: ~₹266 cr/MW of GPUs on a ~₹72.5 cr/MW building. JLL sees 60% lease premiums. | E27: Fast-growing demand; AI ~25% of workloads in 2025, ~50% by 2030 (JLL). | F27: Hardware obsolescence, huge single-site power, utilisation risk. | G27: Neoclouds, hyperscalers, IndiaAI empanelled providers. | H27: IEA: accelerated server power grows ~30% a year.
A28: Edge / micro | B28: 50 kW – 5 MW | C28: Small modular sites near users: telecom exchanges, towers, factories, cities. | D28: Low capex per site, high cost per kW, many sites to run. | E28: Low latency, data reduction, local resilience. | F28: Hard to run at scale, uneven demand, little GPU density. | G28: Telcos (5G), CDNs/OTT, payments, industrial IoT. Nxtra runs 120+ edge sites. | H28: Real but small in MW; a complement, not a core.
A31: ATL-T03 Report 1: Uptime Tier levels
A32: Source: Atlas Ch 1 (from Report 1); Uptime Institute Tier Standard
A33: Data basis: Source-derived (reported, not re-verified)
A34: Used in atlas: Shown in atlas Ch 1 Types (chart, table or calculator data built from the report).
A35: Used to derive: Same purpose as the matching report table; restated in the form the atlas displays.
A36: Tier | B36: Design availability | C36: Downtime a year | D36: Redundancy | E36: Typical use
A37: Tier I | B37: 99.671% | C37: 28.8 h | D37: N, single path | E37: Small business, dev/test
A38: Tier II | B38: 99.741% | C38: 22 h | D38: N+1 components, single path | E38: Non-critical enterprise
A39: Tier III | B39: 99.982% | C39: 1.6 h | D39: N+1, concurrently maintainable | E39: Colocation, cloud, banking production
A40: Tier IV | B40: 99.995% | C40: 26 min | D40: 2N, fault tolerant | E40: Trading, critical health, national systems
A43: ATL-T04 Report 1: Share of global data-centre capacity by owner type (%)
A44: Source: Synergy Research Group (Apr 2026); 2031 is a projection
A45: Data basis: Source-derived (reported, not re-verified)
A46: Used in atlas: Shown in atlas Ch 1 Types (chart, table or calculator data built from the report).
A47: Used to derive: Same purpose as the matching report table; restated in the form the atlas displays.
A48: Year | B48: Hyperscale | C48: Colocation | D48: Enterprise on-prem
A49: 2024 | B49: 41 | C49: 22 | D49: 37
A50: 2025 | B50: 44 | C50: 22 | D50: 34
A51: 2026 | B51: 48 | C51: 20 | D51: 32
A52: 2031 (proj.) | B52: 67 | C52: 14 | D52: 19
A55: ATL-T05 Report 1: India capacity by city, H1 2026 (MW IT)
A56: Source: Cushman & Wakefield India Data Centre H1 2026 Update
A57: Note: City pipeline sums to 3,633 MW; C&W total is 3,860 MW (509 under construction, 3,351 planned).
A58: Data basis: Source-derived (reported, not re-verified)
A59: Used in atlas: Shown in atlas Ch 1 Types (chart, table or calculator data built from the report).
A60: Used to derive: Same purpose as the matching report table; restated in the form the atlas displays.
A61: City | B61: Operational (MW) | C61: Pipeline to 2030 (MW)
A62: Mumbai | B62: 890 | C62: 1726
A63: Hyderabad | B63: 151 | C63: 710
A64: Delhi NCR | B64: 183 | C64: 387
A65: Chennai | B65: 214 | C65: 368
A66: Pune | B66: 133 | C66: 258
A67: Bengaluru | B67: 162 | C67: 100
A68: Kolkata | B68: 22 | C68: 84
A69: Total (7 markets) | B69: 1789 | C69: 3860
A72: ATL-T06 Report 2: Global data-centre electricity (TWh)
A73: Source: IEA, Energy and AI (Apr 2025), base case; 2035 extrapolated
A74: Note: 2030 high case exceeds 1,260 TWh. IEA 2026 update: 485 → 950 TWh.
A75: Data basis: Source-derived (reported, not re-verified)
A76: Used in atlas: Shown in atlas Ch 2 AI vs conventional (chart, table or calculator data built from the report).
A77: Used to derive: Same purpose as the matching report table; restated in the form the atlas displays.
A78: Year | B78: TWh
A79: 2024 | B79: 415
A80: 2030 | B80: 945
A81: 2035 | B81: 1200
A84: ATL-T07 Report 2: Share of facility electricity by use and facility class (%)
A85: Source: Series synthesis from PUE ranges and IEA component shares (estimate)
A86: Data basis: Proxy / estimate
A87: Used in atlas: Shown in atlas Ch 2 AI vs conventional (chart, table or calculator data built from the report).
A88: Used to derive: Same purpose as the matching report table; restated in the form the atlas displays.
A89: Facility class | B89: IT | C89: Cooling | D89: Power losses | E89: Lighting & other
A90: Legacy (PUE ~1.9) | B90: 52 | C90: 35 | D90: 10 | E90: 3
A91: Enterprise/colo (~1.55) | B91: 64 | C91: 27 | D91: 7 | E91: 2
A92: Hyperscale (~1.15) | B92: 88 | C92: 7.5 | D92: 3.5 | E92: 1
A93: AI liquid (~1.2) | B93: 84 | C93: 11 | D93: 4.5 | E93: 0.5
A96: ATL-T08 Report 2: Rack power density by design (kW per rack)
A97: Source: Nvidia specifications and GTC roadmap; industry estimates (Rubin)
A98: Data basis: Proxy / estimate
A99: Used in atlas: Shown in atlas Ch 2 AI vs conventional (chart, table or calculator data built from the report).
A100: Used to derive: Same purpose as the matching report table; restated in the form the atlas displays.
A101: Design point | B101: kW per rack
A102: Enterprise modal | B102: 8
A103: Air practical limit | B103: 20
A104: Active RDHx | B104: 60
A105: GB200/GB300 NVL72 | B105: 132
A106: Vera Rubin | B106: 210
A107: Kyber (2027) | B107: 600
A110: ATL-T09 Report 2: Power-chain losses, grid to chip
A111: Source: Atlas Ch 2 (Report 2); typical industry ranges
A112: Data basis: Proxy / estimate
A113: Used in atlas: Shown in atlas Ch 2 AI vs conventional (chart, table or calculator data built from the report).
A114: Used to derive: Same purpose as the matching report table; restated in the form the atlas displays.
A115: Stage | B115: Typical loss
A116: Transformer | B116: 1–2%
A117: UPS | B117: 2–8%
...

Sheet Simulator
A1: Simulator inputs (Reports 3–9)
A2: 4 tables. Source line under each title; "Note" gives the context sentence from the report.
A4: SIM-T01 Simulator assumptions and evidence
A5: Source: Atlas simulator (Reports 3–7)
A6: Data basis: Mixed: sourced figures plus estimates
A7: Used in atlas: Simulator "Assumptions behind the simulator" table; feeds every simulator output.
A8: Used to derive: Capex, cost per IT-kWh, energy, water, CO₂, MVA and incentives for any design.
A9: Input | B9: Value used | C9: Evidence | D9: Basis
A10: Grid tariffs (energy + demand) | B10: KA ₹6.70 + ₹365/kVA; MH ₹7.27 + ₹560; TN ₹7.50 + ₹608; TG ₹6.65 + ₹500 (FY2025–26 orders) | C10: reported | D10: State commission tariff orders, Report 7
A11: UP and AP tariffs | B11: ₹7.4 and ₹7.2/kWh (typical ₹7–8) | C11: estimate | D11: Not verified in Report 7
A12: Renewable landed cost | B12: ₹5.5–6.2/kWh open access; ≥₹6.4 for 90% hourly clean | C12: estimate | D12: SECI RTC ₹5.25 + charges; group captive ₹4.5–6.5 (Report 7)
A13: Facility capex | B13: Colo ₹56.1, hyperscale ₹39.2, AI ₹72.5 cr/MW before land; cooling adds ₹0–3 cr/MW | C13: model | D13: Report 7 cost stacks
A14: GPU capex | B14: ₹266 cr per MW of IT (~425 GB300-class GPUs/MW) | C14: model | D14: Report 7; GB300 rack price contested at US$3.7–6.5 m
A15: Land | B15: ₹3–20 cr per acre by city; 0.25–0.4 acre/MW | C15: estimate | D15: Report 7 and market reports
A16: Cooling overhead and WUE | B16: Function of design dry and wet bulb; towers ~1.8 L/kWh, adiabatic ~0.4, liquid + dry ~0.03 | C16: model | D16: Reports 3, 4 and 6
A17: Grid carbon | B17: 0.710 tCO₂/MWh for all states | C17: reported | D17: CEA v21; one national grid factor
A18: Power-station water | B18: Karnataka 1.5 L/kWh; other states 2.2 L/kWh | C18: estimate | D18: Reports 4–6
A19: Water price | B19: BWSSB ₹99/kL; ₹80 elsewhere; groundwater ₹20; treated + RO ₹40 | C19: estimate | D19: BWSSB tariff; others assumed
A20: Electricity duty | B20: 7.5% of the energy charge, where waived | C20: estimate | D20: Assumption; duty rates differ by state
... A22: Scarcity weights | B22: Groundwater 1.0, municipal 0.7, treated 0.1, power stations 0.4, × city stress | C22: model | D22: Report 6; illustrative
A25: SIM-T02 Simulator city parameters
A26: Source: Atlas simulator (Reports 3–7)
A27: Data basis: Mixed: sourced figures plus estimates
A28: Used in atlas: Simulator model inputs.
A29: Used to derive: Capex, PUE, WUE and costs for each city and workload in the simulator.
A30: City | B30: State | C30: Design DB (°C) | D30: Design WB (°C) | E30: Land (₹ cr/acre) | F30: Grid energy (₹/kWh) | G30: Demand (₹/kVA-month) | H30: RE landed (₹/kWh) | I30: Power-station water (L/kWh) | J30: Water stress weight | K30: Water price (₹/kL) | L30: Coastal
A31: Bengaluru | B31: Karnataka | C31: 35 | D31: 23 | E31: 8 | F31: 6.7 | G31: 365 | H31: 6.2 | I31: 1.5 | J31: 1 | K31: 99 | L31: no
A32: Mumbai | B32: Maharashtra | C32: 35 | D32: 28 | E32: 20 | F32: 7.27 | G32: 560 | H32: 5.8 | I32: 2.2 | J32: 0.5 | K32: 80 | L32: yes
A33: Chennai | B33: Tamil Nadu | C33: 38 | D33: 29 | E33: 6 | F33: 7.5 | G33: 608 | H33: 5.9 | I33: 2.2 | J33: 0.9 | K33: 80 | L33: yes
A34: Hyderabad | B34: Telangana | C34: 41 | D34: 26 | E34: 8 | F34: 6.65 | G34: 500 | H34: 6.1 | I34: 2.2 | J34: 0.7 | K34: 80 | L34: no
A35: Noida | B35: Uttar Pradesh | C35: 45 | D35: 29 | E35: 10 | F35: 7.4 | G35: 450 | H35: 6 | I35: 2.2 | J35: 0.85 | K35: 80 | L35: no
A36: Vizag | B36: Andhra Pradesh | C36: 36 | D36: 28 | E36: 3 | F36: 7.2 | G36: 475 | H36: 5.5 | I36: 2.2 | J36: 0.6 | K36: 80 | L36: yes
A39: SIM-T03 Simulator workload parameters
A40: Source: Atlas simulator (Report 7)
A41: Data basis: Mixed: sourced figures plus estimates
A42: Used in atlas: Simulator model inputs.
A43: Used to derive: Capex, PUE, WUE and costs for each city and workload in the simulator.
A44: Workload | B44: Facility capex (₹ cr/MW, before land) | C44: Acres per MW | D44: Other opex (₹ cr/MW/yr) | E44: Utilisation (%) | F44: Power losses (PUE share) | G44: Other (PUE share) | H44: GPU capex (₹ cr/MW) | I44: GPUs per MW
A45: Colocation | B45: 56.1 | C45: 0.25 | D45: 2.25 | E45: 70 | F45: 0.1 | G45: 0.03 | H45: — | I45: —
A46: Hyperscale cloud | B46: 39.2 | C46: 0.4 | D46: 1.17 | E46: 75 | F46: 0.08 | G46: 0.02 | H46: — | I46: —
A47: AI training | B47: 72.5 | C47: 0.3 | D47: 3.29 | E47: 80 | F47: 0.08 | G47: 0.02 | H47: 266 | I47: 425
A50: SIM-T04 State incentives modelled in the simulator
A51: Source: State policies (Report 9)
A52: Data basis: Source-derived (reported, not re-verified)
A53: Used in atlas: Simulator incentive line and policy panel.
A54: Used to derive: Incentive value per year and per IT-kWh.
A55: State | B55: ₹1/unit subsidy | C55: Electricity duty waived | D55: One-time bonus (₹ cr) | E55: Note
A56: Karnataka | B56: no | C56: yes | D56: 20 | E56: Electricity-duty exemption, plus ₹20 crore one-time for PUE ≤ 1.20 and reimbursements for WUE and treated water (Sustainable DC Policy 2026–31).
A57: Maharashtra | B57: yes | C57: yes | D57: — | E57: ₹1/unit tariff subsidy and a 20-year duty waiver in green DC parks, conditional on at least 51% renewable power (GR, June 2026).
A58: Tamil Nadu | B58: no | C58: no | D58: — | E58: The 2021 policy lapsed on 31 March 2026. No incentive applies until a successor is notified.
A59: Telangana | B59: no | C59: no | D59: — | E59: A 2016 policy. Large projects get packages negotiated case by case, none of them published, so nothing is modelled here.
A60: Uttar Pradesh | B60: no | C60: yes | D60: — | E60: 10-year electricity-duty waiver, plus a booster for PUE or green certification (DC Policy 2026).
A61: Andhra Pradesh | B61: no | C61: no | D61: — | E61: Industrial tariff; transmission and wheeling relief case by case; stamp-duty and land concessions for mega projects (Policy 4.0).

Sheet Key numbers
A1: Key numbers (all reports)
A2: 1 tables. Source line under each title; "Note" gives the context sentence from the report.
A4: KEY-T01 Key numbers cheat sheet
A5: Source: Atlas Key numbers (all reports)
A6: Data basis: Mixed: sourced figures plus estimates
A7: Used in atlas: Key numbers cheat sheet (searchable list) at the end of the atlas.
A8: Used to derive: Quick reference for the most-used figures; each row names its source.
A9: Figure | B9: Value | C9: Source
A10: Global DC electricity 2024 → 2030 | B10: 415 → 945 TWh | C10: IEA Energy and AI, Apr 2025
A11: Global capacity 2025 → 2030 | B11: ~103 → ~200 GW | C11: JLL, Jan 2026
A12: Hyperscale share of capacity | B12: ~48% (→ 67% by 2031) | C12: Synergy, Apr 2026
A13: India operational capacity | B13: 1,789 MW | C13: Cushman & Wakefield, H1 2026
A14: India pipeline to 2030 | B14: 3,860 MW · US$29.9 bn | C14: Cushman & Wakefield
A15: Mumbai share of India capacity | B15: ~50% (890 MW) | C15: Cushman & Wakefield
A16: Global average PUE | B16: 1.54 | C16: Uptime 2025
A17: Google fleet PUE | B17: 1.09 | C17: Google, 2025
A18: MeitY AI-cloud tender PUE | B18: <1.35 | C18: MeitY, since 2024
A19: Indian leaders' PUE | B19: 1.4–1.5 | C19: SBI, Apr 2026
A20: India grid emission factor | B20: 0.710 tCO₂/MWh | C20: CEA v21, FY25
A21: Karnataka consumption mix | B21: ~0.50 tCO₂/MWh | C21: Series estimate
A22: Evening fossil peak | B22: ~174 GW at 7 pm | C22: Ember, H1 2026
A23: Coal lifecycle carbon | B23: 820 g/kWh (India actual 900–1,100) | C23: IPCC AR5
A24: Indian coal water use | B24: 2.8–4.0+ m³/MWh | C24: CSE / CEA research
A25: Karnataka grid water | B25: ~1.5 L/kWh | C25: Series estimate
A26: Evaporation per kWh of heat | B26: ~1.5 L | C26: Latent heat 2,400 kJ/kg
A27: 50 MW evaporative withdrawal | B27: 1.77 MLD (peak ~2.4) | C27: Report 6 model
A28: BWSSB delivered supply | B28: ~1,935 MLD | C28: Legislative Council, Aug 2026
A29: Bangalore East groundwater stage | B29: ~305% | C29: 2024 assessment
... A51: India subsea bandwidth via Mumbai | B51: ~95% | C51: Series sources
